Workbook

Sheet DashLiveExe
B99: 46059
B100: Total trade | C100: =MAXIFS( 'JOURNAL- NUM'!I:I, 'JOURNAL- NUM'!A:A, $B99 ) -> 2 | D100: Total Point | E100: =SUMIFS( 'JOURNAL- NUM'!M:M, 'JOURNAL- NUM'!A:A, $B99 ) -> -29.95 | F100: Conti trade | G100: =COUNTIFS( 'JOURNAL- NUM'!H:H, "Conti", 'JOURNAL- NUM'!A:A, ">="&$B99, 'JOURNAL- NUM'!A:A, "<"&$B99+1 ) -> 0
B101: Avg Buy | C101: =AVERAGEIFS( 'JOURNAL- NUM'!K:K, 'JOURNAL- NUM'!A:A, $B99 ) -> 115.875 | D101: Total Pat | E101: =SUMIFS( 'JOURNAL- NUM'!V:V, 'JOURNAL- NUM'!A:A, $B99 ) -> -2188.8992 | F101: Reversal Trade | G101: =COUNTIFS( 'JOURNAL- NUM'!H:H, "Reversal", 'JOURNAL- NUM'!A:A, ">="&$B99, 'JOURNAL- NUM'!A:A, "<"&$B99+1 ) -> 0
B102: Avg sell | C102: =AVERAGEIFS( 'JOURNAL- NUM'!L:L, 'JOURNAL- NUM'!A:A, $B99 ) -> 108.3875 | D102: T FC (Tax) | E102: =SUMIFS( 'JOURNAL- NUM'!S:S, 'JOURNAL- NUM'!A:A, $B99 ) -> 160 | F102: Manual Trade | G102: =COUNTIFS( 'JOURNAL- NUM'!H:H, "Manual", 'JOURNAL- NUM'!A:A, ">="&$B99, 'JOURNAL- NUM'!A:A, "<"&$B99+1 ) -> 0
B103: %Retrun | C103: =SUMIFS( 'JOURNAL- NUM'!O:O, 'JOURNAL- NUM'!A:A, $B99 ) -> -0.26602008 | D103: Avg Inv | E103: =AVERAGEIFS( 'JOURNAL- NUM'!N:N, 'JOURNAL- NUM'!A:A, $B99 ) -> 7531.875 | F103: Long trade | G103: =COUNTIFS( 'JOURNAL- NUM'!G:G, "Long", 'JOURNAL- NUM'!A:A, ">="&$B99, 'JOURNAL- NUM'!A:A, "<"&$B99+1 ) -> 0
B104: Lot | C104: =AVERAGEIFS( 'JOURNAL- NUM'!J:J, 'JOURNAL- NUM'!A:A, $B99 )/65 -> 1 | D104: Per Lot Amt | E104: =E101/C104 -> -2188.8992 | F104: Short trade | G104: =COUNTIFS( 'JOURNAL- NUM'!G:G, "Short", 'JOURNAL- NUM'!A:A, ">="&$B99, 'JOURNAL- NUM'!A:A, "<"&$B99+1 ) -> 0
B105: Max Dur | C105: =MAXIFS( 'JOURNAL- NUM'!R:R, 'JOURNAL- NUM'!A:A, $B99 ) -> 0.010393519 | D105: Min Dur | E105: =MINIFS( 'JOURNAL- NUM'!R:R, 'JOURNAL- NUM'!A:A, $B99 ) -> 0.006724537
B108: Life Time Data | G108: ATH Data
B109: Net Pt | C109: =IFERROR(__xludf.DUMMYFUNCTION("LET(col, 'JOURNAL- NUM'!Q:Q, INDEX(col, MAX(FILTER(ROW(col), col<>""""))))"),185.35700000000003) -> 185.357 | D109: Total Gain | E109: =COUNTIF('JOURNAL- NUM'!M:M,">1") -> 26 | G109: Heads | H109: AvgPT | I109: Avg Amt | J109: ATH PT | K109: ATH Amt | L109: Date
B110: Net P/L | C110: =IFERROR(__xludf.DUMMYFUNCTION("LET(col, #REF!, INDEX(col, MAX(FILTER(ROW(col), col<>""""))))"),"#REF!") -> #REF! | D110: Total Loss | E110: =COUNTIF('JOURNAL- NUM'!M:M,"<1") -> 46 | G110: Gain | H110: =LET( valCol, 'JOURNAL- NUM'!M:M, AVERAGEIF(valCol, ">1") ) -> 19.970654 | I110: =LET( valCol, 'JOURNAL- NUM'!U:U, AVERAGEIF(valCol, ">1") ) -> 1892.6025 | J110: =max('JOURNAL- NUM'!M:M) -> 47.65 | K110: =MAX('JOURNAL- NUM'!U:U) -> 6194.5 | L110: {=LET( valCol, 'JOURNAL- NUM'!U:U, dateCol, 'JOURNAL- NUM'!A:A, maxVal, MAX(valCol), INDEX(dateCol, MATCH(maxVal, valCol, 0)) )} -> 46035
B111: Net % | C111: =IFERROR(__xludf.DUMMYFUNCTION("LET(col, 'JOURNAL- NUM'!P:P, INDEX(col, MAX(FILTER(ROW(col), col<>""""))))"),1.669205013912887) -> 1.669205 | D111: Total Trade | E111: =sum(E109:E110) -> 72 | G111: Loss | H111: =LET( valCol, 'JOURNAL- NUM'!M:M, AVERAGEIF(valCol, "<1") ) -> -7.2582609 | I111: =LET( valCol, 'JOURNAL- NUM'!U:U, AVERAGEIF(valCol, "<1") ) -> -817.81304 | J111: =MIN('JOURNAL- NUM'!M:M) -> -24.8 | K111: =MIN('JOURNAL- NUM'!U:U) -> -3224 | L111: {=LET( valCol,'JOURNAL- NUM'!U:U, dateCol,'JOURNAL- NUM'!A:A, minVal, MIN(valCol), INDEX(dateCol, MATCH(minVal, valCol, 0)) )} -> 46049
B112: T. Brokrage | C112: =SUM('JOURNAL- NUM'!S:S) -> 2880 | D112: Accu % | E112: =E109/E111 -> 0.36111111
B113: T. Gov | C113: =SUM('JOURNAL- NUM'!T:T) -> 2375.6207
B114: T.FC | C114: =sum(C112:C113) -> 5255.6207
B116: Str Entry
B117: Str | C117: =OLD!$D$522 -> Conti | D117: =OLD!$D$523 -> Reversal | E117: =OLD!$D$527 -> No Record | F117: =OLD!$D$521 -> FIB ENTRY | G117: =OLD!$D$533 -> Manual | H117: Net
B118: Gain | C118: =LET( amtCol, 'JOURNAL- Disc-Temp'!$C:$C, tagCol, 'JOURNAL- Disc-Temp'!$D:$D, SUMIFS(amtCol, tagCol, "Conti", amtCol, ">0") ) -> #N/A | D118: =LET( amtCol, 'JOURNAL- Disc-Temp'!$C:$C, tagCol, 'JOURNAL- Disc-Temp'!$D:$D, SUMIFS(amtCol, tagCol, "Reversal", amtCol, ">0") ) -> #N/A | E118: =LET( amtCol, 'JOURNAL- Disc-Temp'!$C:$C, tagCol, 'JOURNAL- Disc-Temp'!$D:$D, SUMIFS(amtCol, tagCol, "No Record", amtCol, ">0") ) -> #N/A | F118: =LET( amtCol, 'JOURNAL- Disc-Temp'!$C:$C, tagCol, 'JOURNAL- Disc-Temp'!$D:$D, SUMIFS(amtCol, tagCol, "FIB ENTRY", amtCol, ">0") ) -> #N/A | G118: =LET( amtCol, 'JOURNAL- Disc-Temp'!$C:$C, tagCol, 'JOURNAL- Disc-Temp'!$D:$D, SUMIFS(amtCol, tagCol, "Manual", amtCol, ">0") ) -> #N/A | H118: =SUM(C118:G118) -> #N/A
B119: Loss | C119: =LET( amtCol, 'JOURNAL- Disc-Temp'!C:C, tagCol, 'JOURNAL- Disc-Temp'!D:D, SUMIFS(amtCol, tagCol, "Conti", amtCol, "<0") ) -> #N/A | D119: =LET( amtCol, 'JOURNAL- Disc-Temp'!$C:$C, tagCol, 'JOURNAL- Disc-Temp'!$D:$D, SUMIFS(amtCol, tagCol, "Reversal", amtCol, "<0") ) -> #N/A | E119: =LET( amtCol, 'JOURNAL- Disc-Temp'!$C:$C, tagCol, 'JOURNAL- Disc-Temp'!$D:$D, SUMIFS(amtCol, tagCol, "No Record", amtCol, "<0") ) -> #N/A | F119: =LET( amtCol, 'JOURNAL- Disc-Temp'!$C:$C, tagCol, 'JOURNAL- Disc-Temp'!$D:$D, SUMIFS(amtCol, tagCol, "FIB ENTRY", amtCol, "<0") ) -> #N/A | G119: =LET( amtCol, 'JOURNAL- Disc-Temp'!$C:$C, tagCol, 'JOURNAL- Disc-Temp'!$D:$D, SUMIFS(amtCol, tagCol, "Manual", amtCol, "<0") ) -> #N/A | H119: =SUM(C119:G119) -> #N/A
B120: Sum | C120: =sum(C118:C119) -> #N/A | D120: =sum(D118:D119) -> #N/A | E120: =sum(E118:E119) -> #N/A | F120: =sum(F118:F119) -> #N/A | G120: =sum(G118:G119) -> #N/A | H120: =SUM(C120:G120) -> #N/A
B121: Count | C121: =COUNTIF('JOURNAL- NUM'!H:H, "Conti") -> 25 | D121: =COUNTIF('JOURNAL- NUM'!$H:$H, "Reversal") -> 9 | E121: =COUNTIF('JOURNAL- NUM'!$H:$H, "No Record") -> 8 | F121: =COUNTIF('JOURNAL- NUM'!$H:$H, "FIB ENTRY") -> 2 | G121: =COUNTIF('JOURNAL- NUM'!$H:$H, "Manual") -> 11

Sheet JOURNAL- Disc
A1: Particular | B1: Mon | C1: Tue | D1: Wed | E1: Thu | F1: Fri | G1: Sat | H1: Sun
A2: Date | E2: 1 | F2: 2 | G2: 3 | H2: 4
A3: Link
A4: Amt | E4: -387 | F4: 1375
A5: Obs | F5: - jitni der me soochte ki kyakarna, dusri strategy me boom Order pad gaya!!! - fib ke premium pe entry kar raha tha - koi psycology ka tamasha nahi - jo mai cahta tha wo aaj finally ho raha!!! (64 point ka zone) approx 44% ja return!! - 100 rs ka premium me 2000 - dimag clr bahut zyada info ab process nahi - strike match ka lable sahi !!, simple elegent solution - itna bhadiya, mujhe kuch nahi karna!!!! - hands off approch ho!!, 2/3/5 pe dekh raha tha - ATR baised Trail bana diya !! ema/DEMA,FIB,LL,breakout,PP,Candle , ab to sahii hi hoga!!,Sasta prem, ATM strike, Auto order placement !! sahi hoga mai janta hun kuch anhi,!! profit hoga to bada,loss hoga to chota!! bahut bhadiya, haut bhaut bhaut bhadiya!!
A6: Date | B6: 5 | C6: 6 | D6: 7 | E6: 8 | F6: 9 | G6: 10 | H6: 11
A7: Link | B7: Kal se Lot bhadayenge!!⏰↗️↗️🏃🏻😎 | C7: https://youtu.be/p6MxwE_eP5c?si=D3FJokzw9_tJtr55 | D7: https://youtu.be/L9IgT-EXNzo?si=C8nAXYV4UGoDpR0W | F7: https://youtu.be/L9IgT-EXNzo?si=C8nAXYV4UGoDpR0W
A8: Amt | B8: -249 | C8: -2286 | D8: -3152 | E8: 4927 | F8: 15
A9: Obs | B9: - auto fib me doubt ho raha - LL pe entry, Reversal Algo leak, turant square off !! - prem pe auto fire, samajh aaya ki ye scaleble/predictable nahi hai - long/short auto candle ho gayi - US SAMAY KYA KAR RAHE THEY!!! itna zyada code me nahi define kar sakta, jo hai yahi hai, - lot multiplier add kar diya - entry kun nahi aay!!!, red ke baad turant Green to invalid, visually dikh raha, finally clr!! - 3 min me proper entry aayi!!, par mai pehle hi bhasam ho jaata hun!! - table bhi bana di thi, -index me bol den ki kahan entry,/exit , khud bana diya jo broker nahi dete - sell ke failed order se se test kar raha tha -22 se ye mat samjhe ki chota hai !! - saari hi sahi, har me trade lene ke chakkar me nahi aana | C9: video nahi record hua! | E9: - Pehli baar computer band pe trade - Pehli baar 5000 tak profit dekha! | F9: 500% tarrif dhanmki
A10: Date | B10: 12 | C10: 13 | D10: 14 | E10: 15 | F10: 16 | G10: 17 | H10: 18
A11: Link | B11: https://youtu.be/rEEYsxw6xkg?si=JXSIyk4-8MS2XfF9 | C11: lag raha hai, ab baat ban rahi hai!🧪😀😎🤖 | D11: https://youtu.be/kyoVAyp5s6s?si=JWRWHefJHXene8sv | E11: - | F11: kya se kya ho gaya dekhte dekhte !!😁🎯😎
A12: Amt | B12: 1968 | C12: 1490 | D12: 6101 | E12: - | F12: 4326
A13: Obs | C13: - lekage | D13: - sabhai se baat +3000 ja kar palat aaya | E13: Mumbai me BMC election
A14: Date | B14: 19 | C14: 20 | D14: 21 | E14: 22 | F14: 23 | G14: 24 | H14: 25
A15: Link | C15: https://youtu.be/WBEo5XEM9hA
A16: Amt | B16: -8595 | C16: -667 | D16: -1317 | E16: 2355 | F16: 3451
A17: Obs | C17: -reversal ka lot kam kar diya - continuation ko 2 - pehli baar , confident nahi to size kam_conti me - single candle me 1700 -> seedhe negative! - Algo time se exit kara deta !! - 1.3% index Gira Code - Use Fresh Zone on kar liya - USe auto aur manual Strike Use karna start! | D17: - bahut der tak baitha tha mai!! - feel ki algo late karta hai, maual ke liye kuch banao! -Din bhar light ne tamash kiya, Move miss par Ipad aur mobile pe record Pipleline Clr - 12:30 aur entry nahi mili - jald bazi me 2 min pe li li, dikha ki 2/3 me me DEMA alag alag dikhta hai - bahut desperate ho raha, dil kar raha tha, haath se order punch karo!! - pura din laga entry nahi aayi,par PC pe dekha to kai jagha entry thi Code - Dono me short-Short likh diya to entyr nahi aayi thi | E17: - Introducing Multi TF EQ Curve, and DashBoard - Excel me bhaut heavy forumle banane aa gaye!! | F17: -video jaldi upload kiya kijeye - continuation ki entry, kaafi der baithata fir fata! - ghar nikalna tha - baad me call karte hai,video edit karna , light nahi aa rahi
A18: Date | B18: 26 | C18: 27 | D18: 28 | E18: 29 | F18: 30 | G18: 31 | H18: 1
A19: Amt | B19: - | C19: -3289 | D19: -444 | E19: -711 | F19: 2284
A20: Link | B20: -
A21: Obs | B21: Independence day holiday | C21: - 3 v shape bane -9:28 pe bahut conviction ki manual entry, sahi bhi thi wo - 1:32 fir mann bol raha tha, manual., par nahi, sahi kiya !! - EU deal Sign ho gayi, tab Reversal Alert nahi baja tha!itnaaa fast move aaya tha!!! | D21: - fir lag raha tha , manual le le, test kar raha, tha ki auto SL kahan lagayenge!! Fib/LineVased aaram se entry aayi thi - kal ke loss ke barabar, aaj usse zyada hi le kar jaana hai - 42 min tak baitha tha lag raha tha engulfing, par EMA,Zone,kain to ruke ga!! - +4200 dikha kar palat gaya!!, 2 candle me, bahut bura lag raha tha!! Code - Manual target aur exit ke liye code kiya ! | E21: - 9 Trade Le daale - Aaj sach me kismat aur Algo power ki Gross me profit me they!! - Trump Possible Attack Iran, Lincon Armada -Mere saamne price inc irritattion ki algo me signal nahi, - Tv ke buy/Sell button ko test kar raa - Mind bahut panic, 1-3 ke alert, galti se 3 lot ka order - Ye to easy moeny hai - pagla kar 9 trade le daale - very embarassed | F21: - GoodNotes ka syn Clr -Daily summary, ipad mind maps -BRD start kar diya -organise kar ke Code develop karenge -realise hua ki TV char pe hi sell order -partial lot booking - accha feel aa raha, 3 min pehle alert bajta, to tayyar aur setup karne ka mauka mil jaata | G21: - Silver Gold Crashed!! - Code se hi Sheet me cal, Brokrage/Tax - Jan ki summary - Discriptive, ye calander based view me Observation Record | H21: Budget presnt hoga

Sheet JOURNAL- NUM
A1: Date | B1: Week | C1: unique ID | D1: BUY Time | E1: SELL Time | F1: Strike | G1: L/S | H1: STR Entry | I1: Trade | J1: Qty | K1: BUY | L1: SELL | M1: Pt | N1: Invested | O1: % Return | P1: C% | Q1: C Pt | R1: Dur | S1: {=LET( data, IF( K2:K79="", , LET( buy, K2:K79, sell, L2:L79, qty, J2:J79, brokerage, qty*0+40, stt, (sell*qty)*0.001, exch, (buy*qty + sell*qty)*0.0003503, stamp, (buy*qty)*0.00003, gst, (brokerage + exch + stamp)*0.18, otherCharges, stt + exch + stamp + gst, grossPL, (sell-buy)*qty, netPL, grossPL - (brokerage + otherCharges), HSTACK(brokerage, otherCharges, grossPL, netPL) ) ), VSTACK( {"Brokerage","Other Charges","Gross P/L","Net P/L"}, IFERROR(data,"") ) )} -> Brokerage | T1: Other Charges | U1: Gross P/L | V1: Net P/L | W1: Total FC | X1: TF | Y1: High | Z1: Low | AA1: Runn | AB1: DD
A2: 46023 | B2: W1 | C2: =TEXTJOIN( " | ", TRUE, TEXT(A2,"ddd dd - mmm"), TEXT(D2,"hh:mm"), G2, TEXT(I2,"0") ) -> Thu 01 - Jan | 14:50 | No Record | 1 | D2: 0.61834491 | E2: 0.6250463 | F2: NIFTY 06 JAN 26150 PUT | G2: No Record | H2: No Record | I2: 1 | J2: 65 | K2: 69.15 | L2: 65.05 | M2: =L2-K2 -> -4.1 | N2: =K2*J2 -> 4494.75 | O2: =M2/K2 -> -0.059291396 | P2: =O2 -> -0.059291396 | Q2: =M2 -> -4.1 | R2: =E2-D2 -> 0.0067013889 | S2: 40 | T2: 15.193051 | U2: -266.5 | V2: -321.69305 | W2: =T2+S2 -> 55.193051
A3: 46023 | B3: W1 | C3: =TEXTJOIN( " | ", TRUE, TEXT(A3,"ddd dd - mmm"), TEXT(D3,"hh:mm"), G3, TEXT(I3,"0") ) -> Thu 01 - Jan | 15:15 | No Record | 2 | D3: 0.63561343 | E3: 0.63710648 | F3: NIFTY 06 JAN 26150 PUT | G3: No Record | H3: No Record | I3: 2 | J3: 65 | K3: 71.6 | L3: 71.45 | M3: =L3-K3 -> -0.15 | N3: =K3*J3 -> 4654 | O3: =M3/K3 -> -0.0020949721 | P3: =O3+P2 -> -0.061386368 | Q3: =M3+Q2 -> -4.25 | R3: =E3-D3 -> 0.0014930556 | S3: 40 | T3: 15.85247 | U3: -9.75 | V3: -65.60247 | W3: =T3+S3 -> 55.85247
A4: 46024 | B4: W1 | C4: =TEXTJOIN( " | ", TRUE, TEXT(A4,"ddd dd - mmm"), TEXT(D4,"hh:mm"), G4, TEXT(I4,"0") ) -> Fri 02 - Jan | 09:17 | Short | 1 | D4: 0.3868287 | E4: 0.3909838 | F4: NIFTY 06 JAN 26200 PUT | G4: Short | H4: FIB ENTRY | I4: 1 | J4: 65 | K4: 71.75 | L4: 65.35 | M4: =L4-K4 -> -6.4 | N4: =K4*J4 -> 4663.75 | O4: =M4/K4 -> -0.089198606 | P4: =O4 -> -0.089198606 | Q4: =M4+Q3 -> -10.65 | R4: =E4-D4 -> 0.0041550926 | S4: 40 | T4: 15.296451 | U4: -416 | V4: -471.29645 | W4: =T4+S4 -> 55.296451
A5: 46024 | B5: W1 | C5: =TEXTJOIN( " | ", TRUE, TEXT(A5,"ddd dd - mmm"), TEXT(D5,"hh:mm"), G5, TEXT(I5,"0") ) -> Fri 02 - Jan | 09:25 | Long | 2 | D5: 0.39238426 | E5: 0.40611111 | F5: NIFTY 06 JAN 26200 CALL | G5: Long | H5: Conti | I5: 2 | J5: 65 | K5: 77.3 | L5: 111.6 | M5: =L5-K5 -> 34.3 | N5: =K5*J5 -> 5024.5 | O5: =M5/K5 -> 0.44372574 | P5: =O5+P4 -> 0.35452714 | Q5: =M5+Q4 -> 23.65 | R5: =E5-D5 -> 0.013726852 | S5: 40 | T5: 19.707234 | U5: 2229.5 | V5: 2169.7928 | W5: =T5+S5 -> 59.707234
A6: 46024 | B6: W1 | C6: =TEXTJOIN( " | ", TRUE, TEXT(A6,"ddd dd - mmm"), TEXT(D6,"hh:mm"), G6, TEXT(I6,"0") ) -> Fri 02 - Jan | 10:57 | Short | 3 | D6: 0.45628472 | E6: 0.47503472 | F6: NIFTY 06 JAN 26250 PUT | G6: Short | H6: Reversal | I6: 3 | J6: 65 | K6: 59.75 | L6: 55.6 | M6: =L6-K6 -> -4.15 | N6: =K6*J6 -> 3883.75 | O6: =M6/K6 -> -0.069456067 | P6: =O6+P5 -> 0.28507107 | Q6: =M6+Q5 -> 19.5 | R6: =E6-D6 -> 0.01875 | S6: 40 | T6: 14.05071 | U6: -269.75 | V6: -323.80071 | W6: =T6+S6 -> 54.05071
A7: 46027 | B7: W2 | C7: =TEXTJOIN( " | ", TRUE, TEXT(A7,"ddd dd - mmm"), TEXT(D7,"hh:mm"), G7, TEXT(I7,"0") ) -> Mon 05 - Jan | 09:36 | Short | 1 | D7: 0.40003472 | E7: 0.40038194 | F7: NIFTY 06 JAN 26300 PUT | G7: Short | H7: Reversal | I7: 1 | J7: 65 | K7: 71.35 | L7: 74.9 | M7: =L7-K7 -> 3.55 | N7: =K7*J7 -> 4637.75 | O7: =M7/K7 -> 0.04975473 | P7: =O7+P6 -> 0.3348258 | Q7: =M7+Q6 -> 23.05 | R7: =E7-D7 -> 0.00034722222 | S7: 40 | T7: 16.162123 | U7: 230.75 | V7: 174.58788 | W7: =T7+S7 -> 56.162123
A8: 46027 | B8: W2 | C8: =TEXTJOIN( " | ", TRUE, TEXT(A8,"ddd dd - mmm"), TEXT(D8,"hh:mm"), G8, TEXT(I8,"0") ) -> Mon 05 - Jan | 09:50 | Long | 2 | D8: 0.40975694 | E8: 0.41443287 | F8: NIFTY 06 JAN 26300 CALL | G8: Long | H8: FIB ENTRY | I8: 2 | J8: 65 | K8: 61.8 | L8: 72.65 | M8: =L8-K8 -> 10.85 | N8: =K8*J8 -> 4017 | O8: =M8/K8 -> 0.17556634 | P8: =O8+P7 -> 0.51039214 | Q8: =M8+Q7 -> 33.9 | R8: =E8-D8 -> 0.0046759259 | S8: 40 | T8: 15.676856 | U8: 705.25 | V8: 649.57314 | W8: =T8+S8 -> 55.676856
A9: 46027 | B9: W2 | C9: =TEXTJOIN( " | ", TRUE, TEXT(A9,"ddd dd - mmm"), TEXT(D9,"hh:mm"), G9, TEXT(I9,"0") ) -> Mon 05 - Jan | 10:12 | Short | 3 | D9: 0.42501157 | E9: 0.42503472 | F9: NIFTY 06 JAN 26300 PUT | G9: Short | H9: Reversal | I9: 3 | J9: 65 | K9: 42.75 | L9: 42.7 | M9: =L9-K9 -> -0.05 | N9: =K9*J9 -> 2778.75 | O9: =M9/K9 -> -0.0011695906 | P9: =O9+P8 -> 0.50922255 | Q9: =M9+Q8 -> 33.85 | R9: =E9-D9 -> 2.3148148e-05 | S9: 40 | T9: 12.369739 | U9: -3.25 | V9: -55.619739 | W9: =T9+S9 -> 52.369739
A10: 46027 | B10: W2 | C10: =TEXTJOIN( " | ", TRUE, TEXT(A10,"ddd dd - mmm"), TEXT(D10,"hh:mm"), G10, TEXT(I10,"0") ) -> Mon 05 - Jan | 10:43 | Short | 4 | D10: 0.44653935 | E10: 0.44863426 | F10: NIFTY 06 JAN 26350 PUT | G10: Short | H10: No Record | I10: 4 | J10: 65 | K10: 60.75 | L10: 53.1 | M10: =L10-K10 -> -7.65 | N10: =K10*J10 -> 3948.75 | O10: =M10/K10 -> -0.12592593 | P10: =O10+P9 -> 0.38329663 | Q10: =M10+Q9 -> 26.2 | R10: =E10-D10 -> 0.0020949074 | S10: 40 | T10: 13.850209 | U10: -497.25 | V10: -551.10021 | W10: =T10+S10 -> 53.850209
A11: 46027 | B11: W2 | C11: =TEXTJOIN( " | ", TRUE, TEXT(A11,"ddd dd - mmm"), TEXT(D11,"hh:mm"), G11, TEXT(I11,"0") ) -> Mon 05 - Jan | 11:00 | Short | 5 | D11: 0.45840278 | E11: 0.46045139 | F11: NIFTY 06 JAN 26350 PUT | G11: Short | H11: No Record | I11: 5 | J11: 65 | K11: 54.9 | L11: 48.55 | M11: =L11-K11 -> -6.35 | N11: =K11*J11 -> 3568.5 | O11: =M11/K11 -> -0.11566485 | P11: =O11+P10 -> 0.26763178 | Q11: =M11+Q10 -> 19.85 | R11: =E11-D11 -> 0.0020486111 | S11: 40 | T11: 13.261571 | U11: -412.75 | V11: -466.01157 | W11: =T11+S11 -> 53.261571
A12: 46028 | B12: W2 | C12: =TEXTJOIN( " | ", TRUE, TEXT(A12,"ddd dd - mmm"), TEXT(D12,"hh:mm"), G12, TEXT(I12,"0") ) -> Tue 06 - Jan | 10:22 | Short | 1 | D12: 0.43229167 | E12: 0.43930556 | F12: NIFTY 13 JAN 26250 PUT | G12: Short | H12: No Record | I12: 1 | J12: 65 | K12: 108.45 | L12: 105.65 | M12: =L12-K12 -> -2.8 | N12: =K12*J12 -> 7049.25 | O12: =M12/K12 -> -0.025818349 | P12: =O12+P11 -> 0.24181343 | Q12: =M12+Q11 -> 17.05 | R12: =E12-D12 -> 0.0070138889 | S12: 40 | T12: 20.069234 | U12: -182 | V12: -242.06923 | W12: =T12+S12 -> 60.069234
A13: 46028 | B13: W2 | C13: =TEXTJOIN( " | ", TRUE, TEXT(A13,"ddd dd - mmm"), TEXT(D13,"hh:mm"), G13, TEXT(I13,"0") ) -> Tue 06 - Jan | 10:25 | Short | 2 | D13: 0.4340625 | E13: 0.43930556 | F13: NIFTY 13 JAN 26250 PUT | G13: Short | H13: No Record | I13: 2 | J13: 130 | K13: 112.85 | L13: 105.65 | M13: =L13-K13 -> -7.2 | N13: =K13*J13 -> 14670.5 | O13: =M13/K13 -> -0.063801506 | P13: =O13+P12 -> 0.17801193 | Q13: =M13+Q12 -> 9.85 | R13: =E13-D13 -> 0.0052430556 | S13: 40 | T13: 33.195156 | U13: -936 | V13: -1009.1952 | W13: =T13+S13 -> 73.195156
A14: 46028 | B14: W2 | C14: =TEXTJOIN( " | ", TRUE, TEXT(A14,"ddd dd - mmm"), TEXT(D14,"hh:mm"), G14, TEXT(I14,"0") ) -> Tue 06 - Jan | 10:36 | Short | 3 | D14: 0.44200231 | E14: 0.44592593 | F14: NIFTY 13 JAN 26250 PUT | G14: Short | H14: No Record | I14: 3 | J14: 65 | K14: 113.05 | L14: 114.95 | M14: =L14-K14 -> 1.9 | N14: =K14*J14 -> 7348.25 | O14: =M14/K14 -> 0.016806723 | P14: =O14+P13 -> 0.19481865 | Q14: =M14+Q13 -> 11.75 | R14: =E14-D14 -> 0.0039236111 | S14: 40 | T14: 21.057784 | U14: 123.5 | V14: 62.442216 | W14: =T14+S14 -> 61.057784
A15: 46028 | B15: W2 | C15: =TEXTJOIN( " | ", TRUE, TEXT(A15,"ddd dd - mmm"), TEXT(D15,"hh:mm"), G15, TEXT(I15,"0") ) -> Tue 06 - Jan | 10:55 | Long | 4 | D15: 0.45488426 | E15: 0.45818287 | F15: NIFTY 13 JAN 26250 CALL | G15: Long | H15: No Record | I15: 4 | J15: 130 | K15: 127.5 | L15: 119.65 | M15: =L15-K15 -> -7.85 | N15: =K15*J15 -> 16575 | O15: =M15/K15 -> -0.061568627 | P15: =O15+P14 -> 0.13325002 | Q15: =M15+Q14 -> 3.9 | R15: =E15-D15 -> 0.0032986111 | S15: 40 | T15: 36.622112 | U15: -1020.5 | V15: -1097.1221 | W15: =T15+S15 -> 76.622112
A16: 46029 | B16: W2 | C16: =TEXTJOIN( " | ", TRUE, TEXT(A16,"ddd dd - mmm"), TEXT(D16,"hh:mm"), G16, TEXT(I16,"0") ) -> Wed 07 - Jan | 10:04 | Short | 1 | D16: 0.42010417 | E16: 0.4272338 | F16: NIFTY 13 JAN 26150 PUT | G16: Short | H16: Manual | I16: 1 | J16: 130 | K16: 93.45 | L16: 77.7 | M16: =L16-K16 -> -15.75 | N16: =K16*J16 -> 12148.5 | O16: =M16/K16 -> -0.16853933 | P16: =O16+P15 -> -0.035289304 | Q16: =M16+Q15 -> -11.85 | R16: =E16-D16 -> 0.0071296296 | S16: 40 | T16: 26.927977 | U16: -2047.5 | V16: -2114.428 | W16: =T16+S16 -> 66.927977
... A41: 46044 | B41: W4 | C41: =TEXTJOIN( " | ", TRUE, TEXT(A41,"ddd dd - mmm"), TEXT(D41,"hh:mm"), G41, TEXT(I41,"0") ) -> Thu 22 - Jan | 09:58 | Short | 1 | D41: 0.41548611 | E41: 0.43947917 | F41: NIFTY 27 JAN 25150 PUT | G41: Short | H41: Reversal | I41: 1 | J41: 65 | K41: 52.8 | L41: 89.9 | M41: =L41-K41 -> 37.1 | N41: =K41*J41 -> 3432 | O41: =M41/K41 -> 0.70265152 | P41: =O41+P40 -> 1.4424286 | Q41: =M41+Q40 -> 130.357 | R41: =E41-D41 -> 0.023993056 | S41: 40 | T41: 16.999058 | U41: 2411.5 | V41: 2354.5009 | W41: =T41+S41 -> 56.999058
A42: 46045 | B42: W4 | C42: =TEXTJOIN( " | ", TRUE, TEXT(A42,"ddd dd - mmm"), TEXT(D42,"hh:mm"), G42, TEXT(I42,"0") ) -> Fri 23 - Jan | 10:57 | Short | 1 | D42: 0.4562963 | E42: 0.49017361 | F42: NIFTY 27 JAN 25250 PUT | G42: Short | H42: Conti | I42: 1 | J42: 130 | K42: 83 | L42: 110.1 | M42: =L42-K42 -> 27.1 | N42: =K42*J42 -> 10790 | O42: =M42/K42 -> 0.32650602 | P42: =O42+P41 -> 1.7689346 | Q42: =M42+Q41 -> 157.457 | R42: =E42-D42 -> 0.033877315 | S42: 40 | T42: 32.271391 | U42: 3523 | V42: 3450.7286 | W42: =T42+S42 -> 72.271391 | X42: 3
A43: 46049 | B43: W4 | C43: =TEXTJOIN( " | ", TRUE, TEXT(A43,"ddd dd - mmm"), TEXT(D43,"hh:mm"), G43, TEXT(I43,"0") ) -> Tue 27 - Jan | 12:06 | Long | 1 | D43: 0.50418981 | E43: 0.52107639 | F43: NIFTY 27 JAN 25100 CALL | G43: Long | H43: Conti | I43: 1 | J43: 130 | K43: 90.3 | L43: 65.5 | M43: =L43-K43 -> -24.8 | N43: =K43*J43 -> 11739 | O43: =M43/K43 -> -0.27464009 | P43: =O43+P42 -> 1.4942945 | Q43: =M43+Q42 -> 132.657 | R43: =E43-D43 -> 0.016886574 | S43: 40 | T43: 24.502633 | U43: -3224 | V43: -3288.5026 | W43: =T43+S43 -> 64.502633 | X43: 3
A44: 46050 | B44: W4 | C44: =TEXTJOIN( " | ", TRUE, TEXT(A44,"ddd dd - mmm"), TEXT(D44,"hh:mm"), G44, TEXT(I44,"0") ) -> Wed 28 - Jan | 10:54 | Long | 1 | D44: 0.45418981 | E44: 0.48878472 | F44: NIFTY 03 FEB 25300 CALL | G44: Long | H44: Conti | I44: 1 | J44: 130 | K44: 243.9 | L44: 241.3 | M44: =L44-K44 -> -2.6 | N44: =K44*J44 -> 31707 | O44: =M44/K44 -> -0.010660107 | P44: =O44+P43 -> 1.4836344 | Q44: =M44+Q43 -> 130.057 | R44: =E44-D44 -> 0.034594907 | S44: 40 | T44: 65.764145 | U44: -338 | V44: -443.76414 | W44: =T44+S44 -> 105.76414 | X44: 3 | Y44: 277 | Z44: 235 | AA44: =Y44-K44 -> 33.1 | AB44: =Z44-K44 -> -8.9
A45: 46051 | B45: W4 | C45: =TEXTJOIN( " | ", TRUE, TEXT(A45,"ddd dd - mmm"), TEXT(D45,"hh:mm"), G45, TEXT(I45,"0") ) -> Thu 29 - Jan | 10:02 | Short | 1 | D45: 0.41857639 | E45: 0.42101852 | F45: NIFTY 03 FEB 25050 CALL | G45: Short | H45: Manual | I45: 1 | J45: 65 | K45: 291.35 | L45: 293.2 | M45: =L45-K45 -> 1.85 | N45: =K45*J45 -> 18937.75 | O45: =M45/K45 -> 0.0063497512 | P45: =O45+P44 -> 1.4899842 | Q45: =M45+Q44 -> 131.907 | R45: =E45-D45 -> 0.0024421296 | S45: 40 | T45: 42.634092 | U45: 120.25 | V45: 37.615908 | W45: =T45+S45 -> 82.634092
A46: 46051 | B46: W4 | C46: =TEXTJOIN( " | ", TRUE, TEXT(A46,"ddd dd - mmm"), TEXT(D46,"hh:mm"), G46, TEXT(I46,"0") ) -> Thu 29 - Jan | 10:07 | Short | 2 | D46: 0.42155093 | E46: 0.42229167 | F46: NIFTY 03 FEB 25200 PUT | G46: Short | H46: Manual | I46: 2 | J46: 195 | K46: 207.6 | L46: 205.2 | M46: =L46-K46 -> -2.4 | N46: =K46*J46 -> 40482 | O46: =M46/K46 -> -0.011560694 | P46: =O46+P45 -> 1.4784235 | Q46: =M46+Q45 -> 129.507 | R46: =E46-D46 -> 0.00074074074 | S46: 40 | T46: 81.920406 | U46: -468 | V46: -589.92041 | W46: =T46+S46 -> 121.92041
A47: 46051 | B47: W4 | C47: =TEXTJOIN( " | ", TRUE, TEXT(A47,"ddd dd - mmm"), TEXT(D47,"hh:mm"), G47, TEXT(I47,"0") ) -> Thu 29 - Jan | 11:25 | Short | 3 | D47: 0.47579861 | E47: 0.47672454 | F47: NIFTY 03 FEB 25450 PUT | G47: Short | H47: Manual | I47: 3 | J47: 65 | K47: 273.1 | L47: 282.4 | M47: =L47-K47 -> 9.3 | N47: =K47*J47 -> 17751.5 | O47: =M47/K47 -> 0.03405346 | P47: =O47+P46 -> 1.5124769 | Q47: =M47+Q46 -> 138.807 | R47: =E47-D47 -> 0.00092592593 | S47: 40 | T47: 41.109583 | U47: 604.5 | V47: 523.39042 | W47: =T47+S47 -> 81.109583
A48: 46051 | B48: W4 | C48: =TEXTJOIN( " | ", TRUE, TEXT(A48,"ddd dd - mmm"), TEXT(D48,"hh:mm"), G48, TEXT(I48,"0") ) -> Thu 29 - Jan | 11:37 | Short | 4 | D48: 0.48471065 | E48: 0.48747685 | F48: NIFTY 03 FEB 25450 PUT | G48: Short | H48: Manual | I48: 4 | J48: 65 | K48: 290.65 | L48: 286.85 | M48: =L48-K48 -> -3.8 | N48: =K48*J48 -> 18892.25 | O48: =M48/K48 -> -0.013074144 | P48: =O48+P47 -> 1.4994028 | Q48: =M48+Q47 -> 135.007 | R48: =E48-D48 -> 0.0027662037 | S48: 40 | T48: 42.030311 | U48: -247 | V48: -329.03031 | W48: =T48+S48 -> 82.030311
A49: 46051 | B49: W4 | C49: =TEXTJOIN( " | ", TRUE, TEXT(A49,"ddd dd - mmm"), TEXT(D49,"hh:mm"), G49, TEXT(I49,"0") ) -> Thu 29 - Jan | 11:45 | Short | 5 | D49: 0.48993056 | E49: 0.49181713 | F49: NIFTY 03 FEB 25450 PUT | G49: Short | H49: Manual | I49: 5 | J49: 65 | K49: 289.1 | L49: 284.65 | M49: =L49-K49 -> -4.45 | N49: =K49*J49 -> 18791.5 | O49: =M49/K49 -> -0.015392598 | P49: =O49+P48 -> 1.4840102 | Q49: =M49+Q48 -> 130.557 | R49: =E49-D49 -> 0.0018865741 | S49: 40 | T49: 41.78299 | U49: -289.25 | V49: -371.03299 | W49: =T49+S49 -> 81.78299
A50: 46051 | B50: W4 | C50: =TEXTJOIN( " | ", TRUE, TEXT(A50,"ddd dd - mmm"), TEXT(D50,"hh:mm"), G50, TEXT(I50,"0") ) -> Thu 29 - Jan | 11:48 | Short | 6 | D50: 0.49219907 | E50: 0.49331019 | F50: NIFTY 03 FEB 25450 PUT | G50: Short | H50: Manual | I50: 6 | J50: 65 | K50: 291.05 | L50: 282 | M50: =L50-K50 -> -9.05 | N50: =K50*J50 -> 18918.25 | O50: =M50/K50 -> -0.031094314 | P50: =O50+P49 -> 1.4529159 | Q50: =M50+Q49 -> 121.507 | R50: =E50-D50 -> 0.0011111111 | S50: 40 | T50: 41.596419 | U50: -588.25 | V50: -669.84642 | W50: =T50+S50 -> 81.596419
A51: 46051 | B51: W4 | C51: =TEXTJOIN( " | ", TRUE, TEXT(A51,"ddd dd - mmm"), TEXT(D51,"hh:mm"), G51, TEXT(I51,"0") ) -> Thu 29 - Jan | 11:52 | Short | 7 | D51: 0.49459491 | E51: 0.50231481 | F51: NIFTY 03 FEB 25400 PUT | G51: Short | H51: Manual | I51: 7 | J51: 65 | K51: 257.1 | L51: 247.1 | M51: =L51-K51 -> -10 | N51: =K51*J51 -> 16711.5 | O51: =M51/K51 -> -0.038895371 | P51: =O51+P50 -> 1.4140205 | Q51: =M51+Q50 -> 111.507 | R51: =E51-D51 -> 0.0077199074 | S51: 40 | T51: 37.399938 | U51: -650 | V51: -727.39994 | W51: =T51+S51 -> 77.399938
A52: 46051 | B52: W4 | C52: =TEXTJOIN( " | ", TRUE, TEXT(A52,"ddd dd - mmm"), TEXT(D52,"hh:mm"), G52, TEXT(I52,"0") ) -> Thu 29 - Jan | 12:12 | Long | 8 | D52: 0.50836806 | E52: 0.52005787 | F52: NIFTY 03 FEB 25300 CALL | G52: Long | H52: Conti | I52: 8 | J52: 130 | K52: 186.6 | L52: 186.5 | M52: =L52-K52 -> -0.1 | N52: =K52*J52 -> 24258 | O52: =M52/K52 -> -0.00053590568 | P52: =O52+P51 -> 1.4134846 | Q52: =M52+Q51 -> 111.407 | R52: =E52-D52 -> 0.011689815 | S52: 40 | T52: 52.352642 | U52: -13 | V52: -105.35264 | W52: =T52+S52 -> 92.352642
A53: 46051 | B53: W4 | C53: =TEXTJOIN( " | ", TRUE, TEXT(A53,"ddd dd - mmm"), TEXT(D53,"hh:mm"), G53, TEXT(I53,"0") ) -> Thu 29 - Jan | 12:51 | Long | 9 | D53: 0.53545139 | E53: 0.54751157 | F53: NIFTY 03 FEB 25400 CALL | G53: Long | H53: Reversal | I53: 9 | J53: 65 | K53: 161.85 | L53: 186.3 | M53: =L53-K53 -> 24.45 | N53: =K53*J53 -> 10520.25 | O53: =M53/K53 -> 0.1510658 | P53: =O53+P52 -> 1.5645504 | Q53: =M53+Q52 -> 135.857 | R53: =E53-D53 -> 0.012060185 | S53: 40 | T53: 29.036015 | U53: 1589.25 | V53: 1520.214 | W53: =T53+S53 -> 69.036015
A54: 46052 | B54: W4 | C54: =TEXTJOIN( " | ", TRUE, TEXT(A54,"ddd dd - mmm"), TEXT(D54,"hh:mm"), G54, TEXT(I54,"0") ) -> Fri 30 - Jan | 11:09 | Short | 1 | D54: 0.46461806 | E54: 0.47068287 | F54: NIFTY 03 FEB 25300 PUT | G54: Short | H54: Conti | I54: 1 | J54: 65 | K54: 204.6 | L54: 220.5 | M54: =L54-K54 -> 15.9 | N54: =K54*J54 -> 13299 | O54: =M54/K54 -> 0.07771261 | P54: =O54+P53 -> 1.642263 | Q54: =M54+Q53 -> 151.757 | R54: =E54-D54 -> 0.0060648148 | S54: 40 | T54: 33.424876 | U54: 1033.5 | V54: 960.07512 | W54: =T54+S54 -> 73.424876
A55: 46052 | B55: W4 | C55: =TEXTJOIN( " | ", TRUE, TEXT(A55,"ddd dd - mmm"), TEXT(D55,"hh:mm"), G55, TEXT(I55,"0") ) -> Fri 30 - Jan | 11:09 | Short | 1 | D55: 0.46461806 | E55: 0.47744213 | F55: NIFTY 03 FEB 25300 PUT | G55: Short | H55: Conti | I55: 1 | J55: 65 | K55: 204.6 | L55: 201.1 | M55: =L55-K55 -> -3.5 | N55: =K55*J55 -> 13299 | O55: =M55/K55 -> -0.017106549 | P55: =O55+P54 -> 1.6251565 | Q55: =M55+Q54 -> 148.257 | R55: =E55-D55 -> 0.012824074 | S55: 40 | T55: 31.642636 | U55: -227.5 | V55: -299.14264 | W55: =T55+S55 -> 71.642636
A56: 46052 | B56: W4 | C56: =TEXTJOIN( " | ", TRUE, TEXT(A56,"ddd dd - mmm"), TEXT(D56,"hh:mm"), G56, TEXT(I56,"0") ) -> Fri 30 - Jan | 11:49 | Short | 2 | D56: 0.49247685 | E56: 0.49384259 | F56: NIFTY 03 FEB 25450 PUT | G56: Short | H56: Manual | I56: 2 | J56: 65 | K56: 307.3 | L56: 299.05 | M56: =L56-K56 -> -8.25 | N56: =K56*J56 -> 19974.5 | O56: =M56/K56 -> -0.02684673 | P56: =O56+P55 -> 1.5983097 | Q56: =M56+Q55 -> 140.007 | R56: =E56-D56 -> 0.0013657407 | S56: 40 | T56: 43.636765 | U56: -536.25 | V56: -619.88677 | W56: =T56+S56 -> 83.636765
A57: 46052 | B57: W4 | C57: =TEXTJOIN( " | ", TRUE, TEXT(A57,"ddd dd - mmm"), TEXT(D57,"hh:mm"), G57, TEXT(I57,"0") ) -> Fri 30 - Jan | 13:36 | Long | 3 | D57: 0.56668981 | E57: 0.58409722 | F57: NIFTY 03 FEB 25350 CALL | G57: Long | H57: Reversal | I57: 3 | J57: 65 | K57: 166.5 | L57: 202.1 | M57: =L57-K57 -> 35.6 | N57: =K57*J57 -> 10822.5 | O57: =M57/K57 -> 0.21381381 | P57: =O57+P56 -> 1.8121235 | Q57: =M57+Q56 -> 175.607 | R57: =E57-D57 -> 0.017407407 | S57: 40 | T57: 30.623165 | U57: 2314 | V57: 2243.3768 | W57: =T57+S57 -> 70.623165
A58: 46055 | B58: W5 | C58: =TEXTJOIN( " | ", TRUE, TEXT(A58,"ddd dd - mmm"), TEXT(D58,"hh:mm"), G58, TEXT(I58,"0") ) -> Mon 02 - Feb | 14:00 | 1 | D58: 0.58342593 | E58: 0.59796296 | F58: NIFTY 03 FEB 24850 PUT | I58: 1 | J58: 65 | K58: 68.2 | L58: 66.4 | M58: =L58-K58 -> -1.8 | N58: =K58*J58 -> 4433 | O58: =M58/K58 -> -0.026392962 | P58: =O58+P57 -> 1.7857306 | Q58: =M58+Q57 -> 173.807 | R58: =E58-D58 -> 0.014537037 | S58: 40 | T58: 15.289362 | U58: -117 | V58: -172.28936 | W58: =T58+S58 -> 55.289362
A59: 46055 | B59: W5 | C59: =TEXTJOIN( " | ", TRUE, TEXT(A59,"ddd dd - mmm"), TEXT(D59,"hh:mm"), G59, TEXT(I59,"0") ) -> Mon 02 - Feb | 14:00 | 1 | D59: 0.58342593 | E59: 0.61625 | F59: NIFTY 03 FEB 24850 PUT | I59: 1 | J59: 65 | K59: 68.2 | L59: 59.55 | M59: =L59-K59 -> -8.65 | N59: =K59*J59 -> 4433 | O59: =M59/K59 -> -0.12683284 | P59: =O59+P58 -> 1.6588977 | Q59: =M59+Q58 -> 165.157 | R59: =E59-D59 -> 0.032824074 | S59: 40 | T59: 14.660066 | U59: -562.25 | V59: -616.91007 | W59: =T59+S59 -> 54.660066
A60: 46056 | B60: W5 | C60: =TEXTJOIN( " | ", TRUE, TEXT(A60,"ddd dd - mmm"), TEXT(D60,"hh:mm"), G60, TEXT(I60,"0") ) -> Tue 03 - Feb | 10:50 | 1 | D60: 0.45168981 | E60: 0.45424769 | F60: NIFTY 10 FEB 25800 PUT | I60: 1 | J60: 65 | K60: 237.2 | L60: 236.1 | M60: =L60-K60 -> -1.1 | N60: =K60*J60 -> 15418 | O60: =M60/K60 -> -0.0046374368 | P60: =O60+P59 -> 1.6542603 | Q60: =M60+Q59 -> 164.057 | R60: =E60-D60 -> 0.0025578704 | S60: 40 | T60: 35.808926 | U60: -71.5 | V60: -147.30893 | W60: =T60+S60 -> 75.808926
A61: 46056 | B61: W5 | C61: =TEXTJOIN( " | ", TRUE, TEXT(A61,"ddd dd - mmm"), TEXT(D61,"hh:mm"), G61, TEXT(I61,"0") ) -> Tue 03 - Feb | 11:10 | 2 | D61: 0.46540509 | E61: 0.4675463 | F61: NIFTY 10 FEB 25800 PUT | I61: 2 | J61: 65 | K61: 225 | L61: 220.95 | M61: =L61-K61 -> -4.05 | N61: =K61*J61 -> 14625 | O61: =M61/K61 -> -0.018 | P61: =O61+P60 -> 1.6362603 | Q61: =M61+Q60 -> 160.007 | R61: =E61-D61 -> 0.0021412037 | S61: 40 | T61: 34.061264 | U61: -263.25 | V61: -337.31126 | W61: =T61+S61 -> 74.061264
A62: 46056 | B62: W5 | C62: =TEXTJOIN( " | ", TRUE, TEXT(A62,"ddd dd - mmm"), TEXT(D62,"hh:mm"), G62, TEXT(I62,"0") ) -> Tue 03 - Feb | 11:27 | 3 | D62: 0.47710648 | E62: 0.48171296 | F62: NIFTY 10 FEB 25800 CALL | I62: 3 | J62: 65 | K62: 228.2 | L62: 251.85 | M62: =L62-K62 -> 23.65 | N62: =K62*J62 -> 14833 | O62: =M62/K62 -> 0.10363716 | P62: =O62+P61 -> 1.7398975 | Q62: =M62+Q61 -> 183.657 | R62: =E62-D62 -> 0.0046064815 | S62: 40 | T62: 36.993326 | U62: 1537.25 | V62: 1460.2567 | W62: =T62+S62 -> 76.993326
A63: 46056 | B63: W5 | C63: =TEXTJOIN( " | ", TRUE, TEXT(A63,"ddd dd - mmm"), TEXT(D63,"hh:mm"), G63, TEXT(I63,"0") ) -> Tue 03 - Feb | 11:27 | 3 | D63: 0.47710648 | E63: 0.48493056 | F63: NIFTY 10 FEB 25800 CALL | I63: 3 | J63: 65 | K63: 228.2 | L63: 242.15 | M63: =L63-K63 -> 13.95 | N63: =K63*J63 -> 14833 | O63: =M63/K63 -> 0.061130587 | P63: =O63+P62 -> 1.8010281 | Q63: =M63+Q62 -> 197.607 | R63: =E63-D63 -> 0.0078240741 | S63: 40 | T63: 36.102207 | U63: 906.75 | V63: 830.64779 | W63: =T63+S63 -> 76.102207
A64: 46057 | B64: W5 | C64: =TEXTJOIN( " | ", TRUE, TEXT(A64,"ddd dd - mmm"), TEXT(D64,"hh:mm"), G64, TEXT(I64,"0") ) -> Wed 04 - Feb | 10:15 | 1 | D64: 0.42712963 | E64: 0.44248843 | F64: NIFTY 10 FEB 25700 PUT | I64: 1 | J64: 65 | K64: 131.15 | L64: 152.1 | M64: =L64-K64 -> 20.95 | N64: =K64*J64 -> 8524.75 | O64: =M64/K64 -> 0.15974075 | P64: =O64+P63 -> 1.9607688 | Q64: =M64+Q63 -> 218.557 | R64: =E64-D64 -> 0.015358796 | S64: 40 | T64: 24.99864 | U64: 1361.75 | V64: 1296.7514 | W64: =T64+S64 -> 64.99864
A65: 46057 | B65: W5 | C65: =TEXTJOIN( " | ", TRUE, TEXT(A65,"ddd dd - mmm"), TEXT(D65,"hh:mm"), G65, TEXT(I65,"0") ) -> Wed 04 - Feb | 10:15 | 1 | D65: 0.42712963 | E65: 0.45038194 | F65: NIFTY 10 FEB 25700 PUT | I65: 1 | J65: 65 | K65: 131.15 | L65: 140 | M65: =L65-K65 -> 8.85 | N65: =K65*J65 -> 8524.75 | O65: =M65/K65 -> 0.067479985 | P65: =O65+P64 -> 2.0282488 | Q65: =M65+Q64 -> 227.407 | R65: =E65-D65 -> 0.023252315 | S65: 40 | T65: 23.887037 | U65: 575.25 | V65: 511.36296 | W65: =T65+S65 -> 63.887037
A66: 46057 | B66: W5 | C66: =TEXTJOIN( " | ", TRUE, TEXT(A66,"ddd dd - mmm"), TEXT(D66,"hh:mm"), G66, TEXT(I66,"0") ) -> Wed 04 - Feb | 12:48 | 2 | D66: 0.53335648 | E66: 0.54799769 | F66: NIFTY 10 FEB 25650 PUT | I66: 2 | J66: 65 | K66: 112.85 | L66: 108 | M66: =L66-K66 -> -4.85 | N66: =K66*J66 -> 7335.25 | O66: =M66/K66 -> -0.042977404 | P66: =O66+P65 -> 1.9852714 | Q66: =M66+Q65 -> 222.557 | R66: =E66-D66 -> 0.014641204 | S66: 40 | T66: 20.413468 | U66: -315.25 | V66: -375.66347 | W66: =T66+S66 -> 60.413468
A67: 46058 | B67: W5 | C67: =TEXTJOIN( " | ", TRUE, TEXT(A67,"ddd dd - mmm"), TEXT(D67,"hh:mm"), G67, TEXT(I67,"0") ) -> Thu 05 - Feb | 10:24 | 1 | D67: 0.43335648 | E67: 0.43576389 | F67: NIFTY 10 FEB 25700 CALL | I67: 1 | J67: 65 | K67: 148.7 | L67: 148 | M67: =L67-K67 -> -0.7 | N67: =K67*J67 -> 9665.5 | O67: =M67/K67 -> -0.0047074647 | P67: =O67+P66 -> 1.9805639 | Q67: =M67+Q66 -> 221.857 | R67: =E67-D67 -> 0.0024074074 | S67: 40 | T67: 25.133897 | U67: -45.5 | V67: -110.6339 | W67: =T67+S67 -> 65.133897
A68: 46058 | B68: W5 | C68: =TEXTJOIN( " | ", TRUE, TEXT(A68,"ddd dd - mmm"), TEXT(D68,"hh:mm"), G68, TEXT(I68,"0") ) -> Thu 05 - Feb | 10:57 | 2 | D68: 0.45672454 | E68: 0.46270833 | F68: NIFTY 10 FEB 25650 PUT | I68: 2 | J68: 130 | K68: 143.85 | L68: 134.45 | M68: =L68-K68 -> -9.4 | N68: =K68*J68 -> 18700.5 | O68: =M68/K68 -> -0.065345846 | P68: =O68+P67 -> 1.9152181 | Q68: =M68+Q67 -> 212.457 | R68: =E68-D68 -> 0.0059837963 | S68: 40 | T68: 40.295232 | U68: -1222 | V68: -1302.2952 | W68: =T68+S68 -> 80.295232
A69: 46058 | B69: W5 | C69: =TEXTJOIN( " | ", TRUE, TEXT(A69,"ddd dd - mmm"), TEXT(D69,"hh:mm"), G69, TEXT(I69,"0") ) -> Thu 05 - Feb | 14:59 | 3 | D69: 0.62434028 | E69: 0.62950231 | F69: NIFTY 10 FEB 25650 CALL | I69: 3 | J69: 130 | K69: 142.45 | L69: 145.3 | M69: =L69-K69 -> 2.85 | N69: =K69*J69 -> 18518.5 | O69: =M69/K69 -> 0.02000702 | P69: =O69+P68 -> 1.9352251 | Q69: =M69+Q68 -> 215.307 | R69: =E69-D69 -> 0.005162037 | S69: 40 | T69: 42.207095 | U69: 370.5 | V69: 288.29291 | W69: =T69+S69 -> 82.207095
... A73: 46059 | B73: W5 | C73: =TEXTJOIN( " | ", TRUE, TEXT(A73,"ddd dd - mmm"), TEXT(D73,"hh:mm"), G73, TEXT(I73,"0") ) -> Fri 06 - Feb | 13:57 | 2 | D73: 0.58127315 | E73: 0.58806713 | F73: NIFTY 10 FEB 25600 CALL | I73: 2 | J73: 65 | K73: 122.95 | L73: 118.65 | M73: =L73-K73 -> -4.3 | N73: =K73*J73 -> 7991.75 | O73: =M73/K73 -> -0.034973566 | P73: =O73+P72 -> 1.669205 | Q73: =M73+Q72 -> 185.357 | R73: =E73-D73 -> 0.0067939815 | S73: 40 | T73: 21.686469 | U73: -279.5 | V73: -341.18647 | W73: =T73+S73 -> 61.686469

Sheet DATA
D1: 45853 | E1: 45854 | F1: 45855 | G1: 45856 | H1: 45859 | I1: 45860 | J1: 45861 | K1: 45862 | L1: 45863 | M1: 45866 | N1: 45867 | O1: 45868 | P1: 45869 | Q1: 45870 | R1: 45873 | S1: 45874 | T1: 45875 | U1: 45876 | V1: 45877 | W1: 45880 | X1: 45881 | Y1: 45882 | Z1: 45883 | AA1: 45887 | AB1: 45888 | AC1: 45889 | AD1: 45890 | AE1: 45891 | AF1: 45894 | AG1: 45895 | AH1: 45897 | AI1: 45898 | AJ1: 45901 | AK1: 45902 | AL1: 45903 | AM1: 45904 | AN1: 45905 | AO1: 45908 | AP1: 45909 | AQ1: 45910 | AR1: 45911 | AS1: 45912 | AT1: 45915 | AU1: 45916 | AV1: 45917 | AW1: 45918 | AX1: 45919 | AY1: 45922 | AZ1: 45923 | BA1: 45924 | BB1: 45925 | BC1: 45926 | BD1: 45929 | BE1: 45930 | BF1: 45931 | BG1: 45933 | BH1: 45936 | BI1: 45937 | BJ1: 45938 | BK1: 45939 | BL1: 45940 | BM1: 45943 | BN1: 45944 | BO1: 45945 | BP1: 45946 | BQ1: 45947 | BR1: 45950 | BS1: 45953 | BT1: 45954 | BU1: 45957 | BV1: 45958 | BW1: 45959 | BX1: 45960 | BY1: 45961 | BZ1: 45964 | CA1: 45965 | CB1: 45967 | CC1: 45968 | CD1: 45971 | CE1: 45972 | CF1: 45973 | CG1: 45974 | CH1: 45975 | CI1: 45978 | CJ1: 45979 | CK1: 45980 | CL1: 45981 | CM1: 45982 | CN1: 45985 | CO1: 45986 | CP1: 45987 | CQ1: 45988 | CR1: 45989 | CS1: 45992 | CT1: 45993 | CU1: 45994 | CV1: 45995 | CW1: 45996 | CX1: 45999 | CY1: 46000 | CZ1: 46001 | DA1: 46002 | DB1: 46003 | DC1: 46006 | DD1: 46007 | DE1: 46008 | DF1: 46009 | DG1: 46010 | DH1: 46013 | DI1: 46014 | DJ1: 46015 | DK1: 46017 | DL1: 46020 | DM1: 46021 | DN1: 46022 | DO1: 46023 | DP1: 46024 | DQ1: 46027 | DR1: 46028 | DS1: 46029 | DT1: 46030 | DU1: 46031 | DV1: 46034 | DW1: 46035 | DX1: 46036 | DY1: 46038 | DZ1: 46041 | EA1: 46042 | EB1: 46043 | EC1: 46044 | ED1: 46045 | EE1: 46049 | EF1: 46050 | EG1: 46051 | EH1: 46052 | EI1: 46054 | EJ1: 46054 | EK1: 46055 | EL1: 46056 | EM1: 46057 | EN1: 46058 | EO1: 46059 | EP1: 46062 | EQ1: 46063 | ER1: 46064 | ES1: 46065 | ET1: 46066 | EU1: 46069 | EV1: 46070 | EW1: 46071 | EX1: 46072 | EY1: 46073 | EZ1: 46076 | FA1: 46077 | FB1: 46078 | FC1: 46079
A2: P&L | Q2: -1023.75 | R2: 2635.5 | S2: -1974 | T2: -1790.25 | U2: -38.5 | V2: -792.75 | W2: -2184 | X2: 450.5 | Y2: 25.25 | Z2: -418.25 | AA2: 1384.25 | AB2: -1768 | AC2: 1606.5 | AD2: 392 | AE2: -2826.25 | AF2: 1363.25 | AG2: 208.25 | AH2: 1940.75 | AI2: 716.5 | AJ2: -810 | AK2: 1347.5 | AL2: 768.75 | AM2: 1200 | AN2: -9614.75 | AO2: 2876.25 | AP2: 958 | AQ2: -1200 | AR2: -810 | AS2: -3300 | AT2: -1064 | AU2: 375 | AV2: -3183.75 | AW2: 321 | AX2: -1930.25 | AY2: 1088.5 | AZ2: -2640.75 | BA2: 772.5 | BB2: -25.5 | BC2: -2539.75 | BD2: 1041.25 | BE2: 705.25 | BF2: 1146.25 | BG2: -3927 | BH2: 908 | BI2: 3112 | BJ2: -2219 | BK2: -2000 | BL2: 3000 | BM2: -2227 | DA2: NO TRADE
A3: Trade | Q3: 6 | R3: 3 | S3: 5 | T3: 2 | U3: 6 | V3: 3 | W3: 2 | X3: 3 | Y3: 8 | Z3: 7 | AA3: 2 | AB3: 9 | AC3: 4 | AD3: 4 | AE3: 9 | AF3: 1 | AG3: 2 | AH3: 2 | AI3: 2 | AJ3: 6 | AK3: 1 | AL3: 2 | AM3: 3 | AN3: 5 | AO3: 4 | AP3: 10 | AQ3: 4 | AR3: 3 | AS3: 7 | AT3: 2 | AU3: 1 | AV3: 5 | AW3: 7 | AX3: 13 | AY3: 2 | AZ3: 11 | BA3: 1 | BB3: 9 | BC3: 9 | BD3: 1 | BE3: 1 | BF3: 1 | BG3: 5 | BH3: 1
A5: START | AJ5: startDate = input.time(timestamp("2025-09-01 03:45"), title="Start Date", group="Date Range") | AK5: startDate = input.time(timestamp("2025-09-02 03:45"), title="Start Date", group="Date Range") | AL5: startDate = input.time(timestamp("2025-09-03 03:45"), title="Start Date", group="Date Range") | AM5: startDate = input.time(timestamp("2025-09-04 03:45"), title="Start Date", group="Date Range") | AN5: startDate = input.time(timestamp("2025-09-05 03:45"), title="Start Date", group="Date Range") | AO5: startDate = input.time(timestamp("2025-09-08 03:45"), title="Start Date", group="Date Range") | AP5: startDate = input.time(timestamp("2025-09-09 03:45"), title="Start Date", group="Date Range") | AQ5: startDate = input.time(timestamp("2025-09-10 03:45"), title="Start Date", group="Date Range") | AR5: startDate = input.time(timestamp("2025-09-11 03:45"), title="Start Date", group="Date Range") | AS5: startDate = input.time(timestamp("2025-09-12 03:45"), title="Start Date", group="Date Range") | AT5: startDate = input.time(timestamp("2025-09-15 03:45"), title="Start Date", group="Date Range") | AU5: startDate = input.time(timestamp("2025-09-16 03:45"), title="Start Date", group="Date Range") | AV5: startDate = input.time(timestamp("2025-09-17 03:45"), title="Start Date", group="Date Range") | AW5: startDate = input.time(timestamp("2025-09-18 03:45"), title="Start Date", group="Date Range") | AX5: startDate = input.time(timestamp("2025-09-19 03:45"), title="Start Date", group="Date Range") | AY5: startDate = input.time(timestamp("2025-09-22 03:45"), title="Start Date", group="Date Range") | AZ5: startDate = input.time(timestamp("2025-09-23 03:45"), title="Start Date", group="Date Range") | BA5: startDate = input.time(timestamp("2025-09-24 03:45"), title="Start Date", group="Date Range") | BB5: startDate = input.time(timestamp("2025-09-25 03:45"), title="Start Date", group="Date Range") | BC5: startDate = input.time(timestamp("2025-09-26 03:45"), title="Start Date", group="Date Range") | BD5: startDate = input.time(timestamp("2025-09-29 03:45"), title="Start Date", group="Date Range") | BE5: startDate = input.time(timestamp("2025-09-30 03:45"), title="Start Date", group="Date Range") | BF5: startDate = input.time(timestamp("2025-10-01 03:45"), title="Start Date", group="Date Range") | BG5: startDate = input.time(timestamp("2025-10-03 03:45"), title="Start Date", group="Date Range") | BH5: startDate = input.time(timestamp("2025-10-06 03:45"), title="Start Date", group="Date Range") | BI5: startDate = input.time(timestamp("2025-10-07 03:45"), title="Start Date", group="Date Range") | BJ5: startDate = input.time(timestamp("2025-10-08 03:45"), title="Start Date", group="Date Range") | BK5: startDate = input.time(timestamp("2025-10-09 03:45"), title="Start Date", group="Date Range") | BL5: startDate = input.time(timestamp("2025-10-10 03:45"), title="Start Date", group="Date Range") | BM5: startDate = input.time(timestamp("2025-10-13 03:45"), title="Start Date", group="Date Range") | BN5: startDate = input.time(timestamp("2025-10-14 03:45"), title="Start Date", group="Date Range") | BO5: startDate = input.time(timestamp("2025-10-15 03:45"), title="Start Date", group="Date Range") | BP5: startDate = input.time(timestamp("2025-10-16 03:45"), title="Start Date", group="Date Range") | BQ5: startDate = input.time(timestamp("2025-10-17 03:45"), title="Start Date", group="Date Range") | BR5: startDate = input.time(timestamp("2025-10-20 03:45"), title="Start Date", group="Date Range") | BS5: startDate = input.time(timestamp("2025-10-23 03:45"), title="Start Date", group="Date Range") | BT5: startDate = input.time(timestamp("2025-10-24 03:45"), title="Start Date", group="Date Range") | BU5: startDate = input.time(timestamp("2025-10-27 03:45"), title="Start Date", group="Date Range") | BV5: startDate = input.time(timestamp("2025-10-28 03:45"), title="Start Date", group="Date Range") | BW5: startDate = input.time(timestamp("2025-10-29 03:45"), title="Start Date", group="Date Range") | BX5: startDate = input.time(timestamp("2025-10-30 03:45"), title="Start Date", group="Date Range") | BY5: startDate = input.time(timestamp("2025-10-31 03:45"), title="Start Date", group="Date Range") | BZ5: startDate = input.time(timestamp("2025-11-03 03:45"), title="Start Date", group="Date Range") | CA5: startDate = input.time(timestamp("2025-11-04 03:45"), title="Start Date", group="Date Range") | CB5: startDate = input.time(timestamp("2025-11-06 03:45"), title="Start Date", group="Date Range") | CC5: startDate = input.time(timestamp("2025-11-07 03:45"), title="Start Date", group="Date Range") | CD5: startDate = input.time(timestamp("2025-11-10 03:45"), title="Start Date", group="Date Range") | CE5: startDate = input.time(timestamp("2025-11-11 03:45"), title="Start Date", group="Date Range") | CF5: startDate = input.time(timestamp("2025-11-12 03:45"), title="Start Date", group="Date Range") | CG5: startDate = input.time(timestamp("2025-11-13 03:45"), title="Start Date", group="Date Range") | CH5: startDate = input.time(timestamp("2025-11-14 03:45"), title="Start Date", group="Date Range") | CI5: startDate = input.time(timestamp("2025-11-17 03:45"), title="Start Date", group="Date Range") | CJ5: startDate = input.time(timestamp("2025-11-18 03:45"), title="Start Date", group="Date Range") | CK5: startDate = input.time(timestamp("2025-11-19 03:45"), title="Start Date", group="Date Range") | CL5: startDate = input.time(timestamp("2025-11-20 03:45"), title="Start Date", group="Date Range") | CM5: startDate = input.time(timestamp("2025-11-21 03:45"), title="Start Date", group="Date Range") | CN5: startDate = input.time(timestamp("2025-11-24 03:45"), title="Start Date", group="Date Range") | CO5: startDate = input.time(timestamp("2025-11-25 03:45"), title="Start Date", group="Date Range") | CP5: startDate = input.time(timestamp("2025-11-28603:45"), title="Start Date", group="Date Range") | CQ5: startDate = input.time(timestamp("2025-11-27 03:45"), title="Start Date", group="Date Range") | CR5: startDate = input.time(timestamp("2025-11-28 03:45"), title="Start Date", group="Date Range") | CS5: startDate = input.time(timestamp("2025-12-01 03:45"), title="Start Date", group="Date Range") | CT5: startDate = input.time(timestamp("2025-12-02 03:45"), title="Start Date", group="Date Range") | CU5: startDate = input.time(timestamp("2025-12-03 03:45"), title="Start Date", group="Date Range") | CV5: startDate = input.time(timestamp("2025-12-04 03:45"), title="Start Date", group="Date Range") | CW5: startDate = input.time(timestamp("2025-12-05 03:45"), title="Start Date", group="Date Range") | CX5: startDate = input.time(timestamp("2025-12-08 03:45"), title="Start Date", group="Date Range") | CY5: startDate = input.time(timestamp("2025-12-09 03:45"), title="Start Date", group="Date Range") | CZ5: startDate = input.time(timestamp("2025-12-10 03:45"), title="Start Date", group="Date Range") | DA5: startDate = input.time(timestamp("2025-12-11 03:45"), title="Start Date", group="Date Range") | DB5: startDate = input.time(timestamp("2025-12-12 03:45"), title="Start Date", group="Date Range") | DC5: startDate = input.time(timestamp("2025-12-15 03:45"), title="Start Date", group="Date Range") | DD5: startDate = input.time(timestamp("2025-12-16 03:45"), title="Start Date", group="Date Range") | DE5: startDate = input.time(timestamp("2025-12-17 03:45"), title="Start Date", group="Date Range") | DF5: startDate = input.time(timestamp("2025-12-18 03:45"), title="Start Date", group="Date Range") | DG5: startDate = input.time(timestamp("2025-12-19 03:45"), title="Start Date", group="Date Range") | DH5: startDate = input.time(timestamp("2025-12-22 03:45"), title="Start Date", group="Date Range") | DI5: startDate = input.time(timestamp("2025-12-23 03:45"), title="Start Date", group="Date Range") | DJ5: startDate = input.time(timestamp("2025-12-24 03:45"), title="Start Date", group="Date Range") | DK5: tartDate = input.time(timestamp("2025-12-26 03:45"), title="Start Date", group="Date Range") | DL5: startDate = input.time(timestamp("2025-12-29 03:45"), title="Start Date", group="Date Range") | DM5: startDate = input.time(timestamp("2025-12-31 03:45"), title="Start Date", group="Date Range") | DN5: startDate = input.time(timestamp("2025-12-31 03:45"), title="Start Date", group="Date Range") | DO5: startDate = input.time(timestamp("2026-01-01 03:45"), title="Start Date", group="Date Range") | DP5: startDate = input.time(timestamp("2026-01-02 03:45"), title="Start Date", group="Date Range") | DQ5: startDate = input.time(timestamp("2026-01-05 03:45"), title="Start Date", group="Date Range") | DS5: startDate = input.time(timestamp("2026-01-08 03:45"), title="Start Date", group="Date Range") | DT5: startDate = input.time(timestamp("2026-01-08 03:45"), title="Start Date", group="Date Range") | DU5: startDate = input.time(timestamp("2026-01-09 03:45"), title="Start Date", group="Date Range") | DV5: startDate = input.time(timestamp("2026-01-12 03:45"), title="Start Date", group="Date Range") | DW5: tartDate = input.time(timestamp("2026-01-13 03:45"), title="Start Date", group="Date Range") | DZ5: tartDate = input.time(timestamp("2026-01-19 03:45"), title="Start Date", group="Date Range") | EA5: startDate = input.time(timestamp("2026-01-20 03:45"), title="Start Date", group="Date Range") | EE5: startDate = input.time(timestamp("2026-01-28 03:45"), title="Start Date", group="Date Range") | EF5: startDate = input.time(timestamp("2026-01-29 03:45"), title="Start Date", group="Date Range") | EG5: startDate = input.time(timestamp("2026-01-30 03:45"), title="Start Date", group="Date Range") | EH5: startDate = input.time(timestamp("2026-01-30 03:45"), title="Start Date", group="Date Range") | EI5: startDate = input.time(timestamp("2026-02-02 03:45"), title="Start Date", group="Date Range") | EJ5: startDate = input.time(timestamp("2026-02-03 03:45"), title="Start Date", group="Date Range") | EL5: startDate = input.time(timestamp("2026-02-04 03:45"), title="Start Date", group="Date Range") | EM5: startDate = input.time(timestamp("2026-02-05 03:45"), title="Start Date", group="Date Range") | EP5: startDate = input.time(timestamp("2026-02-09 03:45"), title="Start Date", group="Date Range") | EQ5: startDate = input.time(timestamp("2026-02-10 03:45"), title="Start Date", group="Date Range") | ER5: startDate = input.time(timestamp("2026-02-11 03:45"), title="Start Date", group="Date Range") | EU5: startDate = input.time(timestamp("2026-02-16 03:45"), title="Start Date", group="Date Range") | EV5: startDate = input.time(timestamp("2026-02-17 03:45"), title="Start Date", group="Date Range") | EW5: startDate = input.time(timestamp("2026-02-18 03:45"), title="Start Date", group="Date Range") | EX5: startDate = input.time(timestamp("2026-02-19 03:45"), title="Start Date", group="Date Range") | EY5: startDate = input.time(timestamp("2026-02-20 03:45"), title="Start Date", group="Date Range") | EZ5: startDate = input.time(timestamp("2026-02-23 03:45"), title="Start Date", group="Date Range") | FA5: startDate = input.time(timestamp("2026-02-24 03:45"), title="Start Date", group="Date Range") | FB5: startDate = input.time(timestamp("2026-02-25 03:45"), title="Start Date", group="Date Range") | FC5: startDate = input.time(timestamp("2026-02-26 03:45"), title="Start Date", group="Date Range")
A6: END | AJ6: endDate = input.time(timestamp("2025-09-01 10:00"), title="End Date", group="Date Range")//10:00 | AK6: endDate = input.time(timestamp("2025-09-02 10:00"), title="End Date", group="Date Range")//10:00 | AL6: endDate = input.time(timestamp("2025-09-03 10:00"), title="End Date", group="Date Range")//10:00 | AM6: endDate = input.time(timestamp("2025-09-04 10:00"), title="End Date", group="Date Range")//10:00 | AN6: endDate = input.time(timestamp("2025-09-05 10:00"), title="End Date", group="Date Range")//10:00 | AO6: endDate = input.time(timestamp("2025-09-08 10:00"), title="End Date", group="Date Range")//10:00 | AP6: endDate = input.time(timestamp("2025-09-09 10:00"), title="End Date", group="Date Range")//10:00 | AQ6: endDate = input.time(timestamp("2025-09-10 10:00"), title="End Date", group="Date Range")//10:00 | AR6: endDate = input.time(timestamp("2025-09-11 10:00"), title="End Date", group="Date Range")//10:00 | AS6: endDate = input.time(timestamp("2025-09-12 10:00"), title="End Date", group="Date Range")//10:00 | AT6: endDate = input.time(timestamp("2025-09-15 10:00"), title="End Date", group="Date Range")//10:00 | AU6: endDate = input.time(timestamp("2025-09-16 10:00"), title="End Date", group="Date Range")//10:00 | AV6: endDate = input.time(timestamp("2025-09-17 10:00"), title="End Date", group="Date Range")//10:00 | AW6: endDate = input.time(timestamp("2025-09-18 10:00"), title="End Date", group="Date Range")//10:00 | AX6: endDate = input.time(timestamp("2025-09-19 10:00"), title="End Date", group="Date Range")//10:00 | AY6: endDate = input.time(timestamp("2025-09-22 10:00"), title="End Date", group="Date Range")//10:00 | AZ6: endDate = input.time(timestamp("2025-09-23 10:00"), title="End Date", group="Date Range")//10:00 | BA6: endDate = input.time(timestamp("2025-09-24 10:00"), title="End Date", group="Date Range")//10:00 | BB6: endDate = input.time(timestamp("2025-09-25 10:00"), title="End Date", group="Date Range")//10:00 | BC6: endDate = input.time(timestamp("2025-09-26 10:00"), title="End Date", group="Date Range")//10:00 | BD6: endDate = input.time(timestamp("2025-09-29 10:00"), title="End Date", group="Date Range")//10:00 | BE6: endDate = input.time(timestamp("2025-09-30 10:00"), title="End Date", group="Date Range")//10:00 | BF6: endDate = input.time(timestamp("2025-10-01 10:00"), title="End Date", group="Date Range")//10:00 | BG6: endDate = input.time(timestamp("2025-10-03 10:00"), title="End Date", group="Date Range")//10:00 | BH6: endDate = input.time(timestamp("2025-10-06 10:00"), title="End Date", group="Date Range")//10:00 | BI6: endDate = input.time(timestamp("2025-10-07 10:00"), title="End Date", group="Date Range")//10:00 | BJ6: endDate = input.time(timestamp("2025-10-08 10:00"), title="End Date", group="Date Range")//10:00 | BK6: endDate = input.time(timestamp("2025-10-09 10:00"), title="End Date", group="Date Range")//10:00 | BL6: endDate = input.time(timestamp("2025-10-10 10:00"), title="End Date", group="Date Range")//10:00 | BM6: endDate = input.time(timestamp("2025-10-13 10:00"), title="End Date", group="Date Range")//10:00 | BN6: endDate = input.time(timestamp("2025-10-14 10:00"), title="End Date", group="Date Range")//10:00 | BO6: endDate = input.time(timestamp("2025-10-15 10:00"), title="End Date", group="Date Range")//10:00 | BP6: endDate = input.time(timestamp("2025-10-16 10:00"), title="End Date", group="Date Range")//10:00 | BQ6: endDate = input.time(timestamp("2025-10-17 10:00"), title="End Date", group="Date Range")//10:00 | BR6: endDate = input.time(timestamp("2025-10-20 10:00"), title="End Date", group="Date Range")//10:00 | BS6: endDate = input.time(timestamp("2025-10-23 10:00"), title="End Date", group="Date Range")//10:00 | BT6: endDate = input.time(timestamp("2025-10-24 10:00"), title="End Date", group="Date Range")//10:00 | BU6: endDate = input.time(timestamp("2025-10-27 10:00"), title="End Date", group="Date Range")//10:00 | BV6: endDate = input.time(timestamp("2025-10-28 10:00"), title="End Date", group="Date Range")//10:00 | BW6: endDate = input.time(timestamp("2025-10-29 10:00"), title="End Date", group="Date Range")//10:00 | BX6: endDate = input.time(timestamp("2025-10-30 10:00"), title="End Date", group="Date Range")//10:00 | BY6: endDate = input.time(timestamp("2025-10-31 10:00"), title="End Date", group="Date Range")//10:00 | BZ6: endDate = input.time(timestamp("2025-11-03 10:00"), title="End Date", group="Date Range")//10:00 | CA6: endDate = input.time(timestamp("2025-11-04 10:00"), title="End Date", group="Date Range")//10:00 | CB6: endDate = input.time(timestamp("2025-11-06 10:00"), title="End Date", group="Date Range")//10:00 | CC6: endDate = input.time(timestamp("2025-11-07 10:00"), title="End Date", group="Date Range")//10:00 | CD6: endDate = input.time(timestamp("2025-11-10 10:00"), title="End Date", group="Date Range")//10:00 | CE6: endDate = input.time(timestamp("2025-11-11 10:00"), title="End Date", group="Date Range")//10:00 | CF6: endDate = input.time(timestamp("2025-11-12 10:00"), title="End Date", group="Date Range")//10:00 | CG6: endDate = input.time(timestamp("2025-11-13 10:00"), title="End Date", group="Date Range")//10:00 | CH6: endDate = input.time(timestamp("2025-11-14 10:00"), title="End Date", group="Date Range")//10:00 | CI6: endDate = input.time(timestamp("2025-11-17 10:00"), title="End Date", group="Date Range")//10:00 | CJ6: endDate = input.time(timestamp("2025-11-18 10:00"), title="End Date", group="Date Range")//10:00 | CK6: endDate = input.time(timestamp("2025-11-19 10:00"), title="End Date", group="Date Range")//10:00 | CL6: endDate = input.time(timestamp("2025-11-20 10:00"), title="End Date", group="Date Range")//10:00 | CM6: endDate = input.time(timestamp("2025-11-21 10:00"), title="End Date", group="Date Range")//10:00 | CN6: endDate = input.time(timestamp("2025-11-24 10:00"), title="End Date", group="Date Range")//10:00 | CO6: endDate = input.time(timestamp("2025-11-25 10:00"), title="End Date", group="Date Range")//10:00 | CP6: endDate = input.time(timestamp("2025-11-26 10:00"), title="End Date", group="Date Range")//10:00 | CQ6: endDate = input.time(timestamp("2025-11-27 10:00"), title="End Date", group="Date Range")//10:00 | CR6: endDate = input.time(timestamp("2025-11-28 10:00"), title="End Date", group="Date Range")//10:00 | CS6: endDate = input.time(timestamp("2025-12-01 10:00"), title="End Date", group="Date Range")//10:00 | CT6: endDate = input.time(timestamp("2025-12-02 10:00"), title="End Date", group="Date Range")//10:00 | CU6: endDate = input.time(timestamp("2025-12-03 10:00"), title="End Date", group="Date Range")//10:00 | CV6: endDate = input.time(timestamp("2025-12-04 10:00"), title="End Date", group="Date Range")//10:00 | CW6: endDate = input.time(timestamp("2025-12-05 10:00"), title="End Date", group="Date Range")//10:00 | CX6: endDate = input.time(timestamp("2025-12-08 10:00"), title="End Date", group="Date Range")//10:00 | CY6: endDate = input.time(timestamp("2025-12-09 10:00"), title="End Date", group="Date Range")//10:00 | CZ6: endDate = input.time(timestamp("2025-12-10 10:00"), title="End Date", group="Date Range")//10:00 | DA6: endDate = input.time(timestamp("2025-12-11 10:00"), title="End Date", group="Date Range")//10:00 | DB6: endDate = input.time(timestamp("2025-12-12 10:00"), title="End Date", group="Date Range")//10:00 | DC6: endDate = input.time(timestamp("2025-12-15 10:00"), title="End Date", group="Date Range")//10:00 | DD6: endDate = input.time(timestamp("2025-12-16 10:00"), title="End Date", group="Date Range")//10:00 | DE6: endDate = input.time(timestamp("2025-12-17 10:00"), title="End Date", group="Date Range")//10:00 | DF6: endDate = input.time(timestamp("2025-12-18 10:00"), title="End Date", group="Date Range")//10:00 | DG6: endDate = input.time(timestamp("2025-12-19 10:00"), title="End Date", group="Date Range")//10:00 | DH6: endDate = input.time(timestamp("2025-12-22 10:00"), title="End Date", group="Date Range")//10:00 | DI6: endDate = input.time(timestamp("2025-12-23 10:00"), title="End Date", group="Date Range")//10:00 | DJ6: endDate = input.time(timestamp("2025-12-24 10:00"), title="End Date", group="Date Range")//10:00 | DK6: endDate = input.time(timestamp("2025-12-26 10:00"), title="End Date", group="Date Range")//10:00 | DL6: endDate = input.time(timestamp("2025-12-29 10:00"), title="End Date", group="Date Range")//10:00 | DM6: endDate = input.time(timestamp("2025-12-31 10:00"), title="End Date", group="Date Range")//10:00 | DN6: endDate = input.time(timestamp("2025-12-31 10:00"), title="End Date", group="Date Range")//10:00 | DO6: endDate = input.time(timestamp("2026-01-01 10:00"), title="End Date", group="Date Range")//10:00 | DP6: endDate = input.time(timestamp("2026-01-02 10:00"), title="End Date", group="Date Range")//10:00 | DQ6: endDate = input.time(timestamp("2026-01-05 10:00"), title="End Date", group="Date Range")//10:00 | DS6: endDate = input.time(timestamp("2026-01-08 10:00"), title="End Date", group="Date Range")//10:00 | DT6: endDate = input.time(timestamp("2026-01-08 10:00"), title="End Date", group="Date Range")//10:00 | DU6: endDate = input.time(timestamp("2026-01-09 10:00"), title="End Date", group="Date Range")//10:00 | DV6: endDate = input.time(timestamp("2026-01-12 10:00"), title="End Date", group="Date Range")//10:00 | DW6: endDate = input.time(timestamp("2026-01-13 10:00"), title="End Date", group="Date Range")//10:00 | DZ6: endDate = input.time(timestamp("2026-01-19 10:00"), title="End Date", group="Date Range")//10:00 | EA6: endDate = input.time(timestamp("2026-01-20 10:00"), title="End Date", group="Date Range")//10:00 | EE6: endDate = input.time(timestamp("2026-01-28 10:00"), title="End Date", group="Date Range")//10:00 | EF6: endDate = input.time(timestamp("2026-01-29 10:00"), title="End Date", group="Date Range")//10:00 | EG6: endDate = input.time(timestamp("2026-01-30 10:00"), title="End Date", group="Date Range")//10:00 | EH6: endDate = input.time(timestamp("2026-01-30 10:00"), title="End Date", group="Date Range")//10:00 | EI6: endDate = input.time(timestamp("2026-02-02 10:00"), title="End Date", group="Date Range")//10:00 | EJ6: endDate = input.time(timestamp("2026-02-03 10:00"), title="End Date", group="Date Range")//10:00 | EL6: endDate = input.time(timestamp("2026-02-04 10:00"), title="End Date", group="Date Range")//10:00 | EM6: endDate = input.time(timestamp("2026-02-05 10:00"), title="End Date", group="Date Range")//10:00 | EP6: endDate = input.time(timestamp("2026-02-09 10:00"), title="End Date", group="Date Range")//10:00 | EQ6: endDate = input.time(timestamp("2026-02-10 10:00"), title="End Date", group="Date Range")//10:00 | ER6: endDate = input.time(timestamp("2026-02-11 10:00"), title="End Date", group="Date Range")//10:00 | EU6: endDate = input.time(timestamp("2026-02-16 10:00"), title="End Date", group="Date Range")//10:00 | EV6: endDate = input.time(timestamp("2026-02-17 10:00"), title="End Date", group="Date Range")//10:00 | EW6: endDate = input.time(timestamp("2026-02-18 10:00"), title="End Date", group="Date Range")//10:00 | EX6: endDate = input.time(timestamp("2026-02-19 10:00"), title="End Date", group="Date Range")//10:00 | EY6: endDate = input.time(timestamp("2026-02-20 10:00"), title="End Date", group="Date Range")//10:00 | EZ6: endDate = input.time(timestamp("2026-02-23 10:00"), title="End Date", group="Date Range")//10:00 | FA6: endDate = input.time(timestamp("2026-02-24 10:00"), title="End Date", group="Date Range")//10:00 | FB6: endDate = input.time(timestamp("2026-02-25 10:00"), title="End Date", group="Date Range")//10:00 | FC6: endDate = input.time(timestamp("2026-02-26 10:00"), title="End Date", group="Date Range")//10:00
A7: DATE RANGE | AJ7: inDateRange = (time >= startDate and time <= endDate) | AK7: inDateRange = (time >= startDate and time <= endDate) | AL7: inDateRange = (time >= startDate and time <= endDate) | AM7: inDateRange = (time >= startDate and time <= endDate) | AN7: inDateRange = (time >= startDate and time <= endDate) | AO7: inDateRange = (time >= startDate and time <= endDate) | AP7: inDateRange = (time >= startDate and time <= endDate) | AQ7: inDateRange = (time >= startDate and time <= endDate) | AR7: inDateRange = (time >= startDate and time <= endDate) | AS7: inDateRange = (time >= startDate and time <= endDate) | AT7: inDateRange = (time >= startDate and time <= endDate) | AU7: inDateRange = (time >= startDate and time <= endDate) | AV7: inDateRange = (time >= startDate and time <= endDate) | AW7: inDateRange = (time >= startDate and time <= endDate) | AX7: inDateRange = (time >= startDate and time <= endDate) | AY7: inDateRange = (time >= startDate and time <= endDate) | AZ7: inDateRange = (time >= startDate and time <= endDate) | BA7: inDateRange = (time >= startDate and time <= endDate) | BB7: inDateRange = (time >= startDate and time <= endDate) | BC7: inDateRange = (time >= startDate and time <= endDate) | BD7: inDateRange = (time >= startDate and time <= endDate) | BE7: inDateRange = (time >= startDate and time <= endDate) | BF7: inDateRange = (time >= startDate and time <= endDate) | BG7: inDateRange = (time >= startDate and time <= endDate) | BH7: inDateRange = (time >= startDate and time <= endDate) | BI7: inDateRange = (time >= startDate and time <= endDate) | BJ7: inDateRange = (time >= startDate and time <= endDate) | BK7: inDateRange = (time >= startDate and time <= endDate) | BL7: inDateRange = (time >= startDate and time <= endDate) | BM7: inDateRange = (time >= startDate and time <= endDate) | BN7: inDateRange = (time >= startDate and time <= endDate) | BO7: inDateRange = (time >= startDate and time <= endDate) | BP7: inDateRange = (time >= startDate and time <= endDate) | BQ7: inDateRange = (time >= startDate and time <= endDate) | BR7: inDateRange = (time >= startDate and time <= endDate) | BS7: inDateRange = (time >= startDate and time <= endDate) | BT7: inDateRange = (time >= startDate and time <= endDate) | BU7: inDateRange = (time >= startDate and time <= endDate) | BV7: inDateRange = (time >= startDate and time <= endDate) | BW7: inDateRange = (time >= startDate and time <= endDate) | BX7: inDateRange = (time >= startDate and time <= endDate) | BY7: inDateRange = (time >= startDate and time <= endDate) | BZ7: inDateRange = (time >= startDate and time <= endDate) | CA7: inDateRange = (time >= startDate and time <= endDate) | CB7: inDateRange = (time >= startDate and time <= endDate) | CC7: inDateRange = (time >= startDate and time <= endDate) | CD7: inDateRange = (time >= startDate and time <= endDate) | CE7: inDateRange = (time >= startDate and time <= endDate) | CF7: inDateRange = (time >= startDate and time <= endDate) | CG7: inDateRange = (time >= startDate and time <= endDate) | CH7: inDateRange = (time >= startDate and time <= endDate) | CI7: inDateRange = (time >= startDate and time <= endDate) | CJ7: inDateRange = (time >= startDate and time <= endDate) | CK7: inDateRange = (time >= startDate and time <= endDate) | CL7: inDateRange = (time >= startDate and time <= endDate) | CM7: inDateRange = (time >= startDate and time <= endDate) | CN7: inDateRange = (time >= startDate and time <= endDate) | CO7: inDateRange = (time >= startDate and time <= endDate) | CP7: inDateRange = (time >= startDate and time <= endDate) | CQ7: inDateRange = (time >= startDate and time <= endDate) | CR7: inDateRange = (time >= startDate and time <= endDate) | CS7: inDateRange = (time >= startDate and time <= endDate) | CT7: inDateRange = (time >= startDate and time <= endDate) | CU7: inDateRange = (time >= startDate and time <= endDate) | CV7: inDateRange = (time >= startDate and time <= endDate) | CW7: inDateRange = (time >= startDate and time <= endDate) | CX7: inDateRange = (time >= startDate and time <= endDate) | CY7: inDateRange = (time >= startDate and time <= endDate) | CZ7: inDateRange = (time >= startDate and time <= endDate) | DA7: inDateRange = (time >= startDate and time <= endDate) | DB7: inDateRange = (time >= startDate and time <= endDate) | DC7: inDateRange = (time >= startDate and time <= endDate) | DD7: inDateRange = (time >= startDate and time <= endDate) | DE7: inDateRange = (time >= startDate and time <= endDate) | DF7: inDateRange = (time >= startDate and time <= endDate) | DG7: inDateRange = (time >= startDate and time <= endDate) | DH7: inDateRange = (time >= startDate and time <= endDate) | DI7: inDateRange = (time >= startDate and time <= endDate) | DJ7: inDateRange = (time >= startDate and time <= endDate) | DK7: inDateRange = (time >= startDate and time <= endDate) | DL7: inDateRange = (time >= startDate and time <= endDate) | DM7: inDateRange = (time >= startDate and time <= endDate) | DN7: inDateRange = (time >= startDate and time <= endDate) | DO7: inDateRange = (time >= startDate and time <= endDate) | DP7: inDateRange = (time >= startDate and time <= endDate) | DQ7: inDateRange = (time >= startDate and time <= endDate) | DS7: inDateRange = (time >= startDate and time <= endDate) | DT7: inDateRange = (time >= startDate and time <= endDate) | DU7: inDateRange = (time >= startDate and time <= endDate) | DV7: inDateRange = (time >= startDate and time <= endDate) | DW7: inDateRange = (time >= startDate and time <= endDate) | DZ7: inDateRange = (time >= startDate and time <= endDate) | EA7: inDateRange = (time >= startDate and time <= endDate) | EE7: inDateRange = (time >= startDate and time <= endDate) | EF7: inDateRange = (time >= startDate and time <= endDate) | EG7: inDateRange = (time >= startDate and time <= endDate) | EH7: inDateRange = (time >= startDate and time <= endDate) | EI7: inDateRange = (time >= startDate and time <= endDate) | EJ7: inDateRange = (time >= startDate and time <= endDate) | EL7: inDateRange = (time >= startDate and time <= endDate) | EM7: inDateRange = (time >= startDate and time <= endDate) | EP7: inDateRange = (time >= startDate and time <= endDate) | EQ7: inDateRange = (time >= startDate and time <= endDate) | ER7: inDateRange = (time >= startDate and time <= endDate | EU7: inDateRange = (time >= startDate and time <= endDate) | EV7: inDateRange = (time >= startDate and time <= endDate) | EW7: inDateRange = (time >= startDate and time <= endDate) | EX7: inDateRange = (time >= startDate and time <= endDate) | EY7: inDateRange = (time >= startDate and time <= endDate) | EZ7: inDateRange = (time >= startDate and time <= endDate) | FA7: inDateRange = (time >= startDate and time <= endDate) | FB7: inDateRange = (time >= startDate and time <= endDate) | FC7: inDateRange = (time >= startDate and time <= endDate)
A9: BNF_PD_H | B9: = | D9: 59288.7 | E9: BNF_PD_H=57134.95 | F9: BNF_PD_H=57276.55 | G9: BNF_PD_H=57262.85 | H9: BNF_PD_H=56705.15 | I9: BNF_PD_H=56983.45 | J9: BNF_PD_H=57286.15 | K9: BNF_PD_H=57249 | L9: BNF_PD_H=57316.6 | M9: BNF_PD_H=57170.7 | N9: BNF_PD_H=56578.4 | O9: BNF_PD_H=56296.4 | P9: BNF_PD_H=56321.15 | Q9: BNF_PD_H=56406.2 | R9: BNF_PD_H=56097.6 | S9: BNF_PD_H=55752.45 | T9: BNF_PD_H=55648.15 | U9: BNF_PD_H=55559.4 | V9: BNF_PD_H=55614.85 | W9: BNF_PD_H=55652.6 | X9: BNF_PD_H=55582.15 | Y9: BNF_PD_H=55566.7 | Z9: BNF_PD_H=55340.05 | AA9: BNF_PD_H=55472.8 | AB9: BNF_PD_H=56156.3 | AC9: BNF_PD_H=55965.55 | AD9: BNF_PD_H=55812.6 | AE9: BNF_PD_H=55993.65 | AF9: BNF_PD_H=55745 | AG9: BNF_PD_H=55306 | AH9: BNF_PD_H=55068.9 | AI9: BNF_PD_H=54382.25 | AJ9: BNF_PD_H = 54086 | AK9: BNF_PD_H=54035.85 | AL9: BNF_PD_H=54160.95 | AM9: BNF_PD_H=54136.15 | AN9: BNF_PD_H=54450.55 | AO9: BNF_PD_H = 54308.05 | AP9: BNF_PD_H = 54518.7 | AQ9: BNF_PD_H = 54351.35 | AR9: BNF_PD_H = 55705.9 | AS9: BNF_PD_H = 54757.45 | AT9: BNF_PD_H = 54852.25 | AU9: BNF_PD_H = 55018 | AV9: BNF_PD_H = 55186.65 | AW9: BNF_PD_H = 55543.8 | AX9: BNF_PD_H = 55837.90 | AY9: BNF_PD_H = 55688.45 | AZ9: BNF_PD_H = 55669 | BA9: BNF_PD_H = 55662 | BB9: BNF_PD_H = 55508.8 | BC9: BNF_PD_H = 55276.65 | BD9: BNF_PD_H = 54897 | BE9: BNF_PD_H = 54686.05 | BF9: BNF_PD_H = 54793.05 | BG9: BNF_PD_H = 57526.20 | BH9: BNF_PD_H = 55616.45 | BI9: BNF_PD_H = 56164.2 | BJ9: BNF_PD_H = 56502.45 | BK9: BNF_PD_H = 56303 | BL9: BNF_PD_H = 56286.25 | BM9: BNF_PD_H = 56760.25 | BN9: BNF_PD_H = 56770.9 | BO9: BNF_PD_H = 56721.3 | BP9: BNF_PD_H = 56922.7 | BQ9: BNF_PD_H = 57525.8 | BR9: BNF_PD_H = 57830.2 | BS9: BNF_PD_H = 58155.55 | BT9: BNF_PD_H = 58577.5 | BU9: BNF_PD_H = 58232.9 | BV9: BNF_PD_H = 58224.55 | BW9: BNF_PD_H = 58313.8 | BX9: BNF_PD_H = 58469.9 | BY9: BNF_PD_H = 58331.2 | BZ9: BNF_PD_H = 58254.95 | CA9: BNF_PD_H = 58247.55 | CB9: BNF_PD_H = 58119.65 | CC9: BNF_PD_H = 57945.05 | CD9: BNF_PD_H = 58001.35 | CE9: BNF_PD_H = 58097.2 | CF9: BNF_PD_H = 58187.35 | CG9: BNF_PD_H = 58505.35 | CH9: BNF_PD_H = 58615.95 | CI9: BNF_PD_H = 58590.15 | CJ9: BNF_PD_H = 59001.55 | CK9: BNF_PD_H = 59103.65 | CL9: BNF_PD_H = 59264.25 | CM9: BNF_PD_H = 59440.1 | CN9: BNF_PD_H = 59232.15 | CO9: BNF_PD_H = 59309.9 | CP9: BNF_PD_H = 59166.15 | CQ9: BNF_PD_H = 59554.95 | CR9: BNF_PD_H = 59866.6 | CS9: BNF_PD_H = 59597.5 | CT9: BNF_PD_H = 60114.3 | CU9: BNF_PD_H = 59656.55 | CV9: BNF_PD_H = 59414.9 | CW9: BNF_PD_H = 59548.7 | CX9: BNF_PD_H = 59806.6 | CY9: BNF_PD_H = 59713.15 | CZ9: BNF_PD_H = 59358.25 | DA9: BNF_PD_H = 59440.9 | DB9: BNF_PD_H = 59423.35 | DC9: BNF_PD_H = 59545.7 | DD9: BNF_PD_H = 59533 | DE9: BNF_PD_H = 59335.25 | DF9: BNF_PD_H = 59127.2 | DG9: BNF_PD_H = 59211 | DH9: BNF_PD_H = 59140.55 | DI9: BNF_PD_H = 59371.2 | DJ9: BNF_PD_H = 59402.35 | DK9: BNF_PD_H = 59478.15 | DL9: BNF_PD_H = 59180.65 | DM9: BNF_PD_H = 59140.4 | DN9: BNF_PD_H = 59272.7 | DO9: BNF_PD_H = 59766.2 | DP9: BNF_PD_H = 59766.2 | DQ9: BNF_PD_H = 60203.75
A10: BNF_PD_C | B10: = | D10: BNF_PD_C=56765.35 | E10: BNF_PD_C=57006.65 | F10: BNF_PD_C=57168.95 | G10: BNF_PD_C=56828.8 | H10: BNF_PD_C=56283 | I10: BNF_PD_C=56952.75 | J10: BNF_PD_C=56756 | K10: BNF_PD_C=5721.45 | L10: BNF_PD_C=57066.05 | M10: BNF_PD_C=56528.9 | N10: BNF_PD_C=56084.9 | O10: BNF_PD_C=56222 | P10: BNF_PD_C=56150.7 | Q10: BNF_PD_C=55961.95 | R10: BNF_PD_C=55617.6 | S10: BNF_PD_C=55619.35 | T10: BNF_PD_C=55360.25 | U10: BNF_PD_C=55411.15 | V10: BNF_PD_C=55521.15 | W10: BNF_PD_C=55004.9 | X10: BNF_PD_C=55510.75 | Y10: BNF_PD_C=55043.7 | Z10: BNF_PD_C=55181.45 | AA10: BNF_PD_C=55341.85 | AB10: BNF_PD_C=55734.9 | AC10: BNF_PD_C=55865.15 | AD10: BNF_PD_C=55698.5 | AE10: BNF_PD_C=55755.45 | AF10: BNF_PD_C=55149.4 | AG10: BNF_PD_C=55139.3 | AH10: BNF_PD_C=54450.45 | AI10: BNF_PD_C=53820 | AJ10: BNF_PD_C = 53655 | AK10: BNF_PD_C=54002.45 | AL10: BNF_PD_C=53661 | AM10: BNF_PD_C=54067.55 | AN10: BNF_PD_C=54075.45 | AO10: BNF_PD_C = 54115.55 | AP10: BNF_PD_C = 54186.9 | AQ10: BNF_PD_C = 54215.4 | AR10: BNF_PD_C = 55535.55 | AS10: BNF_PD_C = 54669.6 | AT10: BNF_PD_C = 54809.3 | AU10: BNF_PD_C = 54887.85 | AV10: BNF_PD_C = 55146.5 | AW10: BNF_PD_C = 55491.9 | AX10: BNF_PD_C = 55728.95 | AY10: BNF_PD_C = 55485.5 | AZ10: BNF_PD_C = 55284 | BA10: BNF_PD_C = 55509.75 | BB10: BNF_PD_C = 55121.5 | BC10: BNF_PD_C = 54976.20 | BD10: BNF_PD_C = 54389.35 | BE10: BNF_PD_C = 54461 | BF10: BNF_PD_C = 54635.85 | BG10: BNF_PD_C = 55347.95 | BH10: BNF_PD_C = 55589.25 | BI10: BNF_PD_C = 56104.85 | BJ10: BNF_PD_C = 56239.35 | BK10: BNF_PD_C = 56018.25 | BL10: BNF_PD_C = 56192.05 | BM10: BNF_PD_C = 56609.75 | BN10: BNF_PD_C = 56625 | BO10: BNF_PD_C = 56496.45 | BP10: BNF_PD_C = 56799.9 | BQ10: BNF_PD_C = 57422.55 | BR10: BNF_PD_C = 57713.35 | BS10: BNF_PD_C = 58007.2 | BT10: BNF_PD_C = 58078.05 | BU10: BNF_PD_C = 57699.6 | BV10: BNF_PD_C = 58114.25 | BW10: BNF_PD_C = 58214.1 | BX10: BNF_PD_C = 58385.25 | BY10: BNF_PD_C = 58031.1 | BZ10: BNF_PD_C = 57776.35 | CA10: BNF_PD_C = 58101.45 | CB10: BNF_PD_C = 57827.05 | CC10: BNF_PD_C = 57554.25 | CD10: BNF_PD_C = 57876.8 | CE10: BNF_PD_C = 57937.55 | CF10: BNF_PD_C = 58138.15 | CG10: BNF_PD_C = 58274.65 | CH10: BNF_PD_C = 58381 | CI10: BNF_PD_C = 58517.55 | CJ10: BNF_PD_C = 58962.7 | CK10: BNF_PD_C = 58899.25 | CL10: BNF_PD_C = 59216.05 | CM10: BNF_PD_C = 59347.7 | CN10: BNF_PD_C = 58867.7 | CO10: BNF_PD_C = 58835.35 | CP10: BNF_PD_C = 58820.3 | CQ10: BNF_PD_C = 59528.05 | CR10: BNF_PD_C = 59737.3 | CS10: BNF_PD_C = 59752.7 | CT10: BNF_PD_C = 59681.35 | CU10: BNF_PD_C = 59273.8 | CV10: BNF_PD_C = 59348.25 | CW10: BNF_PD_C = 59288.7 | CX10: BNF_PD_C = 59777.2 | CY10: BNF_PD_C = 59228.55 | CZ10: BNF_PD_C = 59222.35 | DA10: BNF_PD_C = 58960.4 | DB10: BNF_PD_C = 59209.85 | DC10: BNF_PD_C = 59389.95 | DD10: BNF_PD_C = 59461.8 | DE10: BNF_PD_C = 59034.6 | DF10: BNF_PD_C = 58926.75 | DG10: BNF_PD_C = 58912.85 | DH10: BNF_PD_C = 59069.2 | DI10: BNF_PD_C = 59304 | DJ10: BNF_PD_C = 59299.55 | DK10: BNF_PD_C = 59183.6 | DL10: BNF_PD_C = 59011.35 | DM10: BNF_PD_C = 58932.35 | DN10: BNF_PD_C = 59171.25 | DO10: BNF_PD_C = 59581.85 | DP10: BNF_PD_C = 59711.55 | DQ10: BNF_PD_C = 60150.95
A11: BNF_PD_L | B11: = | D11: BNF_PD_L=56594.25 | E11: BNF_PD_L=56707.8 | F11: BNF_PD_L=56937.6 | G11: BNF_PD_L=56780.15 | H11: BNF_PD_L=56204.85 | I11: BNF_PD_L=56255.7 | J11: BNF_PD_L=56692 | K11: BNF_PD_L=56715.8 | L11: BNF_PD_L=56850.9 | M11: BNF_PD_L=56439.4 | N11: BNF_PD_L=55997.45 | O11: BNF_PD_L=55843.25 | P11: BNF_PD_L=56064.55 | Q11: BNF_PD_L=55547.35 | R11: BNF_PD_L=55562.1 | S11: BNF_PD_L=55437.3 | T11: BNF_PD_L=55202.85 | U11: BNF_PD_L=55227.7 | V11: BNF_PD_L=54973.5 | W11: BNF_PD_L=54905.6 | X11: BNF_PD_L=54927.55 | Y11: BNF_PD_L=55001.5 | Z11: BNF_PD_L=55026.95 | AA11: BNF_PD_L=55074.3 | AB11: BNF_PD_L=55647.65 | AC11: BNF_PD_L=55608.15 | AD11: BNF_PD_L=55577.35 | AE11: BNF_PD_L=55708.2 | AF11: BNF_PD_L=55102.6 | AG11: BNF_PD_L=55048.4 | AH11: BNF_PD_L=54396.1 | AI11: BNF_PD_L=53768.45 | AJ11: BNF_PD_L = 53606.45 | AK11: BNF_PD_L=83658.18 | AL11: BNF_PD_L=53578 | AM11: BNF_PD_L=53561.75 | AN11: BNF_PD_L=53971.85 | AO11: BNF_PD_L = 53719.55 | AP11: BNF_PD_L = 54067.15 | AQ11: BNF_PD_L = 54080.15 | AR11: BNF_PD_L = 55399.55 | AS11: BNF_PD_L = 54402.4 | AT11: BNF_PD_L = 54580.35 | AU11: BNF_PD_L = 54807.5 | AV11: BNF_PD_L = 55780.9 | AW11: BNF_PD_L = 55146.9 | AX11: BNF_PD_L = 55491.3 | AY11: BNF_PD_L = 55355.9 | AZ11: BNF_PD_L = 55221 | BA11: BNF_PD_L = 55159 | BB11: BNF_PD_L = 55040.45 | BC11: BNF_PD_L = 54903.30 | BD11: BNF_PD_L = 54310.95 | BE11: BNF_PD_L = 54226.6 | BF11: BNF_PD_L = 54502.95 | BG11: BNF_PD_L = 54582.55 | BH11: BNF_PD_L = 55177 | BI11: BNF_PD_L = 55727.25 | BJ11: BNF_PD_L = 56025.05 | BK11: BNF_PD_L = 55821 | BL11: BNF_PD_L = 55843.9 | BM11: BNF_PD_L = 56152.45 | BN11: BNF_PD_L = 56327.4 | BO11: BNF_PD_L = 56230.15 | BP11: BNF_PD_L = 56491.85 | BQ11: BNF_PD_L = 56994.7 | BR11: BNF_PD_L = 57238.65 | BS11: BNF_PD_L = 57887.2 | BT11: BNF_PD_L = 57951.45 | BU11: BNF_PD_L = 57482.05 | BV11: BNF_PD_L = 57652.75 | BW11: BNF_PD_L = 57770.35 | BX11: BNF_PD_L = 58087.05 | BY11: BNF_PD_L = 57999.2 | BZ11: BNF_PD_L = 57656.95 | CA11: BNF_PD_L = 57718.4 | CB11: BNF_PD_L = 57714.8 | CC11: BNF_PD_L = 57521 | CD11: BNF_PD_L = 57157.85 | CE11: BNF_PD_L = 57846.2 | CF11: BNF_PD_L = 57594.25 | CG11: BNF_PD_L = 58171.85 | CH11: BNF_PD_L = 58127.1 | CI11: BNF_PD_L = 58050 | CJ11: BNF_PD_L = 58605.3 | CK11: BNF_PD_L = 58798.9 | CL11: BNF_PD_L = 58688.55 | CM11: BNF_PD_L = 59125.25 | CN11: BNF_PD_L = 58823.65 | CO11: BNF_PD_L = 58649.5 | CP11: BNF_PD_L = 58746.2 | CQ11: BNF_PD_L = 58783.05 | CR11: BNF_PD_L = 59523 | CS11: BNF_PD_L = 59598.95 | CT11: BNF_PD_L = 59527.6 | CU11: BNF_PD_L = 59251.9 | CV11: BNF_PD_L = 58925.7 | CW11: BNF_PD_L = 59062.15 | CX11: BNF_PD_L = 59106.55 | CY11: BNF_PD_L = 59030.6 | CZ11: BNF_PD_L = 58878.45 | DA11: BNF_PD_L = 58853.9 | DB11: BNF_PD_L = 58799.9 | DC11: BNF_PD_L = 59224.85 | DD11: BNF_PD_L = 59052.3 | DE11: BNF_PD_L = 58966.35 | DF11: BNF_PD_L = 58801.4 | DG11: BNF_PD_L = 58712.7 | DH11: BNF_PD_L = 58897.5 | DI11: BNF_PD_L = 59155.5 | DJ11: BNF_PD_L = 59216.75 | DK11: BNF_PD_L = 59118.25 | DL11: BNF_PD_L = 58947.05 | DM11: BNF_PD_L = 58809.55 | DN11: BNF_PD_L = 58737.6 | DO11: BNF_PD_L = 59187.1 | DP11: BNF_PD_L = 59569.65 | DQ11: BNF_PD_L = 59738.25
A13: BNF_R5 | B13: = | D13: BNF_R5=57527.15 | E13: BNF_R5=58102.95 | F13: BNF_R5=58036.95 | G13: BNF_R5=57971.3 | H13: BNF_R5=57476.4 | I13: BNF_R5=58883.2 | J13: BNF_R5=58163.7 | K13: BNF_R5=58619.45 | L13: BNF_R5=58224.4 | M13: BNF_R5=58265.1 | N13: BNF_R5=57469.6 | O13: BNF_R5=57405.6 | P13: BNF_R5=56778.15 | Q13: BNF_R5=58104.15 | R13: BNF_R5=56885.6 | S13: BNF_R5=56415.4 | T13: BNF_R5=56451.75 | U13: BNF_R5=56246.25 | V13: BNF_R5=57199.95 | W13: BNF_R5=56781 | X13: BNF_R5=57232.55 | Y13: BNF_R5=56376.55 | Z13: BNF_R5=55963.5 | AA13: BNF_R5=56360.85 | AB13: BNF_R5=56950.85 | AC13: BNF_R5=56784.75 | AD13: BNF_R5=56287.8 | AE13: BNF_R5=56437.25 | AF13: BNF_R5=56663.95 | AG13: BNF_R5=55770.65 | AH13: BNF_R5=56038.45 | AI13: BNF_R5=55269.85 | AJ13: BNF_R5 = 54791 | AK13: BNF_R5=54998.5 | AL13: BNF_R5=55048.9 | AM13: BNF_R5=55576.4 | AN13: BNF_R5=55226.95 | AO13: BNF_R5 = 55619.4 | AP13: BNF_R5 = 55280.45 | AQ13: BNF_R5 = 54894.45 | AR13: BNF_R5 = 55293.45 | AS13: BNF_R5 = 55587.1 | AT13: BNF_R5 = 55520.05 | AU13: BNF_R5 = 55407.45 | AV13: BNF_R5 = 56222.2 | AW13: BNF_R5 = 56528.7 | AX13: BNF_R5 = 56609.8 | AY13: BNF_R5 = 56271.4 | AZ13: BNF_R5 = 56359.55 | BA13: BNF_R5 = 56800.35 | BB13: BNF_R5 = 56246.7 | BC13: BNF_R5 = 55871.65 | BD13: BNF_R5 = 55782.95 | BE13: BNF_R5 = 55611.2 | BF13: BNF_R5 = 55357.05 | BG13: BNF_R5 = 55510 | BH13: BNF_R5 = 56752.05 | BI13: BNF_R5 = 57250.25 | BJ13: BNF_R5 = 57424.7 | BK13: BNF_R5 = 57210.05 | BL13: BNF_R5 = 57340.25 | BM13: BNF_R5 = 58180.4 | BN13: BNF_R5 = 57759.05 | BO13: BNF_R5 = 57731.25 | BP13: BNF_R5 = 57907.9 | BQ13: BNF_R5 = 58804.4 | BR13: BNF_R5 = 59251.85 | BS13: BNF_R5 = 58673.35 | BT13: BNF_R5 = 59581.05 | BU13: BNF_R5 = 59524.1 | BV13: BNF_R5 = 59602.3 | BW13: BNF_R5 = 59630.05 | BX13: BNF_R5 = 59377.95 | BY13: BNF_R5 = 58816.4 | BZ13: BNF_R5 = 59211.5 | CA13: BNF_R5 = 59463.8 | CB13: BNF_R5 = 58760.7 | CC13: BNF_R5 = 58554.8 | CD13: BNF_R5 = 60084.6 | CE13: BNF_R5 = 58553.65 | CF13: BNF_R5 = 59703.35 | CG13: BNF_R5 = 59092.55 | CH13: BNF_R5 = 59607.55 | CI13: BNF_R5 = 59933.75 | CJ13: BNF_R5 = 60006.4 | CK13: BNF_R5 = 59643.8 | CL13: BNF_R5 = 60735.2 | CM13: BNF_R5 = 60156.5 | CN13: BNF_R5 = 59835.55 | CO13: BNF_R5 = 60438.25 | CP13: BNF_R5 = 59824.9 | CQ13: BNF_R5 = 61577.5 | CR13: BNF_R5 = 60610.45 | CS13: BNF_R5 = 60500.55 | CT13: BNF_R5 = 61101.55 | CU13: BNF_R5 = 60225.15 | CV13: BNF_R5 = 60630.55 | CW13: BNF_R5 = 60499.5 | CX13: BNF_R5 = 61634.2 | CY13: BNF_R5 = 60900.5 | CZ13: BNF_R5 = 60456.5 | DA13: BNF_R5 = 60365.5 | DB13: BNF_R5 = 60801.2 | DC13: BNF_R5 = 60193.65 | DD13: BNF_R5 = 60719.95 | DE13: BNF_R5 = 59918.1 | DF13: BNF_R5 = 59728.75 | DG13: BNF_R5 = 60142.25 | DH13: BNF_R5 = 59693.55 | DI13: BNF_R5 = 59856.8 | DJ13: BNF_R5 = 59760.2 | DK13: BNF_R5 = 60045.15 | DL13: BNF_R5 = 59577.85 | DM13: BNF_R5 = 59745.25 | DN13: BNF_R5 = 60564.35 | DO13: BNF_R5 = 61064.65 | DP13: BNF_R5 = 60163.8 | DQ13: BNF_R5 = 61374.7
A14: BNF_R4 | B14: = | D14: BNF_R4=57369.45 | E14: BNF_R4=5780.95 | F14: BNF_R4=57846.85 | G14: BNF_R4=57794.2 | H14: BNF_R4=57283.6 | I14: BNF_R4=58408.25 | J14: BNF_R4=57944.3 | K14: BNF_R4=58276.85 | L14: BNF_R4=57997.45 | M14: BNF_R4=57991.5 | N14: BNF_R4=57246.8 | O14: BNF_R4=57128.3 | P14: BNF_R4=56663.9 | Q14: BNF_R4=57679.65 | R14: BNF_R4=56688.6 | S14: BNF_R4=56249.65 | T14: BNF_R4=56250.85 | U14: BNF_R4=560754.55 | V14: BNF_R4=56803.65 | W14: BNF_R4=56498.8 | X14: BNF_R4=56819.95 | Y14: BNF_R4=56174.1 | Z14: BNF_R4=55807.65 | AA14: BNF_R4=56138.85 | AB14: BNF_R4=56752.2 | AC14: BNF_R4=56579.95 | AD14: BNF_R4=56169 | AE14: BNF_R4=56326.35 | AF14: BNF_R4=56434.2 | AG14: BNF_R4=55654.5 | AH14: BNF_R4=55796.05 | AI14: BNF_R4=55047.95 | AJ14: BNF_R4 = 54614.75 | AK14: BNF_R4=54757.85 | AL14: BNF_R4=54826.9 | AM14: BNF_R4=55216.35 | AN14: BNF_R4=55032.85 | AO14: BNF_R4 = 55291.55 | AP14: BNF_R4 = 55090 | AQ14: BNF_R4 = 54758.5 | AR14: BNF_R4 = 55146.4 | AS14: BNF_R4 = 55379.7 | AT14: BNF_R4 = 55353.1 | AU14: BNF_R4 = 55310.25 | AV14: BNF_R4 = 55963 | AW14: BNF_R4 = 56281.7 | AX14: BNF_R4 = 56416.15 | AY14: BNF_R4 = 56125.75 | AZ14: BNF_R4 = 56186.25 | BA14: BNF_R4 = 56515.75 | BB14: BNF_R4 = 56062.8 | BC14: BNF_R4 = 55722.90 | BD14: BNF_R4 = 55561.45 | BE14: BNF_R4 = 55379.9 | BF14: BNF_R4 = 55216.05 | BG14: BNF_R4 = 56996.35 | BH14: BNF_R4 = 56468.15 | BI14: BNF_R4 = 56978.75 | BJ14: BNF_R4 = 57194.15 | BK14: BNF_R4 = 56983.45 | BL14: BNF_R4 = 57076.75 | BM14: BNF_R4 = 57825.35 | BN14: BNF_R4 = 57512 | BO14: BNF_R4 = 57478.75 | BP14: BNF_R4 = 57661.6 | BQ14: BNF_R4 = 58484.75 | BR14: BNF_R4 = 58896.45 | BS14: BNF_R4 = 58543.9 | BT14: BNF_R4 = 59330.15 | BU14: BNF_R4 = 59201.3 | BV14: BNF_R4 = 59257.85 | BW14: BNF_R4 = 59301 | BX14: BNF_R4 = 59150.95 | BY14: BNF_R4 = 58695.1 | BZ14: BNF_R4 = 58972.35 | CA14: BNF_R4 = 59159.75 | CB14: BNF_R4 = 58600.45 | CC14: BNF_R4 = 58402.35 | CD14: BNF_R4 = 59563.8 | CE14: BNF_R4 = 58439.55 | CF14: BNF_R4 = 59324.35 | CG14: BNF_R4 = 58946.35 | CH14: BNF_R4 = 59359.65 | CI14: BNF_R4 = 59597.85 | CJ14: BNF_R4 = 59755.2 | CK14: BNF_R4 = 59508.75 | CL14: BNF_R4 = 60367.45 | CM14: BNF_R4 = 59977.4 | CN14: BNF_R4 = 59684.7 | CO14: BNF_R4 = 60156.15 | CP14: BNF_R4 = 59660.2 | CQ14: BNF_R4 = 61071.85 | CR14: BNF_R4 = 60424.5 | CS14: BNF_R4 = 60349.8 | CT14: BNF_R4 = 60854.75 | CU14: BNF_R4 = 60083 | CV14: BNF_R4 = 60326.65 | CW14: BNF_R4 = 60261.8 | CX14: BNF_R4 = 61177.3 | CY14: BNF_R4 = 60603.65 | CZ14: BNF_R4 = 60181.95 | DA14: BNF_R4 = 60134.4 | DB14: BNF_R4 = 60456.75 | DC14: BNF_R4 = 60031.65 | DD14: BNF_R4 = 60423.2 | DE14: BNF_R4 = 59772.4 | DF14: BNF_R4 = 59578.35 | DG14: BNF_R4 = 59909.45 | DH14: BNF_R4 = 59555.3 | DI14: BNF_R4 = 59735.4 | DJ14: BNF_R4 = 59670.75 | DK14: BNF_R4 = 59903.4 | DL14: BNF_R4 = 59478.55 | DM14: BNF_R4 = 59594.05 | DN14: BNF_R4 = 60241.45 | DO14: BNF_R4 = 60740.05 | DP14: BNF_R4 = 60058.65 | DQ14: BNF_R4 = 61081.95
A15: BNF_R3 | B15: = | D15: BNF_R3=57211.75 | E15: BNF_R3=57618.95 | F15: BNF_R3=57656.75 | G15: BNF_R3=57617.1 | H15: BNF_R3=57090.8 | I15: BNF_R3=57933.3 | J15: BNF_R3=57724.9 | K15: BNF_R3=57934.25 | L15: BNF_R3=57770.5 | M15: BNF_R3=57717.9 | N15: BNF_R3=57024 | O15: BNF_R3=5651 | P15: BNF_R3=56549.65 | Q15: BNF_R3=57255.15 | R15: BNF_R3=56491.6 | S15: BNF_R3=56083.9 | T15: BNF_R3=56049.95 | U15: BNF_R3=55902.85 | V15: BNF_R3=56407.35 | W15: BNF_R3=56216.8 | X15: BNF_R3=56407.35 | Y15: BNF_R3=55971.65 | Z15: BNF_R3=55651.8 | AA15: BNF_R3=55916.85 | AB15: BNF_R3=56553.55 | AC15: BNF_R3=56375.15 | AD15: BNF_R3=56050.2 | AE15: BNF_R3=56215.45 | AF15: BNF_R3=56204.45 | AG15: BNF_R3=55538.35 | AH15: BNF_R3=55553.65 | AI15: BNF_R3=54826.05 | AJ15: BNF_R3 = 54438.5 | AK15: BNF_R3=54517.2 | AL15: BNF_R3=54604.9 | AM15: BNF_R3=54856.3 | AN15: BNF_R3=54838.75 | AO15: BNF_R3 = 54963.7 | AP15: BNF_R3 = 54899.55 | AQ15: BNF_R3 = 54622.55 | AR15: BNF_R3 = 54999.35 | AS15: BNF_R3 = 55172.3 | AT15: BNF_R3 = 55186.15 | AU15: BNF_R3 = 55213.05 | AV15: BNF_R3 = 55703.8 | AW15: BNF_R3 = 56034.7 | AX15: BNF_R3 = 56222.5 | AY15: BNF_R3 = 55980.1 | AZ15: BNF_R3 = 56012.95 | BA15: BNF_R3 = 56231.15 | BB15: BNF_R3 = 55878.9 | BC15: BNF_R3 = 55574.15 | BD15: BNF_R3 = 55339.95 | BE15: BNF_R3 = 55148.6 | BF15: BNF_R3 = 55075.05 | BG15: BNF_R3 = 56466.5 | BH15: BNF_R3 = 56184.25 | BI15: BNF_R3 = 56707.25 | BJ15: BNF_R3 = 56963.6 | BK15: BNF_R3 = 56756.85 | BL15: BNF_R3 = 56813.25 | BM15: BNF_R3 = 57470.3 | BN15: BNF_R3 = 57264.95 | BO15: BNF_R3 = 57226.25 | BP15: BNF_R3 = 57415.3 | BQ15: BNF_R3 = 58165.1 | BR15: BNF_R3 = 58541.05 | BS15: BNF_R3 = 58414.45 | BT15: BNF_R3 = 59079.25 | BU15: BNF_R3 = 58878.5 | BV15: BNF_R3 = 58913.4 | BW15: BNF_R3 = 58971.95 | BX15: BNF_R3 = 58923.95 | BY15: BNF_R3 = 58573.8 | BZ15: BNF_R3 = 58733.2 | CA15: BNF_R3 = 58885.7 | CB15: BNF_R3 = 58440.2 | CC15: BNF_R3 = 58249.9 | CD15: BNF_R3 = 59043 | CE15: BNF_R3 = 58325.45 | CF15: BNF_R3 = 58945.35 | CG15: BNF_R3 = 58800.15 | CH15: BNF_R3 = 59111.75 | CI15: BNF_R3 = 59261.95 | CJ15: BNF_R3 = 59504 | CK15: BNF_R3 = 59373.7 | CL15: BNF_R3 = 59999.7 | CM15: BNF_R3 = 59798.3 | CN15: BNF_R3 = 59533.85 | CO15: BNF_R3 = 59874.05 | CP15: BNF_R3 = 59495.5 | CQ15: BNF_R3 = 60566.2 | CR15: BNF_R3 = 60238.55 | CS15: BNF_R3 = 60199.05 | CT15: BNF_R3 = 60607.95 | CU15: BNF_R3 = 59940.85 | CV15: BNF_R3 = 60022.75 | CW15: BNF_R3 = 60024.1 | CX15: BNF_R3 = 60720.4 | CY15: BNF_R3 = 60306.8 | CZ15: BNF_R3 = 59907.4 | DA15: BNF_R3 = 59903.25 | DB15: BNF_R3 = 60112.3 | DC15: BNF_R3 = 59869.65 | DD15: BNF_R3 = 60126.45 | DE15: BNF_R3 = 59626.7 | DF15: BNF_R3 = 59427.95 | DG15: BNF_R3 = 59676.65 | DH15: BNF_R3 = 59417.05 | DI15: BNF_R3 = 59614 | DJ15: BNF_R3 = 59581.3 | DK15: BNF_R3 = 59761.65 | DL15: BNF_R3 = 59379.25 | DM15: BNF_R3 = 59442.85 | DN15: BNF_R3 = 59918.55 | DO15: BNF_R3 = 60415.45 | DP15: BNF_R3 = 59953.5 | DQ15: BNF_R3 = 60789.2
A16: BNF_R2 | B16: = | D16: BNF_R2=57054 | E16: BNF_R2=5737.95 | F16: BNF_R2=57466.65 | G16: BNF_R2=57439.95 | H16: BNF_R2=56897.95 | I16: BNF_R2=57458.4 | J16: BNF_R2=57505.55 | K16: BNF_R2=57591.6 | L16: BNF_R2=57543.55 | M16: BNF_R2=57444.3 | N16: BNF_R2=56801.2 | O16: BNF_R2=56573.7 | P16: BNF_R2=56435.4 | Q16: BNF_R2=56830.7 | R16: BNF_R2=56294.6 | S16: BNF_R2=55918.2 | T16: BNF_R2=55849.05 | U16: BNF_R2=55731.1 | V16: BNF_R2=56011.1 | W16: BNF_R2=5593.7 | X16: BNF_R2=55994.75 | Y16: BNF_R2=55769.15 | Z16: BNF_R2=55495.9 | AA16: BNF_R2=55694.8 | AB16: BNF_R2=56354.95 | AC16: BNF_R2=6170.35 | AD16: BNF_R2=55931.4 | AE16: BNF_R2=56104.55 | AF16: BNF_R2=55974.75 | AG16: BNF_R2=55422.15 | AH16: BNF_R2=55311.3 | AI16: BNF_R2=54604.15 | AJ16: BNF_R2 = 54262.25 | AK16: BNF_R2=54276.5 | AL16: BNF_R2=54382.95 | AM16: BNF_R2=54496.2 | AN16: BNF_R2=54644.65 | AO16: BNF_R2 = 54635.9 | AP16: BNF_R2 = 54709.15 | AQ16: BNF_R2 = 54486.6 | AR16: BNF_R2 = 54852.25 | AS16: BNF_R2 = 54964.85 | AT16: BNF_R2 = 55019.2 | AU16: BNF_R2 = 55115.9 | AV16: BNF_R2 = 55444.65 | AW16: BNF_R2 = 55787.75 | AX16: BNF_R2 = 56028.9 | AY16: BNF_R2 = 55834.4 | AZ16: BNF_R2 = 55839.65 | BA16: BNF_R2 = 55946.6 | BB16: BNF_R2 = 55695 | BC16: BNF_R2 = 55425.40 | BD16: BNF_R2 = 55118.5 | BE16: BNF_R2 = 54917.35 | BF16: BNF_R2 = 54934.05 | BG16: BNF_R2 = 55936.6 | BH16: BNF_R2 = 55900.35 | BI16: BNF_R2 = 56435.7 | BJ16: BNF_R2 = 56733 | BK16: BNF_R2 = 56530.2 | BL16: BNF_R2 = 56549.75 | BM16: BNF_R2 = 57115.3 | BN16: BNF_R2 = 57017.95 | BO16: BNF_R2 = 56973.8 | BP16: BNF_R2 = 57169 | BQ16: BNF_R2 = 57845.45 | BR16: BNF_R2 = 58185.6 | BS16: BNF_R2 = 58285 | BT16: BNF_R2 = 58828.4 | BU16: BNF_R2 = 58555.7 | BV16: BNF_R2 = 58569 | BW16: BNF_R2 = 58642.85 | BX16: BNF_R2 = 58696.9 | BY16: BNF_R2 = 58452.5 | BZ16: BNF_R2 = 58494.1 | CA16: BNF_R2 = 58551.6 | CB16: BNF_R2 = 58279.9 | CC16: BNF_R2 = 58097.5 | CD16: BNF_R2 = 58522.15 | CE16: BNF_R2 = 58211.3 | CF16: BNF_R2 = 58566.35 | CG16: BNF_R2 = 58653.9 | CH16: BNF_R2 = 58863.85 | CI16: BNF_R2 = 58926.05 | CJ16: BNF_R2 = 59252.75 | CK16: BNF_R2 = 59238.7 | CL16: BNF_R2 = 59632 | CM16: BNF_R2 = 59619.2 | CN16: BNF_R2 = 59383 | CO16: BNF_R2 = 59592 | CP16: BNF_R2 = 59330.85 | CQ16: BNF_R2 = 60060.6 | CR16: BNF_R2 = 60052.55 | CS16: BNF_R2 = 60048.25 | CT16: BNF_R2 = 60361.1 | CU16: BNF_R2 = 59798.7 | CV16: BNF_R2 = 59718.8 | CW16: BNF_R2 = 59786.4 | CX16: BNF_R2 = 60263.5 | CY16: BNF_R2 = 60010 | CZ16: BNF_R2 = 59632.8 | DA16: BNF_R2 = 59672.05 | DB16: BNF_R2 = 59767.8 | DC16: BNF_R2 = 59707.7 | DD16: BNF_R2 = 59829.75 | DE16: BNF_R2 = 59480.95 | DF16: BNF_R2 = 59277.6 | DG16: BNF_R2 = 59443.8 | DH16: BNF_R2 = 59278.8 | DI16: BNF_R2 = 59492.6 | DJ16: BNF_R2 = 59491.8 | DK16: BNF_R2 = 59619.9 | DL16: BNF_R2 = 59279.95 | DM16: BNF_R2 = 59291.65 | DN16: BNF_R2 = 59595.6 | DO16: BNF_R2 = 60090.8 | DP16: BNF_R2 = 59848.35 | DQ16: BNF_R2 = 60496.5
A17: BNF_R1 | B17: = | D17: BNF_R1=56909.7 | E17: BNF_R1=57191.8 | F17: BNF_R1=57317.8 | G17: BNF_R1=57134.4 | H17: BNF_R1=56590.5 | I17: BNF_R1=57205.55 | J17: BNF_R1=57130.75 | K17: BNF_R1=57401.05 | L17: BNF_R1=57304.8 | M17: BNF_R1=56956.6 | N17: BNF_R1=56443.05 | O17: BNF_R1=56397.85 | P17: BNF_R1=56293.05 | Q17: BNF_R1=56396.3 | R17: BNF_R1=55956.1 | S17: BNF_R1=55768.5 | T17: BNF_R1=55604.65 | U17: BNF_R1=55571.1 | V17: BNF_R1=55766.1 | W17: BNF_R1=55469.8 | X17: BNF_R1=55752.75 | Y17: BNF_R1=55406.45 | Z17: BNF_R1=55338.7 | AA17: BNF_R1=55518.35 | AB17: BNF_R1=56044.9 | AC17: BNF_R1=56017.75 | AD17: BNF_R1=55814.95 | AE17: BNF_R1=55930 | AF17: BNF_R1=55562.05 | AG17: BNF_R1=55280.75 | AH17: BNF_R1=54880.85 | AI17: BNF_R1=54212.25 | AJ17: BNF_R1 = 53958.95 | AK17: BNF_R1=54139.5 | AL17: BNF_R1=54021.95 | AM17: BNF_R1=54281.9 | AN17: BNF_R1=54360.05 | AO17: BNF_R1 = 54375.2 | AP17: BNF_R1 = 54448 | AQ17: BNF_R1 = 54351.35 | AR17: BNF_R1 = 54694.15 | AS17: BNF_R1 = 54817.25 | AT17: BNF_R1 = 54914.25 | AU17: BNF_R1 = 55001.85 | AV17: BNF_R1 = 55296.1 | AW17: BNF_R1 = 55640.5 | AX17: BNF_R1 = 55878.15 | AY17: BNF_R1 = 55646.65 | AZ17: BNF_R1 = 55562.2 | BA17: BNF_R1 = 55728.15 | BB17: BNF_R1 = 55408.25 | BC17: BNF_R1 = 55200.80 | BD17: BNF_R1 = 54753.9 | BE17: BNF_R1 = 54689.15 | BF17: BNF_R1 = 54784.95 | BG17: BNF_R1 = 55642.3 | BH17: BNF_R1 = 55744.8 | BI17: BNF_R1 = 56270.3 | BJ17: BNF_R1 = 56486.2 | BK17: BNF_R1 = 56274.25 | BL17: BNF_R1 = 56370.9 | BM17: BNF_R1 = 56862.5 | BN17: BNF_R1 = 56821.45 | BO17: BNF_R1 = 56735.1 | BP17: BNF_R1 = 56984.45 | BQ17: BNF_R1 = 57634 | BR17: BNF_R1 = 57949.5 | BS17: BNF_R1 = 58146.1 | BT17: BNF_R1 = 58453.2 | BU17: BNF_R1 = 58127.65 | BV17: BNF_R1 = 58341.6 | BW17: BNF_R1 = 58428.5 | BX17: BNF_R1 = 58541.1 | BY17: BNF_R1 = 58241.8 | BZ17: BNF_R1 = 58135.2 | CA17: BNF_R1 = 58326.55 | CB17: BNF_R1 = 58053.5 | CC17: BNF_R1 = 57825.85 | CD17: BNF_R1 = 58199.5 | CE17: BNF_R1 = 58074.45 | CF17: BNF_R1 = 58352.25 | CG17: BNF_R1 = 58464.3 | CH17: BNF_R1 = 58622.9 | CI17: BNF_R1 = 58721.8 | CJ17: BNF_R1 = 59107.75 | CK17: BNF_R1 = 59068.95 | CL17: BNF_R1 = 59424 | CM17: BNF_R1 = 59483.45 | CN17: BNF_R1 = 59125.35 | CO17: BNF_R1 = 59213.65 | CP17: BNF_R1 = 59075.55 | CQ17: BNF_R1 = 59794.3 | CR17: BNF_R1 = 59894.95 | CS17: BNF_R1 = 59900.5 | CT17: BNF_R1 = 60021.25 | CU17: BNF_R1 = 59536.25 | CV17: BNF_R1 = 59533.55 | CW17: BNF_R1 = 59537.55 | CX17: BNF_R1 = 60020.35 | CY17: BNF_R1 = 59624.25 | CZ17: BNF_R1 = 59427.6 | DA17: BNF_R1 = 59316.25 | DB17: BNF_R1 = 59488.85 | DC17: BNF_R1 = 59548.8 | DD17: BNF_R1 = 59645.75 | DE17: BNF_R1 = 59257.8 | DF17: BNF_R1 = 59102.15 | DG17: BNF_R1 = 59178.35 | DH17: BNF_R1 = 59174 | DI17: BNF_R1 = 59398.3 | DJ17: BNF_R1 = 59395.7 | DK17: BNF_R1 = 59401.75 | DL17: BNF_R1 = 59145.65 | DM17: BNF_R1 = 59112 | DN17: BNF_R1 = 59383.45 | DO17: BNF_R1 = 59836.35 | DP17: BNF_R1 = 59779.95 | DQ17: BNF_R1 = 60323.7
A18: BNF_CP | B18: = | D18: BNF_CP=56751.95 | E18: BNF_CP=56949.8 | F18: BNF_CP=57127.7 | G18: BNF_CP=56957.25 | H18: BNF_CP=56397.65 | I18: BNF_CP=56730.65 | J18: BNF_CP=56911.4 | K18: BNF_CP=57058.4 | L18: BNF_CP=57077.85 | M18: BNF_CP=56713 | N18: BNF_CP=56220.25 | O18: BNF_CP=56120.55 | P18: BNF_CP=56178.8 | Q18: BNF_CP=55971.85 | R18: BNF_CP=55759.1 | S18: BNF_CP=55603.05 | T18: BNF_CP=55403.75 | U18: BNF_CP=55399.4 | V18: BNF_CP=55369.85 | W18: BNF_CP=55187.7 | X18: BNF_CP=55340.15 | Y18: BNF_CP=55203.95 | Z18: BNF_CP=55182 | AA18: BNF_CP=55296.3 | AB18: BNF_CP=55846.3 | AC18: BNF_CP=55812.95 | AD18: BNF_CP=55896.15 | AE18: BNF_CP=55819.1 | AF18: BNF_CP=55332.35 | AG18: BNF_CP=55184.55 | AH18: BNF_CP=54638.5 | AI18: BNF_CP=53990.35 | AJ18: BNF_CP = 53782.7 | AK18: BNF_CP=53898.8 | AL18: BNF_CP=53800 | AM18: BNF_CP=53921.8 | AN18: BNF_CP=54165.95 | AO18: BNF_CP = 54047.4 | AP18: BNF_CP = 54257.6 | AQ18: BNF_CP = 54215.4 | AR18: BNF_CP = 54547.05 | AS18: BNF_CP = 54609.8 | AT18: BNF_CP = 54747.3 | AU18: BNF_CP = 54904.7 | AV18: BNF_CP = 55036.95 | AW18: BNF_CP = 55393.55 | AX18: BNF_CP = 55684.55 | AY18: BNF_CP = 55500.95 | AZ18: BNF_CP = 55388.9 | BA18: BNF_CP = 55443.6 | BB18: BNF_CP = 55224.35 | BC18: BNF_CP = 55052.05 | BD18: BNF_CP = 54532.45 | BE18: BNF_CP = 54457.9 | BF18: BNF_CP = 54643.95 | BG18: BNF_CP = 55112.4 | BH18: BNF_CP = 55460.9 | BI18: BNF_CP = 55998.75 | BJ18: BNF_CP = 56255.6 | BK18: BNF_CP = 56047.6 | BL18: BNF_CP = 56107.4 | BM18: BNF_CP = 56507.5 | BN18: BNF_CP = 56574.45 | BO18: BNF_CP = 56482.65 | BP18: BNF_CP = 56738.15 | BQ18: BNF_CP = 57314.35 | BR18: BNF_CP = 57594.05 | BS18: BNF_CP = 58016.65 | BT18: BNF_CP = 58202.35 | BU18: BNF_CP = 57804.85 | BV18: BNF_CP = 57997.2 | BW18: BNF_CP = 58099.4 | BX18: BNF_CP = 58314.05 | BY18: BNF_CP = 58120.5 | BZ18: BNF_CP = 57896.1 | CA18: BNF_CP = 58022.45 | CB18: BNF_CP = 57893.2 | CC18: BNF_CP = 57673.45 | CD18: BNF_CP = 57678.65 | CE18: BNF_CP = 57960.3 | CF18: BNF_CP = 57973.25 | CG18: BNF_CP = 58318.05 | CH18: BNF_CP = 58375 | CI18: BNF_CP = 58385.9 | CJ18: BNF_CP = 58856.5 | CK18: BNF_CP = 58933.95 | CL18: BNF_CP = 59056.3 | CM18: BNF_CP = 59304.35 | CN18: BNF_CP = 58974.5 | CO18: BNF_CP = 58931.6 | CP18: BNF_CP = 58910.9 | CQ18: BNF_CP = 59288.7 | CR18: BNF_CP = 59708.95 | CS18: BNF_CP = 59749.7 | CT18: BNF_CP = 59774.4 | CU18: BNF_CP = 59394.1 | CV18: BNF_CP = 59229.6 | CW18: BNF_CP = 59299.85 | CX18: BNF_CP = 59563.45 | CY18: BNF_CP = 59327.45 | CZ18: BNF_CP = 59153 | DA18: BNF_CP = 59085.05 | DB18: BNF_CP = 59144.35 | DC18: BNF_CP = 59386.85 | DD18: BNF_CP = 59349.05 | DE18: BNF_CP = 59112.05 | DF18: BNF_CP = 58951.8 | DG18: BNF_CP = 58945.5 | DH18: BNF_CP = 59035.75 | DI18: BNF_CP = 59276.9 | DJ18: BNF_CP = 59306.2 | DK18: BNF_CP = 59260 | DL18: BNF_CP = 59046.35 | DM18: BNF_CP = 58960.75 | DN18: BNF_CP = 59060.5 | DO18: BNF_CP = 59511.7 | DP18: BNF_CP = 59674.8 | DQ18: BNF_CP = 60031
A19: BNF_S1 | B19: = | D19: BNF_S1=56607.65 | E19: BNF_S1=56764.65 | F19: BNF_S1=56978.85 | G19: BNF_S1=56651.7 | H19: BNF_S1=56090.2 | I19: BNF_S1=56477.8 | J19: BNF_S1=56536.6 | K19: BNF_S1=56867.85 | L19: BNF_S1=56839.1 | M19: BNF_S1=56255.3 | N19: BNF_S1=55862.1 | O19: BNF_S1=55944.7 | P19: BNF_S1=56036.45 | Q19: BNF_S1=55537.45 | R19: BNF_S1=55420.6 | S19: BNF_S1=55453.6 | T19: BNF_S1=55159.35 | U19: BNF_S1=55239.45 | V19: BNF_S1=55124.85 | W19: BNF_S1=54722.8 | X19: BNF_S1=55098.15 | Y19: BNF_S1=54841.25 | Z19: BNF_S1=55025.6 | AA19: BNF_S1=5519.85 | AB19: BNF_S1=55536.25 | AC19: BNF_S1=55660.35 | AD19: BNF_S1=55579.7 | AE19: BNF_S1=55644.55 | AF19: BNF_S1=54919.65 | AG19: BNF_S1=55023.15 | AH19: BNF_S1=54208.05 | AI19: BNF_S1=53598.45 | AJ19: BNF_S1 = 53479.4 | AK19: BNF_S1=53761 | AL19: BNF_S1=53439 | AM19: BNF_S1=53707.5 | AN19: BNF_S1=53881.35 | AO19: BNF_S1 = 53786.7 | AP19: BNF_S1 = 53996.45 | AQ19: BNF_S1 = 54080.15 | AR19: BNF_S1 = 54388.95 | AS19: BNF_S1 = 54462.2 | AT19: BNF_S1 = 54642.35 | AU19: BNF_S1 = 54790.65 | AV19: BNF_S1 = 54888.4 | AW19: BNF_S1 = 55246.3 | AX19: BNF_S1 = 55533.8 | AY19: BNF_S1 = 55313.2 | AZ19: BNF_S1 = 55111.45 | BA19: BNF_S1 = 55225.15 | BB19: BNF_S1 = 54937.6 | BC19: BNF_S1 = 54827.45 | BD19: BNF_S1 = 54167.85 | BE19: BNF_S1 = 54229.7 | BF19: BNF_S1 = 54494.85 | BG19: BNF_S1 = 54818.1 | BH19: BNF_S1 = 55305.35 | BI19: BNF_S1 = 55833.35 | BJ19: BNF_S1 = 56008.8 | BK19: BNF_S1 = 55791.65 | BL19: BNF_S1 = 55928.55 | BM19: BNF_S1 = 56254.7 | BN19: BNF_S1 = 56377.95 | BO19: BNF_S1 = 56243.95 | BP19: BNF_S1 = 56553.6 | BQ19: BNF_S1 = 57102.9 | BR19: BNF_S1 = 57357.95 | BS19: BNF_S1 = 57877.75 | BT19: BNF_S1 = 57827.15 | BU19: BNF_S1 = 57376.8 | BV19: BNF_S1 = 57769.8 | BW19: BNF_S1 = 57885.05 | BX19: BNF_S1 = 58158.25 | BY19: BNF_S1 = 57909.8 | BZ19: BNF_S1 = 57537.2 | CA19: BNF_S1 = 57797.4 | CB19: BNF_S1 = 57666.8 | CC19: BNF_S1 = 57401.8 | CD19: BNF_S1 = 57356 | CE19: BNF_S1 = 57823.45 | CF19: BNF_S1 = 57759.15 | CG19: BNF_S1 = 58128.45 | CH19: BNF_S1 = 58134.05 | CI19: BNF_S1 = 58181.65 | CJ19: BNF_S1 = 58711.5 | CK19: BNF_S1 = 58764.2 | CL19: BNF_S1 = 58848.3 | CM19: BNF_S1 = 59168.6 | CN19: BNF_S1 = 58716.85 | CO19: BNF_S1 = 58553.25 | CP19: BNF_S1 = 58655.6 | CQ19: BNF_S1 = 59022.4 | CR19: BNF_S1 = 59551.35 | CS19: BNF_S1 = 59601.95 | CT19: BNF_S1 = 59434.55 | CU19: BNF_S1 = 59131.65 | CV19: BNF_S1 = 59044.35 | CW19: BNF_S1 = 59051 | CX19: BNF_S1 = 59320.3 | CY19: BNF_S1 = 58941.7 | CZ19: BNF_S1 = 58947.8 | DA19: BNF_S1 = 58729.25 | DB19: BNF_S1 = 58865.4 | DC19: BNF_S1 = 59227.95 | DD19: BNF_S1 = 59165.05 | DE19: BNF_S1 = 58888.9 | DF19: BNF_S1 = 58776.35 | DG19: BNF_S1 = 58680.05 | DH19: BNF_S1 = 58930.95 | DI19: BNF_S1 = 59182.6 | DJ19: BNF_S1 = 59210.1 | DK19: BNF_S1 = 59041.85 | DL19: BNF_S1 = 58912.05 | DM19: BNF_S1 = 58781.15 | DN19: BNF_S1 = 58848.35 | DO19: BNF_S1 = 59257.25 | DP19: BNF_S1 = 59606.4 | DQ19: BNF_S1 = 59858.2
A20: BNF_S2 | B20: = | D20: BNF_S2=56449.9 | E20: BNF_S2=56522.65 | F20: BNF_S2=56788.75 | G20: BNF_S2=56474.55 | H20: BNF_S2=55897.35 | I20: BNF_S2=56002.9 | J20: BNF_S2=56317.25 | K20: BNF_S2=56525.2 | L20: BNF_S2=56612.15 | M20: BNF_S2=55981.7 | N20: BNF_S2=55639.3 | O20: BNF_S2=55667.4 | P20: BNF_S2=55922.2 | Q20: BNF_S2=55113 | R20: BNF_S2=55223.6 | S20: BNF_S2=55287.9 | T20: BNF_S2=54958.45 | U20: BNF_S2=55067.7 | V20: BNF_S2=54728.6 | W20: BNF_S2=54440.7 | X20: BNF_S2=54685.55 | Y20: BNF_S2=54638.75 | Z20: BNF_S2=54869.7 | AA20: BNF_S2=54897.8 | AB20: BNF_S2=55337.65 | AC20: BNF_S2=55455.55 | AD20: BNF_S2=55460.9 | AE20: BNF_S2=55533.65 | AF20: BNF_S2=54689.95 | AG20: BNF_S2=54906.95 | AH20: BNF_S2=53965.7 | AI20: BNF_S2=53376.55 | AJ20: BNF_S2 = 53303.15 | AK20: BNF_S2=53521.1 | AL20: BNF_S2=53217.05 | AM20: BNF_S2=53347.4 | AN20: BNF_S2=53687.25 | AO20: BNF_S2 = 53458.9 | AP20: BNF_S2 = 53806.05 | AQ20: BNF_S2 = 53944.2 | AR20: BNF_S2 = 54241.85 | AS20: BNF_S2 = 54254.75 | AT20: BNF_S2 = 54475.4 | AU20: BNF_S2 = 54693.5 | AV20: BNF_S2 = 54629.25 | AW20: BNF_S2 = 54999.35 | AX20: BNF_S2 = 55340.2 | AY20: BNF_S2 = 55167.5 | AZ20: BNF_S2 = 54938.15 | BA20: BNF_S2 = 54940.6 | BB20: BNF_S2 = 54753.7 | BC20: BNF_S2 = 54678.70 | BD20: BNF_S2 = 53946.4 | BE20: BNF_S2 = 53998.45 | BF20: BNF_S2 = 54353.85 | BG20: BNF_S2 = 54288.2 | BH20: BNF_S2 = 55021.45 | BI20: BNF_S2 = 55561.8 | BJ20: BNF_S2 = 55778.2 | BK20: BNF_S2 = 55565 | BL20: BNF_S2 = 55665.05 | BM20: BNF_S2 = 55899.7 | BN20: BNF_S2 = 56130.95 | BO20: BNF_S2 = 55991.5 | BP20: BNF_S2 = 56307.3 | BQ20: BNF_S2 = 56783.25 | BR20: BNF_S2 = 57002.5 | BS20: BNF_S2 = 57748.3 | BT20: BNF_S2 = 57576.3 | BU20: BNF_S2 = 57054 | BV20: BNF_S2 = 57425.4 | BW20: BNF_S2 = 57555.95 | BX20: BNF_S2 = 57931.2 | BY20: BNF_S2 = 57788.5 | BZ20: BNF_S2 = 57298.1 | CA20: BNF_S2 = 57493.3 | CB20: BNF_S2 = 58506.5 | CC20: BNF_S2 = 57249.4 | CD20: BNF_S2 = 56835.15 | CE20: BNF_S2 = 57709.3 | CF20: BNF_S2 = 57380.15 | CG20: BNF_S2 = 57982.2 | CH20: BNF_S2 = 57886.15 | CI20: BNF_S2 = 57845.75 | CJ20: BNF_S2 = 58460.25 | CK20: BNF_S2 = 58629.2 | CL20: BNF_S2 = 58480.6 | CM20: BNF_S2 = 58989.5 | CN20: BNF_S2 = 58566 | CO20: BNF_S2 = 58271.2 | CP20: BNF_S2 = 58490.95 | CQ20: BNF_S2 = 58516.8 | CR20: BNF_S2 = 59365.35 | CS20: BNF_S2 = 59451.15 | CT20: BNF_S2 = 59187.7 | CU20: BNF_S2 = 58989.5 | CV20: BNF_S2 = 58740.4 | CW20: BNF_S2 = 58813.3 | CX20: BNF_S2 = 58863.4 | CY20: BNF_S2 = 58644.9 | CZ20: BNF_S2 = 58673.2 | DA20: BNF_S2 = 58498.05 | DB20: BNF_S2 = 58520.9 | DC20: BNF_S2 = 59066 | DD20: BNF_S2 = 58868.35 | DE20: BNF_S2 = 58743.15 | DF20: BNF_S2 = 58626 | DG20: BNF_S2 = 58447.2 | DH20: BNF_S2 = 58792.7 | DI20: BNF_S2 = 59061.2 | DJ20: BNF_S2 = 59120.6 | DK20: BNF_S2 = 58900.1 | DL20: BNF_S2 = 58812.75 | DM20: BNF_S2 = 58629.9 | DN20: BNF_S2 = 58525.4 | DO20: BNF_S2 = 58932.6 | DP20: BNF_S2 = 59501.25 | DQ20: BNF_S2 = 59565.5
A21: BNF_S3 | B21: = | D21: BNF_S3=56305.6 | E21: BNF_S3=56337.5 | F21: BNF_S3=56639.9 | G21: BNF_S3=56169 | H21: BNF_S3=55589.9 | I21: BNF_S3=55750.05 | J21: BNF_S3=55942.45 | K21: BNF_S3=56334.65 | L21: BNF_S3=56373.4 | M21: BNF_S3=55524 | N21: BNF_S3=55281.15 | O21: BNF_S3=55491.55 | P21: BNF_S3=55779.85 | Q21: BNF_S3=54678.6 | R21: BNF_S3=54885.1 | S21: BNF_S3=55138.45 | T21: BNF_S3=54958.45 | U21: BNF_S3=54907.75 | V21: BNF_S3=54483.6 | W21: BNF_S3=53975.8 | X21: BNF_S3=54443.55 | Y21: BNF_S3=54276.05 | Z21: BNF_S3=54712.5 | AA21: BNF_S3=54721.35 | AB21: BNF_S3=55027.6 | AC21: BNF_S3=55302.95 | AD21: BNF_S3=55344.45 | AE21: BNF_S3=55359.1 | AF21: BNF_S3=5477.25 | AG21: BNF_S3=54765.55 | AH21: BNF_S3=53535.25 | AI21: BNF_S3=53984.65 | AJ21: BNF_S3 = 52999.5 | AK21: BNF_S3=53384.1 | AL21: BNF_S3=52856.8 | AM21: BNF_S3=53133.1 | AN21: BNF_S3=53402.65 | AO21: BNF_S3 = 53198.2 | AP21: BNF_S3 = 53544.9 | AQ21: BNF_S3 = 53808.95 | AR21: BNF_S3 = 54083.75 | AS21: BNF_S3 = 54107.15 | AT21: BNF_S3 = 54370.45 | AU21: BNF_S3 = 54579.45 | AV21: BNF_S3 = 54480.7 | AW21: BNF_S3 = 54852.1 | AX21: BNF_S3 = 55189.45 | AY21: BNF_S3 = 54979.75 | AZ21: BNF_S3 = 54660.7 | BA21: BNF_S3 = 54722.15 | BB21: BNF_S3 = 54466.95 | BC21: BNF_S3 = 54454.10 | BD21: BNF_S3 = 53581.8 | BE21: BNF_S3 = 53770.25 | BF21: BNF_S3 = 54204.75 | BG21: BNF_S3 = 53993.9 | BH21: BNF_S3 = 54865.9 | BI21: BNF_S3 = 55396.4 | BJ21: BNF_S3 = 55531.4 | BK21: BNF_S3 = 55309.05 | BL21: BNF_S3 = 55486.2 | BM21: BNF_S3 = 55646.9 | BN21: BNF_S3 = 55934.45 | BO21: BNF_S3 = 55752.8 | BP21: BNF_S3 = 56122.75 | BQ21: BNF_S3 = 56571.8 | BR21: BNF_S3 = 56766.4 | BS21: BNF_S3 = 57609.4 | BT21: BNF_S3 = 57201.1 | BU21: BNF_S3 = 56625.95 | BV21: BNF_S3 = 57198 | BW21: BNF_S3 = 57341.6 | BX21: BNF_S3 = 57775.4 | BY21: BNF_S3 = 57577.8 | BZ21: BNF_S3 = 56939.2 | CA21: BNF_S3 = 57268.25 | CB21: BNF_S3 = 57280.1 | CC21: BNF_S3 = 56977.75 | CD21: BNF_S3 = 56512.5 | CE21: BNF_S3 = 57572.45 | CF21: BNF_S3 = 57166.05 | CG21: BNF_S3 = 57792.6 | CH21: BNF_S3 = 57645.2 | CI21: BNF_S3 = 57641.5 | CJ21: BNF_S3 = 58315.25 | CK21: BNF_S3 = 58459.45 | CL21: BNF_S3 = 58274.6 | CM21: BNF_S3 = 58853.75 | CN21: BNF_S3 = 58308.35 | CO21: BNF_S3 = 57892.85 | CP21: BNF_S3 = 58235.65 | CQ21: BNF_S3 = 58250.5 | CR21: BNF_S3 = 59207.75 | CS21: BNF_S3 = 59303.4 | CT21: BNF_S3 = 58847.85 | CU21: BNF_S3 = 58727.05 | CV21: BNF_S3 = 58555.15 | CW21: BNF_S3 = 58564.45 | CX21: BNF_S3 = 58620.25 | CY21: BNF_S3 = 58259.15 | CZ21: BNF_S3 = 58468 | DA21: BNF_S3 = 58142.25 | DB21: BNF_S3 = 58241.95 | DC21: BNF_S3 = 58907.1 | DD21: BNF_S3 = 58684.35 | DE21: BNF_S3 = 58520 | DF21: BNF_S3 = 58450.55 | DG21: BNF_S3 = 58181.75 | DH21: BNF_S3 = 58687.9 | DI21: BNF_S3 = 58966.9 | DJ21: BNF_S3 = 59024.5 | DK21: BNF_S3 = 58681.95 | DL21: BNF_S3 = 58678.45 | DM21: BNF_S3 = 58450.3 | DN21: BNF_S3 = 58313.25 | DO21: BNF_S3 = 58678.15 | DP21: BNF_S3 = 59432.85 | DQ21: BNF_S3 = 59392.7
A22: BNF_S4 | B22: = | D22: BNF_S4=56161.25 | E22: BNF_S4=56152.35 | F22: BNF_S4=56491.05 | G22: BNF_S4=55863.4 | H22: BNF_S4=55282.4 | I22: BNF_S4=55497.25 | J22: BNF_S4=55567.7 | K22: BNF_S4=56144.05 | L22: BNF_S4=56134.65 | M22: BNF_S4=55066.3 | N22: BNF_S4=54923 | O22: BNF_S4=55313.7 | P22: BNF_S4=55637.5 | Q22: BNF_S4=54244.25 | R22: BNF_S4=54546.6 | S22: BNF_S4=54989.05 | T22: BNF_S4=54469.65 | U22: BNF_S4=54747.75 | V22: BNF_S4=54238.65 | W22: BNF_S4=53510.9 | X22: BNF_S4=54201.55 | Y22: BNF_S4=53913.3 | Z22: BNF_S4=54555.25 | AA22: BNF_S4=54544.85 | AB22: BNF_S4=54717.6 | AC22: BNF_S4=55150.35 | AD22: BNF_S4=5528 | AE22: BNF_S4=55184.55 | AF22: BNF_S4=53864.6 | AG22: BNF_S4=54624.1 | AH22: BNF_S4=53104.85 | AI22: BNF_S4=52592.75 | AJ22: BNF_S4 = 52696.55 | AK22: BNF_S4=53247.05 | AL22: BNF_S4=52495.41 | AM22: BNF_S4=52918.75 | AN22: BNF_S4=53118.05 | AO22: BNF_S4 = 52937.55 | AP22: BNF_S4 = 53283.8 | AQ22: BNF_S4 = 53673.7 | AR22: BNF_S4 = 53925.6 | AS22: BNF_S4 = 53959.5 | AT22: BNF_S4 = 54265.5 | AU22: BNF_S4 = 54465.45 | AV22: BNF_S4 = 54332.2 | AW22: BNF_S4 = 54704.9 | AX22: BNF_S4 = 55038.75 | AY22: BNF_S4 = 54791.95 | AZ22: BNF_S4 = 54383.25 | BA22: BNF_S4 = 54503.75 | BB22: BNF_S4 = 54180.2 | BC22: BNF_S4 = 54229.90 | BD22: BNF_S4 = 53217.25 | BE22: BNF_S4 = 53542.1 | BF22: BNF_S4 = 54055.65 | BG22: BNF_S4 = 53699.55 | BH22: BNF_S4 = 54710.35 | BI22: BNF_S4 = 55230.95 | BJ22: BNF_S4 = 55284.55 | BK22: BNF_S4 = 55053.05 | BL22: BNF_S4 = 55307.35 | BM22: BNF_S4 = 55394.15 | BN22: BNF_S4 = 55738 | BO22: BNF_S4 = 55514.15 | BP22: BNF_S4 = 55938.2 | BQ22: BNF_S4 = 56360.35 | BR22: BNF_S4 = 56530.25 | BS22: BNF_S4 = 57470.5 | BT22: BNF_S4 = 56825.95 | BU22: BNF_S4 = 56197.9 | BV22: BNF_S4 = 56970.65 | BW22: BNF_S4 = 57127.2 | BX22: BNF_S4 = 57619.55 | BY22: BNF_S4 = 57367.1 | BZ22: BNF_S4 = 56580.35 | CA22: BNF_S4 = 57043.15 | CB22: BNF_S4 = 57053.65 | CC22: BNF_S4 = 56706.15 | CD22: BNF_S4 = 56189.8 | CE22: BNF_S4 = 57435.55 | CF22: BNF_S4 = 56951.95 | CG22: BNF_S4 = 57602.95 | CH22: BNF_S4 = 57404.25 | CI22: BNF_S4 = 57437.25 | CJ22: BNF_S4 = 58170.2 | CK22: BNF_S4 = 58289.75 | CL22: BNF_S4 = 58064.65 | CM22: BNF_S4 = 58718 | CN22: BNF_S4 = 58050.7 | CO22: BNF_S4 = 57514.55 | CP22: BNF_S4 = 57980.4 | CQ22: BNF_S4 = 57984.25 | CR22: BNF_S4 = 59050.1 | CS22: BNF_S4 = 59155.6 | CT22: BNF_S4 = 58507.95 | CU22: BNF_S4 = 58464.6 | CV22: BNF_S4 = 58369.85 | CW22: BNF_S4 = 58315.6 | CX22: BNF_S4 = 58377.1 | CY22: BNF_S4 = 57873.45 | CZ22: BNF_S4 = 58262.75 | DA22: BNF_S4 = 57786.4 | DB22: BNF_S4 = 57962.95 | DC22: BNF_S4 = 58748.25 | DD22: BNF_S4 = 58500.4 | DE22: BNF_S4 = 58296.8 | DF22: BNF_S4 = 58275.15 | DG22: BNF_S4 = 57916.25 | DH22: BNF_S4 = 58583.1 | DI22: BNF_S4 = 58872.6 | DJ22: BNF_S4 = 58928.35 | DK22: BNF_S4 = 58463.8 | DL22: BNF_S4 = 58544.15 | DM22: BNF_S4 = 58270.65 | DN22: BNF_S4 = 58101.05 | DO22: BNF_S4 = 58423.65 | DP22: BNF_S4 = 59364.45 | DQ22: BNF_S4 = 59219.95
A23: BNF_S5 | B23: = | D23: BNF_S5=56016.9 | E23: BNF_S5=55967.2 | F23: BNF_S5=56342.2 | G23: BNF_S5=55557.8 | H23: BNF_S5=54974.9 | I23: BNF_S5=55244.45 | J23: BNF_S5=55192.95 | K23: BNF_S5=55953.45 | L23: BNF_S5=55895.9 | M23: BNF_S5=54608.6 | N23: BNF_S5=54564.85 | O23: BNF_S5=55139.85 | P23: BNF_S5=55495.15 | Q23: BNF_S5=53809.9 | R23: BNF_S5=54208.1 | S23: BNF_S5=54839.65 | T23: BNF_S5=54225.25 | U23: BNF_S5=54587.75 | V23: BNF_S5=53993.7 | W23: BNF_S5=53046 | X23: BNF_S5=53959.55 | Y23: BNF_S5=53550.55 | Z23: BNF_S5=54398 | AA23: BNF_S5=54368.3 | AB23: BNF_S5=54407.6 | AC23: BNF_S5=54997.75 | AD23: BNF_S5=55111.55 | AE23: BNF_S5=55010 | AF23: BNF_S5=53451.95 | AG23: BNF_S5=54482.65 | AH23: BNF_S5=52674.45 | AI23: BNF_S5=52200.85 | AJ23: BNF_S5 = 52393.25 | AK23: BNF_S5=53110 | AL23: BNF_S5=52134.15 | AM23: BNF_S5=52704.4 | AN23: BNF_S5=52833.45 | AO23: BNF_S5 = 52676.9 | AP23: BNF_S5 = 53022.7 | AQ23: BNF_S5 = 53538.45 | AR23: BNF_S5 = 53767.45 | AS23: BNF_S5 = 53811.85 | AT23: BNF_S5 = 54160.55 | AU23: BNF_S5 = 54351.45 | AV23: BNF_S5 = 54183.7 | AW23: BNF_S5 = 54557.7 | AX23: BNF_S5 = 54888.05 | AY23: BNF_S5 = 54604.15 | AZ23: BNF_S5 = 54105.8 | BA23: BNF_S5 = 54285.35 | BB23: BNF_S5 = 53893.45 | BC23: BNF_S5 = 54004.90 | BD23: BNF_S5 = 52852.7 | BE23: BNF_S5 = 53313.95 | BF23: BNF_S5 = 53906.55 | BG23: BNF_S5 = 53405.2 | BH23: BNF_S5 = 54554.8 | BI23: BNF_S5 = 55065.5 | BJ23: BNF_S5 = 55037.7 | BK23: BNF_S5 = 54797.05 | BL23: BNF_S5 = 55128.5 | BM23: BNF_S5 = 55141.4 | BN23: BNF_S5 = 55541.55 | BO23: BNF_S5 = 55275.5 | BP23: BNF_S5 = 55753.65 | BQ23: BNF_S5 = 56148.9 | BR23: BNF_S5 = 56294.1 | BS23: BNF_S5 = 57331.6 | BT23: BNF_S5 = 56450.8 | BU23: BNF_S5 = 55769.85 | BV23: BNF_S5 = 56743.3 | BW23: BNF_S5 = 56912.8 | BX23: BNF_S5 = 57463.7 | BY23: BNF_S5 = 57156.4 | BZ23: BNF_S5 = 56221.5 | CA23: BNF_S5 = 56818.05 | CB23: BNF_S5 = 56827.2 | CC23: BNF_S5 = 56434.55 | CD23: BNF_S5 = 55867.1 | CE23: BNF_S5 = 57298.65 | CF23: BNF_S5 = 56737.85 | CG23: BNF_S5 = 57413.3 | CH23: BNF_S5 = 57163.3 | CI23: BNF_S5 = 57233 | CJ23: BNF_S5 = 58025.15 | CK23: BNF_S5 = 58120.05 | CL23: BNF_S5 = 57856.7 | CM23: BNF_S5 = 58582.25 | CN23: BNF_S5 = 57793.05 | CO23: BNF_S5 = 57136.25 | CP23: BNF_S5 = 57725.15 | CQ23: BNF_S5 = 57718 | CR23: BNF_S5 = 58892.45 | CS23: BNF_S5 = 59007.8 | CT23: BNF_S5 = 58168.05 | CU23: BNF_S5 = 58202.15 | CV23: BNF_S5 = 58184.55 | CW23: BNF_S5 = 58066.75 | CX23: BNF_S5 = 58133.95 | CY23: BNF_S5 = 57487.75 | CZ23: BNF_S5 = 58057.5 | DA23: BNF_S5 = 57430.55 | DB23: BNF_S5 = 57683.95 | DC23: BNF_S5 = 58589.4 | DD23: BNF_S5 = 58316.45 | DE23: BNF_S5 = 58073.6 | DF23: BNF_S5 = 58099.75 | DG23: BNF_S5 = 57650.75 | DH23: BNF_S5 = 58478.3 | DI23: BNF_S5 = 58778.3 | DJ23: BNF_S5 = 58832.2 | DK23: BNF_S5 = 58245.65 | DL23: BNF_S5 = 58409.85 | DM23: BNF_S5 = 58091 | DN23: BNF_S5 = 57888.85 | DO23: BNF_S5 = 58169.15 | DP23: BNF_S5 = 59296.05 | DQ23: BNF_S5 = 59047.2
A25: NIFTY_PD_H | B25: = | C25: 25652.6 | D25: NIFTY_PD_H=25151.1 | E25: NIFTY_PD_H=25245.2 | F25: NIFTY_PD_H=25255.3 | G25: NIFTY_PD_H=25238.35 | H25: NIFTY_PD_H=25144.6 | I25: NIFTY_PD_H=25111.4 | J25: NIFTY_PD_H=25182 | K25: NIFTY_PD_H=25233.5 | L25: NIFTY_PD_H=25010.35 | M25: NIFTY_PD_H=25010.35 | N25: NIFTY_PD_H=24889.2 | O25: NIFTY_PD_H=24847.15 | P25: NIFTY_PD_H=24902.3 | Q25: NIFTY_PD_H=24956.5 | R25: NIFTY_PD_H=24784.15 | S25: NIFTY_PD_H=24736.25 | T25: NIFTY_PD_H=24733.1 | U25: NIFTY_PD_H=24671.4 | V25: NIFTY_PD_H=24634.2 | W25: NIFTY_PD_H=24585.5 | X25: NIFTY_PD_H=24600.85 | Y25: NIFTY_PD_H=24702.6 | Z25: NIFTY_PD_H=24664.55 | AA25: NIFTY_PD_H=24673.65 | AB25: NIFTY_PD_H=25022 | AC25: NIFTY_PD_H=25012.65 | AD25: NIFTY_PD_H=25088.7 | AE25: NIFTY_PD_H=25153.65 | AF25: NIFTY_PD_H=25084.85 | AG25: NIFTY_PD_H=25021.55 | AH25: NIFTY_PD_H=24919.65 | AI25: NIFTY_PD_H=24702.65 | AJ25: NIFTY_PD_H=24572.45 | AK25: NIFTY_PD_H=24635.6 | AL25: NIFTY_PD_H=24756.1 | AM25: NIFTY_PD_H=24737.05 | AN25: NIFTY_PD_H=24980.75 | AO25: NIFTY_PD_H=24832.35 | AP25: NIFTY_PD_H=24885.5 | AQ25: NIFTY_PD_H=24891.8 | AR25: NIFTY_PD_H=25035.7 | AS25: NIFTY_PD_H=25037.3 | AT25: NIFTY_PD_H=25139.45 | AU25: NIFTY_PD_H=25138.45 | AV25: NIFTY_PD_H=25261.4 | AW25: NIFTY_PD_H=25346.5 | AX25: NIFTY_PD_H=25448.95 | AY25: NIFTY_PD_H=2542.75 | AZ25: NIFTY_PD_H=25331.7 | BA25: NIFTY_PD_H=25261.9 | BB25: NIFTY_PD_H=25149.85 | BC25: NIFTY_PD_H=25092.7 | BD25: NIFTY_PD_H = 24868.6 | BE25: NIFTY_PD_H = 24791.3 | BF25: NIFTY_PD_H = 24731.8 | BG25: NIFTY_PD_H = 24867.95 | BH25: NIFTY_PD_H = 24904.8 | BI25: NIFTY_PD_H = 25095.95 | BJ25: NIFTY_PD_H = 25220.9 | BK25: NIFTY_PD_H = 25192.5 | BL25: NIFTY_PD_H = 25199.25 | BM25: NIFTY_PD_H = 25330.75 | BN25: NIFTY_PD_H = 25267.3 | BO25: NIFTY_PD_H = 25310.35 | BP25: NIFTY_PD_H = 25365.15 | BQ25: NIFTY_PD_H = 25625.4 | BR25: NIFTY_PD_H = 25783.75 | BS25: NIFTY_PD_H = 25934.35 | BT25: NIFTY_PD_H = 26104.2 | BU25: NIFTY_PD_H = 25944.15 | BV25: NIFTY_PD_H = 26005.95 | BW25: NIFTY_PD_H = 26005.95 | BX25: NIFTY_PD_H = 26041.7 | BY25: NIFTY_PD_H = 26032.05 | BZ25: NIFTY_PD_H = 25953.75 | CA25: NIFTY_PD_H = 24803.1 | CB25: NIFTY_PD_H = 25787.4 | CC25: NIFTY_PD_H = 25679.15 | CD25: NIFTY_PD_H = 25551.25 | CE25: NIFTY_PD_H = 25551.25 | CF25: NIFTY_PD_H = 25715.8 | CG25: NIFTY_PD_H = 25934.55 | CH25: NIFTY_PD_H = 26010.7 | CI25: NIFTY_PD_H = 25940.2 | CJ25: NIFTY_PD_H = 26024.2 | CK25: NIFTY_PD_H = 26029.85 | CL25: NIFTY_PD_H = 26074.65 | CM25: NIFTY_PD_H = 26246.65 | CN25: NIFTY_PD_H = 26179.2 | CO25: NIFTY_PD_H = 26142.8 | CP25: NIFTY_PD_H = 26032.6 | CQ25: NIFTY_PD_H = 26215.15 | CR25: NIFTY_PD_H = 26310.45 | CS25: NIFTY_PD_H = 26280.75 | CT25: NIFTY_PD_H = 26325.8 | CU25: NIFTY_PD_H = 26154.6 | CV25: NIFTY_PD_H = 26066.45 | CW25: NIFTY_PD_H = 26098.25 | CX25: NIFTY_PD_H = 26202.6 | CY25: NIFTY_PD_H = 26178.7 | CZ25: NIFTY_PD_H = 25923.65 | DA25: NIFTY_PD_H = 25947.65 | DB25: NIFTY_PD_H = 25922.8 | DC25: NIFTY_PD_H = 26057.6 | DD25: NIFTY_PD_H = 26047.15 | DE25: NIFTY_PD_H = 25980.75 | DF25: NIFTY_PD_H = 25929.15 | DG25: NIFTY_PD_H = 25902.35 | DH25: NIFTY_PD_H = 25993.35 | DI25: NIFTY_PD_H = 26180.7 | DJ25: NIFTY_PD_H = 26233.55 | DK25: NIFTY_PD_H = 26236.4 | DL25: NIFTY_PD_H = 26144.2 | DM25: NIFTY_PD_H = 26106.8 | DN25: NIFTY_PD_H = 25976.75 | DO25: NIFTY_PD_H = 26187.95 | DP25: NIFTY_PD_H = 26197.55 | DQ25: NIFTY_PD_H = 26340 | DR25: NIFTY_PD_H = 26373.2 | DS25: NIFTY_PD_H = 26273.95 | DT25: NIFTY_PD_H = 26187.15 | DU25: NIFTY_PD_H = 26133.2 | DV25: NIFTY_PD_H = 25940.6 | DW25: NIFTY_PD_H = 25813.15 | DX25: NIFTY_PD_H = 25899.8 | DZ25: NIFTY_PD_H = 25873.5 | EA25: NIFTY_PD_H = 25653.3 | EB25: NIFTY_PD_H = 25585 | EC25: NIFTY_PD_H = 25300.95 | ED25: NIFTY_PD_H = 25435.75 | EE25: NIFTY_PD_H = 25347.95 | EF25: NIFTY_PD_H = 25246.65 | EG25: NIFTY_PD_H = 25372 | EH25: NIFTY_PD_H = 25458.15 | EI25: NIFTY_PD_H = 25370.7 | EJ25: NIFTY_PD_H = 25440.9 | EK25: NIFTY_PD_H = 25440.9 | EL25: NIFTY_PD_H = 25108.1 | EM25: NIFTY_PD_H = 26341.2 | EN25: NIFTY_PD_H = 25818.55 | EO25: NIFTY_PD_H = 25757.65 | EP25: NIFTY_PD_H = 25703.95 | EQ25: NIFTY_PD_H = 25922.25 | ER25: NIFTY_PD_H = 25989.45 | ES25: NIFTY_PD_H = 26009.4 | ET25: NIFTY_PD_H = 25906.7 | EU25: NIFTY_PD_H = 25630.25 | EV25: NIFTY_PD_H = 25697 | EW25: NIFTY_PD_H = 25764.4 | EX25: NIFTY_PD_H = 25828.05 | EY25: NIFTY_PD_H = 25885.3 | EZ25: NIFTY_PD_H = 25663.55 | FA25: NIFTY_PD_H = 25771.45 | FB25: NIFTY_PD_H = 25641.8 | FC25: NIFTY_PD_H = 25652.6
A26: NIFTY_PD_C | B26: = | C26: 25482.5 | D26: NIFTY_PD_C=25082.3 | E26: NIFTY_PD_C=25195.8 | F26: NIFTY_PD_C=25212.05 | G26: NIFTY_PD_C=25111.45 | H26: NIFTY_PD_C=24968.4 | I26: NIFTY_PD_C=25090.7 | J26: NIFTY_PD_C=25060.9 | K26: NIFTY_PD_C=25219.9 | L26: NIFTY_PD_C=24837 | M26: NIFTY_PD_C=24837 | N26: NIFTY_PD_C=24680.9 | O26: NIFTY_PD_C=24821.1 | P26: NIFTY_PD_C=24855.05 | Q26: NIFTY_PD_C=24768.35 | R26: NIFTY_PD_C=24565.35 | S26: NIFTY_PD_C=24722.75 | T26: NIFTY_PD_C=24649.55 | U26: NIFTY_PD_C=24574.2 | V26: NIFTY_PD_C=24596.1 | W26: NIFTY_PD_C=24363.3 | X26: NIFTY_PD_C=24585.05 | Y26: NIFTY_PD_C=24487.4 | Z26: NIFTY_PD_C=24619.35 | AA26: NIFTY_PD_C=24631.3 | AB26: NIFTY_PD_C=24876.95 | AC26: NIFTY_PD_C=24980.65 | AD26: NIFTY_PD_C=25050.55 | AE26: NIFTY_PD_C=25083.75 | AF26: NIFTY_PD_C=24870.1 | AG26: NIFTY_PD_C=24967.75 | AH26: NIFTY_PD_C=24712.05 | AI26: NIFTY_PD_C=24500.9 | AJ26: NIFTY_PD_C=24426.85 | AK26: NIFTY_PD_C=24625.05 | AL26: NIFTY_PD_C=24579.6 | AM26: NIFTY_PD_C=24715.05 | AN26: NIFTY_PD_C=24734.3 | AO26: NIFTY_PD_C=24741 | AP26: NIFTY_PD_C=24773.15 | AQ26: NIFTY_PD_C=24868.65 | AR26: NIFTY_PD_C=24973.1 | AS26: NIFTY_PD_C=25005.5 | AT26: NIFTY_PD_C=25114 | AU26: NIFTY_PD_C=25069.2 | AV26: NIFTY_PD_C=25239.1 | AW26: NIFTY_PD_C=25330.25 | AX26: NIFTY_PD_C=25423.6 | AY26: NIFTY_PD_C=25327.05 | AZ26: NIFTY_PD_C=25202.35 | BA26: NIFTY_PD_C=25169.5 | BB26: NIFTY_PD_C=25056.9 | BC26: NIFTY_PD_C=24890.85 | BD26: NIFTY_PD_C = 24654.7 | BE26: NIFTY_PD_C = 24691.95 | BF26: NIFTY_PD_C = 24611.1 | BG26: NIFTY_PD_C = 24836.3 | BH26: NIFTY_PD_C = 24894.25 | BI26: NIFTY_PD_C = 25077.65 | BJ26: NIFTY_PD_C = 25108.3 | BK26: NIFTY_PD_C = 25046.15 | BL26: NIFTY_PD_C = 25181.8 | BM26: NIFTY_PD_C = 25285.35 | BN26: NIFTY_PD_C = 25227.35 | BO26: NIFTY_PD_C = 25145.5 | BP26: NIFTY_PD_C = 25323.55 | BQ26: NIFTY_PD_C = 25585.3 | BR26: NIFTY_PD_C = 25709.85 | BS26: NIFTY_PD_C = 25868.6 | BT26: NIFTY_PD_C = 25891.4 | BU26: NIFTY_PD_C = 25795.15 | BV26: NIFTY_PD_C = 25966.05 | BW26: NIFTY_PD_C = 25966.05 | BX26: NIFTY_PD_C = 25936.2 | BY26: NIFTY_PD_C = 25877.85 | BZ26: NIFTY_PD_C = 25722.1 | CA26: NIFTY_PD_C = 25763.35 | CB26: NIFTY_PD_C = 25593.35 | CC26: NIFTY_PD_C = 25509.7 | CD26: NIFTY_PD_C = 25492.3 | CE26: NIFTY_PD_C = 25492.3 | CF26: NIFTY_PD_C = 25694.95 | CG26: NIFTY_PD_C = 25875.8 | CH26: NIFTY_PD_C = 25879.15 | CI26: NIFTY_PD_C = 25910.05 | CJ26: NIFTY_PD_C = 26013.45 | CK26: NIFTY_PD_C = 25910.05 | CL26: NIFTY_PD_C = 26052.65 | CM26: NIFTY_PD_C = 26192.15 | CN26: NIFTY_PD_C = 26068.15 | CO26: NIFTY_PD_C = 25959.5 | CP26: NIFTY_PD_C = 25884.8 | CQ26: NIFTY_PD_C = 26205.3 | CR26: NIFTY_PD_C = 26215.55 | CS26: NIFTY_PD_C = 26202.95 | CT26: NIFTY_PD_C = 26175.75 | CU26: NIFTY_PD_C = 26032.2 | CV26: NIFTY_PD_C = 25986 | CW26: NIFTY_PD_C = 26033.75 | CX26: NIFTY_PD_C = 26186.45 | CY26: NIFTY_PD_C = 25960.55 | CZ26: NIFTY_PD_C = 25839.65 | DA26: NIFTY_PD_C = 25758 | DB26: NIFTY_PD_C = 25898.55 | DC26: NIFTY_PD_C = 26046.95 | DD26: NIFTY_PD_C = 26027.3 | DE26: NIFTY_PD_C = 25860.1 | DF26: NIFTY_PD_C = 25818.55 | DG26: NIFTY_PD_C = 25815.65 | DH26: NIFTY_PD_C = 25966.4 | DI26: NIFTY_PD_C = 26172.4 | DJ26: NIFTY_PD_C = 26177.15 | DK26: NIFTY_PD_C = 26142.1 | DL26: NIFTY_PD_C = 26042.3 | DM26: NIFTY_PD_C = 25942.1 | DN26: NIFTY_PD_C = 25938.85 | DO26: NIFTY_PD_C = 26129.6 | DP26: NIFTY_PD_C = 26146.55 | DQ26: NIFTY_PD_C = 26328.55 | DR26: NIFTY_PD_C = 26250.3 | DS26: NIFTY_PD_C = 26178.7 | DT26: NIFTY_PD_C = 26140.75 | DU26: NIFTY_PD_C = 25876.85 | DV26: NIFTY_PD_C = 25683.3 | DW26: NIFTY_PD_C = 25790.25 | DX26: NIFTY_PD_C = 25732.3 | DZ26: NIFTY_PD_C = 25694.35 | EA26: NIFTY_PD_C = 25585.5 | EB26: NIFTY_PD_C = 25232.5 | EC26: NIFTY_PD_C = 25157.5 | ED26: NIFTY_PD_C = 25289.9 | EE26: NIFTY_PD_C = 25048.65 | EF26: NIFTY_PD_C = 25175.4 | EG26: NIFTY_PD_C = 25342.75 | EH26: NIFTY_PD_C = 25418.9 | EI26: NIFTY_PD_C = 25320.65 | EJ26: NIFTY_PD_C = 24825.45 | EK26: NIFTY_PD_C = 24825.45 | EL26: NIFTY_PD_C = 25088.4 | EM26: NIFTY_PD_C = 25727.55 | EN26: NIFTY_PD_C = 25776 | EO26: NIFTY_PD_C = 25642.8 | EP26: NIFTY_PD_C = 25693.7 | EQ26: NIFTY_PD_C = 25867.3 | ER26: NIFTY_PD_C = 25922.65 | ES26: NIFTY_PD_C = 25953.85 | ET26: NIFTY_PD_C = 25807.2 | EU26: NIFTY_PD_C = 25471.1 | EV26: NIFTY_PD_C = 25682.75 | EW26: NIFTY_PD_C = 25725.4 | EX26: NIFTY_PD_C = 25819.35 | EY26: NIFTY_PD_C = 25454.35 | EZ26: NIFTY_PD_C = 25571.25 | FA26: NIFTY_PD_C = 25713 | FB26: NIFTY_PD_C = 25424.65 | FC26: NIFTY_PD_C = 25482.5
A27: NIFTY_PD_L | B27: = | C27: 25428.2 | D27: NIFTY_PD_L=25001.95 | E27: NIFTY_PD_L=25088.45 | F27: NIFTY_PD_L=25121.05 | G27: NIFTY_PD_L=25101 | H27: NIFTY_PD_L=24918.65 | I27: NIFTY_PD_L=24882.3 | J27: NIFTY_PD_L=25035.55 | K27: NIFTY_PD_L=25085.5 | L27: NIFTY_PD_L=24806.35 | M27: NIFTY_PD_L=24806.35 | N27: NIFTY_PD_L=24646.6 | O27: NIFTY_PD_L=24598.6 | P27: NIFTY_PD_L=24771.95 | Q27: NIFTY_PD_L=24635 | R27: NIFTY_PD_L=24535.05 | S27: NIFTY_PD_L=24554 | T27: NIFTY_PD_L=24590.3 | U27: NIFTY_PD_L=24539.2 | V27: NIFTY_PD_L=24344.15 | W27: NIFTY_PD_L=24337.5 | X27: NIFTY_PD_L=24347.45 | Y27: NIFTY_PD_L=24465.65 | Z27: NIFTY_PD_L=24535.25 | AA27: NIFTY_PD_L=24596.9 | AB27: NIFTY_PD_L=24852.85 | AC27: NIFTY_PD_L=24873.95 | AD27: NIFTY_PD_L=24929.7 | AE27: NIFTY_PD_L=25054.9 | AF27: NIFTY_PD_L=24859.15 | AG27: NIFTY_PD_L=24394.35 | AH27: NIFTY_PD_L=246689.6 | AI27: NIFTY_PD_L=24481.6 | AJ27: NIFTY_PD_L=24404.7 | AK27: NIFTY_PD_L=24467.80 | AL27: NIFTY_PD_L=24522.35 | AM27: NIFTY_PD_L=24533.2 | AN27: NIFTY_PD_L=24708.2 | AO27: NIFTY_PD_L=24621.6 | AP27: NIFTY_PD_L=24751.55 | AQ27: NIFTY_PD_L=24814 | AR27: NIFTY_PD_L=24915 | AS27: NIFTY_PD_L=24940.15 | AT27: NIFTY_PD_L=25038.05 | AU27: NIFTY_PD_L=25048.75 | AV27: NIFTY_PD_L=25070.45 | AW27: NIFTY_PD_L=25275.35 | AX27: NIFTY_PD_L=25329.5 | AY27: NIFTY_PD_L=25286.3 | AZ27: NIFTY_PD_L=25151.05 | BA27: NIFTY_PD_L=25084.65 | BB27: NIFTY_PD_L=25027.45 | BC27: NIFTY_PD_L=24878.3 | BD27: NIFTY_PD_L = 24629.45 | BE27: NIFTY_PD_L = 24634.9 | BF27: NIFTY_PD_L = 24587.7 | BG27: NIFTY_PD_L = 24605.95 | BH27: NIFTY_PD_L = 24747.55 | BI27: NIFTY_PD_L = 24881.65 | BJ27: NIFTY_PD_L = 25076.3 | BK27: NIFTY_PD_L = 25008.5 | BL27: NIFTY_PD_L = 25024.3 | BM27: NIFTY_PD_L = 25156.85 | BN27: NIFTY_PD_L = 25152.3 | BO27: NIFTY_PD_L = 25060.55 | BP27: NIFTY_PD_L = 25159.35 | BQ27: NIFTY_PD_L = 25376.85 | BR27: NIFTY_PD_L = 25508.6 | BS27: NIFTY_PD_L = 25825.8 | BT27: NIFTY_PD_L = 25862.45 | BU27: NIFTY_PD_L = 25718.2 | BV27: NIFTY_PD_L = 25827 | BW27: NIFTY_PD_L = 25718.2 | BX27: NIFTY_PD_L = 25810.05 | BY27: NIFTY_PD_L = 25845.25 | BZ27: NIFTY_PD_L = 25711.2 | CA27: NIFTY_PD_L = 25645.5 | CB27: NIFTY_PD_L = 25378.4 | CC27: NIFTY_PD_L = 25491.55 | CD27: NIFTY_PD_L = 25318.45 | CE27: NIFTY_PD_L = 25318.45 | CF27: NIFTY_PD_L = 25449.25 | CG27: NIFTY_PD_L = 25781.15 | CH27: NIFTY_PD_L = 25808.4 | CI27: NIFTY_PD_L = 25740.8 | CJ27: NIFTY_PD_L = 25906.35 | CK27: NIFTY_PD_L = 25876.5 | CL27: NIFTY_PD_L = 25856.2 | CM27: NIFTY_PD_L = 26063.2 | CN27: NIFTY_PD_L = 26052.2 | CO27: NIFTY_PD_L = 25912.15 | CP27: NIFTY_PD_L = 25857.5 | CQ27: NIFTY_PD_L = 25842.95 | CR27: NIFTY_PD_L = 26141.9 | CS27: NIFTY_PD_L = 26172.4 | CT27: NIFTY_PD_L = 26124.2 | CU27: NIFTY_PD_L = 25997.85 | CV27: NIFTY_PD_L = 25891 | CW27: NIFTY_PD_L = 25938.95 | CX27: NIFTY_PD_L = 25985.35 | CY27: NIFTY_PD_L = 25892.25 | CZ27: NIFTY_PD_L = 25728 | DA27: NIFTY_PD_L = 25734.55 | DB27: NIFTY_PD_L = 25693.25 | DC27: NIFTY_PD_L = 25938.45 | DD27: NIFTY_PD_L = 25904.75 | DE27: NIFTY_PD_L = 25834.35 | DF27: NIFTY_PD_L = 25770.35 | DG27: NIFTY_PD_L = 25726.3 | DH27: NIFTY_PD_L = 25880.45 | DI27: NIFTY_PD_L = 26047.8 | DJ27: NIFTY_PD_L = 26119.05 | DK27: NIFTY_PD_L = 26123 | DL27: NIFTY_PD_L = 26008.6 | DM27: NIFTY_PD_L = 25920.3 | DN27: NIFTY_PD_L = 25878 | DO27: NIFTY_PD_L = 25969 | DP27: NIFTY_PD_L = 26113.4 | DQ27: NIFTY_PD_L = 26118.4 | DR27: NIFTY_PD_L = 26210.05 | DS27: NIFTY_PD_L = 26124.75 | DT27: NIFTY_PD_L = 26067.9 | DU27: NIFTY_PD_L = 25858.45 | DV27: NIFTY_PD_L = 25623 | DW27: NIFTY_PD_L = 25473.4 | DX27: NIFTY_PD_L = 25603.3 | DZ27: NIFTY_PD_L = 25662.4 | EA27: NIFTY_PD_L = 25494.35 | EB27: NIFTY_PD_L = 25171.35 | EC27: NIFTY_PD_L = 24919.8 | ED27: NIFTY_PD_L = 25168.5 | EE27: NIFTY_PD_L = 25025.3 | EF27: NIFTY_PD_L = 24932.55 | EG27: NIFTY_PD_L = 25187.65 | EH27: NIFTY_PD_L = 25159.8 | EI27: NIFTY_PD_L = 25213.65 | EJ27: NIFTY_PD_L = 24571.75 | EK27: NIFTY_PD_L = 24571.75 | EL27: NIFTY_PD_L = 24679.4 | EM27: NIFTY_PD_L = 25641.3 | EN27: NIFTY_PD_L = 25563.95 | EO27: NIFTY_PD_L = 25579.5 | EP27: NIFTY_PD_L = 25491.9 | EQ27: NIFTY_PD_L = 25780.9 | ER27: NIFTY_PD_L = 25870.45 | ES27: NIFTY_PD_L = 25899.8 | ET27: NIFTY_PD_L = 25752.4 | EU27: NIFTY_PD_L = 25444.3 | EV27: NIFTY_PD_L = 25372.7 | EW27: NIFTY_PD_L = 25570.3 | EX27: NIFTY_PD_L = 25645.15 | EY27: NIFTY_PD_L = 25388.75 | EZ27: NIFTY_PD_L = 25379.75 | FA27: NIFTY_PD_L = 25609.35 | FB27: NIFTY_PD_L = 25327.6 | FC27: NIFTY_PD_L = 25428.2
A29: NIFTY_R5 | B29: = | C29: 26024.2 | D29: NIFTY_R5=25457.1 | E29: NIFTY_R5=25597.35 | F29: NIFTY_R5=25555.65 | G29: NIFTY_R5=25435.4 | H29: NIFTY_R5=25512.2 | I29: NIFTY_R5=25694.75 | J29: NIFTY_R5=25411.05 | K29: NIFTY_R5=25610.05 | L29: NIFTY_R5=25607.5 | M29: NIFTY_R5=25323.2 | N29: NIFTY_R5=25258.4 | O29: NIFTY_R5=25475.2 | P29: NIFTY_R5=25186.9 | Q29: NIFTY_R5=25562.95 | R29: NIFTY_R5=25156.7 | S29: NIFTY_R5=25204.25 | T29: NIFTY_R5=25002.5 | U29: NIFTY_R5=24894.35 | V29: NIFTY_R5=25356.95 | W29: NIFTY_R5=24950.55 | X29: NIFTY_R5=25255.5 | Y29: NIFTY_R5=25047.55 | Z29: NIFTY_R5=24949.1 | AA29: NIFTY_R5=24821.85 | AB29: NIFTY_R5=25279.65 | AC29: NIFTY_R5=25339.85 | AD29: NIFTY_R5=25461.85 | AE29: NIFTY_R5=25323.8 | AF29: NIFTY_R5=25400.4 | AG29: NIFTY_R5=25289 | AH29: NIFTY_R5=25256.3 | AI29: NIFTY_R5=25023.1 | AJ29: NIFTY_R5=24825.65 | AK29: NIFTY_R5=25162.6 | AL29: NIFTY_R5=25144.1 | AM29: NIFTY_R5=25251.3 | AN29: NIFTY_R5=25378.95 | AO29: NIFTY_R5=25272.55 | AP29: NIFTY_R5=25092.9 | AQ29: NIFTY_R5=25068.35 | AR29: NIFTY_R5=25273.95 | AS29: NIFTY_R5=25253.95 | AT29: NIFTY_R5=25375.9 | AU29: NIFTY_R5=25285.3 | AV29: NIFTY_R5=25740.85 | AW29: NIFTY_R5=25514.55 | AX29: NIFTY_R5=25733 | AY29: NIFTY_R5=25673 | AZ29: NIFTY_R5=25640.95 | BA29: NIFTY_R5=25611.35 | BB29: NIFTY_R5=25352.3 | BC29: NIFTY_R5=25395.3 | BD29: NIFTY_R5 = 25221.15 | BE29: NIFTY_R5 = 25076.35 | BF29: NIFTY_R5 = 24955.15 | BG29: NIFTY_R5 = 25524.4 | BH29: NIFTY_R5 = 25310.05 | BI29: NIFTY_R5 = 25643 | BJ29: NIFTY_R5 = 25456.35 | BK29: NIFTY_R5 = 25488.05 | BL29: NIFTY_R5 = 25642.5 | BM29: NIFTY_R5 = 25733.95 | BN29: NIFTY_R5 = 25520.7 | BO29: NIFTY_R5 = 25756.7 | BP29: NIFTY_R5 = 25858.5 | BQ29: NIFTY_R5 = 26234.75 | BR29: NIFTY_R5 = 26413.7 | BS29: NIFTY_R5 = 26136.15 | BT29: NIFTY_R5 = 26465.15 | BU29: NIFTY_R5 = 26348 | BV29: NIFTY_R5 = 26429.95 | BW29: NIFTY_R5 = 26429.95 | BX29: NIFTY_R5 = 26518.75 | BY29: NIFTY_R5 = 26324.6 | BZ29: NIFTY_R5 = 26291.7 | CA29: NIFTY_R5 = 26170.35 | CB29: NIFTY_R5 = 26091.75 | CC29: NIFTY_R5 = 25953.5 | CD29: NIFTY_R5 = 26093.5 | CE29: NIFTY_R5 = 26093.5 | CF29: NIFTY_R5 = 26398.8 | CG29: NIFTY_R5 = 26265.3 | CH29: NIFTY_R5 = 26374.75 | CI29: NIFTY_R5 = 26431.75 | CJ29: NIFTY_R5 = 26324.15 | CK29: NIFTY_R5 = 26279.05 | CL29: NIFTY_R5 = 26627.85 | CM29: NIFTY_R5 = 26663.2 | CN29: NIFTY_R5 = 26369.8 | CO29: NIFTY_R5 = 26513.45 | CP29: NIFTY_R5 = 26302.45 | CQ29: NIFTY_R5 = 27194.55 | CR29: NIFTY_R5 = 26633.4 | CS29: NIFTY_R5 = 26465.95 | CT29: NIFTY_R5 = 26663.35 | CU29: NIFTY_R5 = 26409.4 | CV29: NIFTY_R5 = 26427.05 | CW29: NIFTY_R5 = 26437.05 | CX29: NIFTY_R5 = 26760.4 | CY29: NIFTY_R5 = 26651.7 | CZ29: NIFTY_R5 = 26333.4 | DA29: NIFTY_R5 = 26263.05 | DB29: NIFTY_R5 = 26502.6 | DC29: NIFTY_R5 = 26361.15 | DD29: NIFTY_R5 = 26400.4 | DE29: NIFTY_R5 = 26210.3 | DF29: NIFTY_R5 = 26205.15 | DG29: NIFTY_R5 = 26256.1 | DH29: NIFTY_R5 = 26258.5 | DI29: NIFTY_R5 = 26524.05 | DJ29: NIFTY_R5 = 26463.7 | DK29: NIFTY_R5 = 26413.05 | DL29: NIFTY_R5 = 26369.95 | DM29: NIFTY_R5 = 26384.55 | DN29: NIFTY_R5 = 26189.55 | DO29: NIFTY_R5 = 26694 | DP29: NIFTY_R5 = 26353.95 | DQ29: NIFTY_R5 = 26915.65 | DR29: NIFTY_R5 = 26644.4 | DS29: NIFTY_R5 = 26544.8 | DT29: NIFTY_R5 = 26443.3 | DU29: NIFTY_R5 = 26524.05 | DV29: NIFTY_R5 = 26444.45 | DW29: NIFTY_R5 = 26688.6 | DX29: NIFTY_R5 = 26467.15 | DZ29: NIFTY_R5 = 26197.55 | EA29: NIFTY_R5 = 26197.55 | EB29: NIFTY_R5 = 26218.05 | EC29: NIFTY_R5 = 26126.1 | ED29: NIFTY_R5 = 25953.95 | EE29: NIFTY_R5 = 25809.3 | EF29: NIFTY_R5 = 25989.25 | EG29: NIFTY_R5 = 25824.85 | EH29: NIFTY_R5 = 26201.4 | EI29: NIFTY_R5 = 26201.4 | EJ29: NIFTY_R5 = 26938.05 | EK29: NIFTY_R5 = 26938.05 | EL29: NIFTY_R5 = 26225.05 | EM29: NIFTY_R5 = 27389.4 | EN29: NIFTY_R5 = 26440.75 | EO29: NIFTY_R5 = 26079.6 | EP29: NIFTY_R5 = 26255.75 | EQ29: NIFTY_R5 = 26225.9 | ER29: NIFTY_R5 = 26234.4 | ES29: NIFTY_R5 = 26227.6 | ET29: NIFTY_R5 = 26185.5 | EU29: NIFTY_R5 = 25914.15 | EV29: NIFTY_R5 = 26542.8 | EW29: NIFTY_R5 = 26230 | EX29: NIFTY_R5 = 26304.2 | EY29: NIFTY_R5 = 26634.85 | EZ29: NIFTY_R5 = 26297.3 | FA29: NIFTY_R5 = 26125.8 | FB29: NIFTY_R5 = 26190.15 | FC29: NIFTY_R5 = 26024.2
A30: NIFTY_R4 | B30: = | C30: 25931.3 | D30: NIFTY_R4=25380.6 | E30: NIFTY_R4=25509.3 | F30: NIFTY_R4=25480.55 | G30: NIFTY_R4=25386.15 | H30: NIFTY_R4=25420.3 | I30: NIFTY_R4=25548.9 | J30: NIFTY_R4=25353.8 | K30: NIFTY_R4=25515.9 | L30: NIFTY_R4=25517.2 | M30: NIFTY_R4=25245 | N30: NIFTY_R4=25166.1 | O30: NIFTY_R4=25318.2 | P30: NIFTY_R4=25115.75 | Q30: NIFTY_R4=25411.35 | R30: NIFTY_R4=25063.55 | S30: NIFTY_R4=25087.25 | T30: NIFTY_R4=24935.15 | U30: NIFTY_R4=24838.6 | V30: NIFTY_R4=25176.25 | W30: NIFTY_R4=24859.3 | X30: NIFTY_R4=25091.85 | Y30: NIFTY_R4=24961.3 | Z30: NIFTY_R4=24877.95 | AA30: NIFTY_R4=24784.8 | AB30: NIFTY_R4=25215.25 | AC30: NIFTY_R4=25258.05 | AD30: NIFTY_R4=25368.55 | AE30: NIFTY_R4=25281.25 | AF30: NIFTY_R4=25321.5 | AG30: NIFTY_R4=25222.15 | AH30: NIFTY_R4=25172.15 | AI30: NIFTY_R4=24943 | AJ30: NIFTY_R4=24762.35 | AK30: NIFTY_R4=25030.85 | AL30: NIFTY_R4=25047.1 | AM30: NIFTY_R4=25122.75 | AN30: NIFTY_R4=25279.4 | AO30: NIFTY_R4=25162.5 | AP30: NIFTY_R4=25041.05 | AQ30: NIFTY_R4=25024.2 | AR30: NIFTY_R4=25214.4 | AS30: NIFTY_R4=25199.8 | AT30: NIFTY_R4=25316.8 | AU30: NIFTY_R4=25248.6 | AV30: NIFTY_R4=25621 | AW30: NIFTY_R4=25472.55 | AX30: NIFTY_R4=25662 | AY30: NIFTY_R4=25611.95 | AZ30: NIFTY_R4=25563.65 | BA30: NIFTY_R4=25524 | BB30: NIFTY_R4=25301.7 | BC30: NIFTY_R4=25319.65 | BD30: NIFTY_R4 = 25133 | BE30: NIFTY_R4 = 25005.1 | BF30: NIFTY_R4 = 24899.3 | BG30: NIFTY_R4 = 25360.3 | BH30: NIFTY_R4 = 25208.75 | BI30: NIFTY_R4 = 25506.25 | BJ30: NIFTY_R4 = 25397.5 | BK30: NIFTY_R4 = 25414.15 | BL30: NIFTY_R4 = 25531.7 | BM30: NIFTY_R4 = 25633.15 | BN30: NIFTY_R4 = 25457.35 | BO30: NIFTY_R4 = 25645.1 | BP30: NIFTY_R4 = 25735.15 | BQ30: NIFTY_R4 = 26082.4 | BR30: NIFTY_R4 = 26255.65 | BS30: NIFTY_R4 = 26085.7 | BT30: NIFTY_R4 = 26374.9 | BU30: NIFTY_R4 = 26247.05 | BV30: NIFTY_R4 = 26323.95 | BW30: NIFTY_R4 = 26323.95 | BX30: NIFTY_R4 = 26399.5 | BY30: NIFTY_R4 = 26251.45 | BZ30: NIFTY_R4 = 26207.2 | CA30: NIFTY_R4 = 26078.55 | CB30: NIFTY_R4 = 26015.65 | CC30: NIFTY_R4 = 25884.9 | CD30: NIFTY_R4 = 25957.9 | CE30: NIFTY_R4 = 25957.9 | CF30: NIFTY_R4 = 26228.05 | CG30: NIFTY_R4 = 26182.6 | CH30: NIFTY_R4 = 26283.75 | CI30: NIFTY_R4 = 26308.85 | CJ30: NIFTY_R4 = 26249.15 | CK30: NIFTY_R4 = 26216.75 | CL30: NIFTY_R4 = 26489.55 | CM30: NIFTY_R4 = 26559.05 | CN30: NIFTY_R4 = 26322.15 | CO30: NIFTY_R4 = 26420.8 | CP30: NIFTY_R4 = 26235 | CQ30: NIFTY_R4 = 26949 | CR30: NIFTY_R4 = 26552.65 | CS30: NIFTY_R4 = 26419.65 | CT30: NIFTY_R4 = 26578.95 | CU30: NIFTY_R4 = 26345.7 | CV30: NIFTY_R4 = 26336.9 | CW30: NIFTY_R4 = 26352.35 | CX30: NIFTY_R4 = 26620.95 | CY30: NIFTY_R4 = 26533.45 | CZ30: NIFTY_R4 = 26230.95 | DA30: NIFTY_R4 = 26184.2 | DB30: NIFTY_R4 = 26357.65 | DC30: NIFTY_R4 = 26285.25 | DD30: NIFTY_R4 = 26312.1 | DE30: NIFTY_R4 = 26152.9 | DF30: NIFTY_R4 = 26136.15 | DG30: NIFTY_R4 = 26167.65 | DH30: NIFTY_R4 = 26192.2 | DI30: NIFTY_R4 = 26438.2 | DJ30: NIFTY_R4 = 26406.15 | DK30: NIFTY_R4 = 26368.9 | DL30: NIFTY_R4 = 26313.5 | DM30: NIFTY_R4 = 26315.1 | DN30: NIFTY_R4 = 26136.35 | DO30: NIFTY_R4 = 26567.5 | DP30: NIFTY_R4 = 26314.85 | DQ30: NIFTY_R4 = 26771.75 | DR30: NIFTY_R4 = 26576.6 | DS30: NIFTY_R4 = 26477.1 | DT30: NIFTY_R4 = 26379.2 | DU30: NIFTY_R4 = 26426.35 | DV30: NIFTY_R4 = 26318.5 | DW30: NIFTY_R4 = 26469.75 | DX30: NIFTY_R4 = 26325.3 | DZ30: NIFTY_R4 = 26116.55 | EA30: NIFTY_R4 = 26116.55 | EB30: NIFTY_R4 = 26059.8 | EC30: NIFTY_R4 = 25919.8 | ED30: NIFTY_R4 = 25824.4 | EE30: NIFTY_R4 = 25693.95 | EF30: NIFTY_R4 = 25803.6 | EG30: NIFTY_R4 = 25711.65 | EH30: NIFTY_R4 = 26015.6 | EI30: NIFTY_R4 = 26015.6 | EJ30: NIFTY_R4 = 26563.75 | EK30: NIFTY_R4 = 26563.75 | EL30: NIFTY_R4 = 25945.8 | EM30: NIFTY_R4 = 27127.35 | EN30: NIFTY_R4 = 26285.2 | EO30: NIFTY_R4 = 25999.1 | EP30: NIFTY_R4 = 26117.8 | EQ30: NIFTY_R4 = 26150 | ER30: NIFTY_R4 = 26173.15 | ES30: NIFTY_R4 = 26173.05 | ET30: NIFTY_R4 = 26115.8 | EU30: NIFTY_R4 = 25843.2 | EV30: NIFTY_R4 = 26331.35 | EW30: NIFTY_R4 = 26113.6 | EX30: NIFTY_R4 = 26185.15 | EY30: NIFTY_R4 = 26447.45 | EZ30: NIFTY_R4 = 26138.85 | FA30: NIFTY_R4 = 26037.2 | FB30: NIFTY_R4 = 26053.05 | FC30: NIFTY_R4 = 25931.3
A31: NIFTY_R3 | B31: = | C31: 25838.4 | D31: NIFTY_R3=25034.1 | E31: NIFTY_R3=2542125 | F31: NIFTY_R3=25405.45 | G31: NIFTY_R3=25336.9 | H31: NIFTY_R3=25328.4 | I31: NIFTY_R3=25403.05 | J31: NIFTY_R3=25296.55 | K31: NIFTY_R3=25421.75 | L31: NIFTY_R3=25426.9 | M31: NIFTY_R3=25166.8 | N31: NIFTY_R3=25073.8 | O31: NIFTY_R3=25161.2 | P31: NIFTY_R3=25044.6 | Q31: NIFTY_R3=25259.75 | R31: NIFTY_R3=24970.4 | S31: NIFTY_R3=24970.25 | T31: NIFTY_R3=24867.8 | U31: NIFTY_R3=24782.85 | V31: NIFTY_R3=24995.55 | W31: NIFTY_R3=24768.05 | X31: NIFTY_R3=24928.2 | Y31: NIFTY_R3=24875.05 | Z31: NIFTY_R3=24806.8 | AA31: NIFTY_R3=24747.75 | AB31: NIFTY_R3=25150.85 | AC31: NIFTY_R3=25176.25 | AD31: NIFTY_R3=25275.25 | AE31: NIFTY_R3=25238.7 | AF31: NIFTY_R3=25242.6 | AG31: NIFTY_R3=25155.3 | AH31: NIFTY_R3=25088 | AI31: NIFTY_R3=24862.9 | AJ31: NIFTY_R3=24699.05 | AK31: NIFTY_R3=24899.1 | AL31: NIFTY_R3=24950.1 | AM31: NIFTY_R3=24994.2 | AN31: NIFTY_R3=25179.85 | AO31: NIFTY_R3=25052.45 | AP31: NIFTY_R3=24989.2 | AQ31: NIFTY_R3=24980.05 | AR31: NIFTY_R3=25154.85 | AS31: NIFTY_R3=25145.65 | AT31: NIFTY_R3=25257.7 | AU31: NIFTY_R3=25211.9 | AV31: NIFTY_R3=25501.15 | AW31: NIFTY_R3=25430.55 | AX31: NIFTY_R3=25591 | AY31: NIFTY_R3=25550.9 | AZ31: NIFTY_R3=25486.35 | BA31: NIFTY_R3=25436.65 | BB31: NIFTY_R3=25251.1 | BC31: NIFTY_R3=25244 | BD31: NIFTY_R3 = 25044.85 | BE31: NIFTY_R3 = 24933.85 | BF31: NIFTY_R3 = 24843.45 | BG31: NIFTY_R3 = 25196.2 | BH31: NIFTY_R3 = 25107.45 | BI31: NIFTY_R3 = 25369.5 | BJ31: NIFTY_R3 = 25338.65 | BK31: NIFTY_R3 = 25340.25 | BL31: NIFTY_R3 = 25420.9 | BM31: NIFTY_R3 = 25532.35 | BN31: NIFTY_R3 = 25394 | BO31: NIFTY_R3 = 25533.5 | BP31: NIFTY_R3 = 25611.8 | BQ31: NIFTY_R3 = 25930.05 | BR31: NIFTY_R3 = 26097.6 | BS31: NIFTY_R3 = 26035.25 | BT31: NIFTY_R3 = 26284.65 | BU31: NIFTY_R3 = 26146.1 | BV31: NIFTY_R3 = 26217.95 | BW31: NIFTY_R3 = 26217.95 | BX31: NIFTY_R3 = 26280.25 | BY31: NIFTY_R3 = 26178.3 | BZ31: NIFTY_R3 = 26122.7 | CA31: NIFTY_R3 = 25986.75 | CB31: NIFTY_R3 = 25939.55 | CC31: NIFTY_R3 = 25816.3 | CD31: NIFTY_R3 = 25822.35 | CE31: NIFTY_R3 = 25822.35 | CF31: NIFTY_R3 = 26057.3 | CG31: NIFTY_R3 = 26099.9 | CH31: NIFTY_R3 = 26192.75 | CI31: NIFTY_R3 = 26185.95 | CJ31: NIFTY_R3 = 26174.15 | CK31: NIFTY_R3 = 26154.45 | CL31: NIFTY_R3 = 26351.25 | CM31: NIFTY_R3 = 26454.9 | CN31: NIFTY_R3 = 26274.5 | CO31: NIFTY_R3 = 26328.15 | CP31: NIFTY_R3 = 26167.55 | CQ31: NIFTY_R3 = 26704.85 | CR31: NIFTY_R3 = 26471 | CS31: NIFTY_R3 = 26373.35 | CT31: NIFTY_R3 = 26494.55 | CU31: NIFTY_R3 = 26282 | CV31: NIFTY_R3 = 26246.75 | CW31: NIFTY_R3 = 26267.65 | CX31: NIFTY_R3 = 26481.5 | CY31: NIFTY_R3 = 26415.2 | CZ31: NIFTY_R3 = 26128.5 | DA31: NIFTY_R3 = 26105.35 | DB31: NIFTY_R3 = 26212.7 | DC31: NIFTY_R3 = 26209.35 | DD31: NIFTY_R3 = 26223.8 | DE31: NIFTY_R3 = 26095.5 | DF31: NIFTY_R3 = 26067.15 | DG31: NIFTY_R3 = 26079.2 | DH31: NIFTY_R3 = 26125.9 | DI31: NIFTY_R3 = 26352.35 | DJ31: NIFTY_R3 = 26348.6 | DK31: NIFTY_R3 = 26324.75 | DL31: NIFTY_R3 = 26257.05 | DM31: NIFTY_R3 = 26245.65 | DN31: NIFTY_R3 = 26083.15 | DO31: NIFTY_R3 = 26441 | DP31: NIFTY_R3 = 26275.75 | DQ31: NIFTY_R3 = 26627.85 | DR31: NIFTY_R3 = 26508.8 | DS31: NIFTY_R3 = 26409.4 | DT31: NIFTY_R3 = 26315.2 | DU31: NIFTY_R3 = 26328.65 | DV31: NIFTY_R3 = 26192.55 | DW31: NIFTY_R3 = 26250.9 | DX31: NIFTY_R3 = 26183.45 | DZ31: NIFTY_R3 = 26035.55 | EA31: NIFTY_R3 = 26035.55 | EB31: NIFTY_R3 = 25901.55 | EC31: NIFTY_R3 = 25713.5 | ED31: NIFTY_R3 = 25694.85 | EE31: NIFTY_R3 = 25578.6 | EF31: NIFTY_R3 = 25617.95 | EG31: NIFTY_R3 = 25598.45 | EH31: NIFTY_R3 = 25829.8 | EI31: NIFTY_R3 = 25829.8 | EJ31: NIFTY_R3 = 26189.45 | EK31: NIFTY_R3 = 26189.45 | EL31: NIFTY_R3 = 25666.55 | EM31: NIFTY_R3 = 26865.3 | EN31: NIFTY_R3 = 26129.65 | EO31: NIFTY_R3 = 25918.6 | EP31: NIFTY_R3 = 25979.85 | EQ31: NIFTY_R3 = 26074.1 | ER31: NIFTY_R3 = 26111.9 | ES31: NIFTY_R3 = 26118.5 | ET31: NIFTY_R3 = 26046.1 | EU31: NIFTY_R3 = 25772.25 | EV31: NIFTY_R3 = 26119.9 | EW31: NIFTY_R3 = 25997.2 | EX31: NIFTY_R3 = 26066.1 | EY31: NIFTY_R3 = 26260.05 | EZ31: NIFTY_R3 = 25980.4 | FA31: NIFTY_R3 = 25948.6 | FB31: NIFTY_R3 = 25915.95 | FC31: NIFTY_R3 = 25838.4
A32: NIFTY_R2 | B32: = | C32: 25745.5 | D32: NIFTY_R2=25227.6 | E32: NIFTY_R2=25333.25 | F32: NIFTY_R2=25330.4 | G32: NIFTY_R2=25287.6 | H32: NIFTY_R2=25236.5 | I32: NIFTY_R2=25257.25 | J32: NIFTY_R2=25239.25 | K32: NIFTY_R2=25327.65 | L32: NIFTY_R2=25336.55 | M32: NIFTY_R2=25088.55 | N32: NIFTY_R2=24981.50 | O32: NIFTY_R2=25004.15 | P32: NIFTY_R2=24973.45 | Q32: NIFTY_R2=25108.1 | R32: NIFTY_R2=24877.3 | S32: NIFTY_R2=24853.25 | T32: NIFTY_R2=24800.45 | U32: NIFTY_R2=24727.15 | V32: NIFTY_R2=24814.9 | W32: NIFTY_R2=24676.75 | X32: NIFTY_R2=24764.5 | Y32: NIFTY_R2=24788.85 | Z32: NIFTY_R2=24735.7 | AA32: NIFTY_R2=24710.7 | AB32: NIFTY_R2=25086.4 | AC32: NIFTY_R2=25094.45 | AD32: NIFTY_R2=25182 | AE32: NIFTY_R2=25196.2 | AF32: NIFTY_R2=25163.75 | AG32: NIFTY_R2=25088.4 | AH32: NIFTY_R2=25003.8 | AI32: NIFTY_R2=24782.75 | AJ32: NIFTY_R2=24635.75 | AK32: NIFTY_R2=24767.35 | AL32: NIFTY_R2=24853.1 | AM32: NIFTY_R2=24865.6 | AN32: NIFTY_R2=25080.3 | AO32: NIFTY_R2=24942.4 | AP32: NIFTY_R2=24937.35 | AQ32: NIFTY_R2=24935.95 | AR32: NIFTY_R2=25095.25 | AS32: NIFTY_R2=25091.45 | AT32: NIFTY_R2=25198.55 | AU32: NIFTY_R2=25175.15 | AV32: NIFTY_R2=25381.25 | AW32: NIFTY_R2=25388.5 | AX32: NIFTY_R2=25519.95 | AY32: NIFTY_R2=25489.8 | AZ32: NIFTY_R2=25409 | BA32: NIFTY_R2=25349.25 | BB32: NIFTY_R2=25200.45 | BC32: NIFTY_R2=25168.35 | BD32: NIFTY_R2 = 24956.75 | BE32: NIFTY_R2 = 24862.55 | BF32: NIFTY_R2 = 24787.65 | BG32: NIFTY_R2 = 25032.05 | BH32: NIFTY_R2 = 25006.1 | BI32: NIFTY_R2 = 25232.7 | BJ32: NIFTY_R2 = 25279.75 | BK32: NIFTY_R2 = 25266.4 | BL32: NIFTY_R2 = 25310.05 | BM32: NIFTY_R2 = 25431.55 | BN32: NIFTY_R2 = 25330.65 | BO32: NIFTY_R2 = 25421.95 | BP32: NIFTY_R2 = 25488.5 | BQ32: NIFTY_R2 = 25777.75 | BR32: NIFTY_R2 = 25939.55 | BS32: NIFTY_R2 = 25984.8 | BT32: NIFTY_R2 = 26194.45 | BU32: NIFTY_R2 = 26045.1 | BV32: NIFTY_R2 = 26111.95 | BW32: NIFTY_R2 = 26111.95 | BX32: NIFTY_R2 = 26160.95 | BY32: NIFTY_R2 = 26105.2 | BZ32: NIFTY_R2 = 26038.25 | CA32: NIFTY_R2 = 25894.9 | CB32: NIFTY_R2 = 25863.5 | CC32: NIFTY_R2 = 25747.75 | CD32: NIFTY_R2 = 25686.8 | CE32: NIFTY_R2 = 25686.8 | CF32: NIFTY_R2 = 25886.55 | CG32: NIFTY_R2 = 26017.25 | CH32: NIFTY_R2 = 26101.7 | CI32: NIFTY_R2 = 26063.1 | CJ32: NIFTY_R2 = 26099.2 | CK32: NIFTY_R2 = 26092.15 | CL32: NIFTY_R2 = 26212.95 | CM32: NIFTY_R2 = 26350.8 | CN32: NIFTY_R2 = 26226.85 | CO32: NIFTY_R2 = 26235.45 | CP32: NIFTY_R2 = 26100.05 | CQ32: NIFTY_R2 = 26460 | CR32: NIFTY_R2 = 26391.2 | CS32: NIFTY_R2 = 26327.05 | CT32: NIFTY_R2 = 26410.2 | CU32: NIFTY_R2 = 26218.3 | CV32: NIFTY_R2 = 26156.6 | CW32: NIFTY_R2 = 26182.95 | CX32: NIFTY_R2 = 26342.05 | CY32: NIFTY_R2 = 26296.95 | CZ32: NIFTY_R2 = 26026.1 | DA32: NIFTY_R2 = 26026.5 | DB32: NIFTY_R2 = 26067.75 | DC32: NIFTY_R2 = 26133.5 | DD32: NIFTY_R2 = 26135.45 | DE32: NIFTY_R2 = 26038.15 | DF32: NIFTY_R2 = 25998.15 | DG32: NIFTY_R2 = 25990.8 | DH32: NIFTY_R2 = 26059.65 | DI32: NIFTY_R2 = 26266.55 | DJ32: NIFTY_R2 = 26291.1 | DK32: NIFTY_R2 = 26280.55 | DL32: NIFTY_R2 = 26200.65 | DM32: NIFTY_R2 = 26176.25 | DN32: NIFTY_R2 = 26029.95 | DO32: NIFTY_R2 = 26314.45 | DP32: NIFTY_R2 = 26236.65 | DQ32: NIFTY_R2 = 26483.9 | DR32: NIFTY_R2 = 26441 | DS32: NIFTY_R2 = 26341.65 | DT32: NIFTY_R2 = 26251.2 | DU32: NIFTY_R2 = 26230.9 | DV32: NIFTY_R2 = 26066.55 | DW32: NIFTY_R2 = 26032 | DX32: NIFTY_R2 = 26041.65 | DZ32: NIFTY_R2 = 25954.5 | EA32: NIFTY_R2 = 25954.5 | EB32: NIFTY_R2 = 25743.25 | EC32: NIFTY_R2 = 25507.25 | ED32: NIFTY_R2 = 25565.3 | EE32: NIFTY_R2 = 25463.3 | EF32: NIFTY_R2 = 25432.3 | EG32: NIFTY_R2 = 25485.3 | EH32: NIFTY_R2 = 25643.95 | EI32: NIFTY_R2 = 25643.95 | EJ32: NIFTY_R2 = 25815.2 | EK32: NIFTY_R2 = 25815.2 | EL32: NIFTY_R2 = 25387.35 | EM32: NIFTY_R2 = 26603.25 | EN32: NIFTY_R2 = 25974.1 | EO32: NIFTY_R2 = 25838.15 | EP32: NIFTY_R2 = 25841.9 | EQ32: NIFTY_R2 = 25998.15 | ER32: NIFTY_R2 = 26050.7 | ES32: NIFTY_R2 = 26063.95 | ET32: NIFTY_R2 = 25976.4 | EU32: NIFTY_R2 = 25701.3 | EV32: NIFTY_R2 = 25908.45 | EW32: NIFTY_R2 = 25880.8 | EX32: NIFTY_R2 = 25947.1 | EY32: NIFTY_R2 = 26072.7 | EZ32: NIFTY_R2 = 25822 | FA32: NIFTY_R2 = 25860.05 | FB32: NIFTY_R2 = 25778.9 | FC32: NIFTY_R2 = 25745.5
A33: NIFTY_R1 | B33: = | C33: 25614 | D33: NIFTY_R1=25154.5 | E33: NIFTY_R1=25264.5 | F33: NIFTY_R1=25271.2 | G33: NIFTY_R1=25199.5 | H33: NIFTY_R1=25102.45 | I33: NIFTY_R1=25173.95 | J33: NIFTY_R1=25150.1 | K33: NIFTY_R1=25273.75 | L33: NIFTY_R1=25199.35 | M33: NIFTY_R1=24962.8 | N33: NIFTY_R1=24831.2 | O33: NIFTY_R1=24912.65 | P33: NIFTY_R1=24914.25 | Q33: NIFTY_R1=24938.25 | R33: NIFTY_R1=24721.3 | S33: NIFTY_R1=24788 | T33: NIFTY_R1=24725 | U33: NIFTY_R1=24650.65 | V33: NIFTY_R1=24705.5 | W33: NIFTY_R1=24520.05 | X33: NIFTY_R1=24674.8 | Y33: NIFTY_R1=24638.1 | Z33: NIFTY_R1=2467750 | AA33: NIFTY_R1=24671 | AB33: NIFTY_R1=24981.7 | AC33: NIFTY_R1=25037.55 | AD33: NIFTY_R1=25116.25 | AE33: NIFTY_R1=25139.95 | AF33: NIFTY_R1=25016.9 | AG33: NIFTY_R1=25028.1 | AH33: NIFTY_R1=24857.95 | AI33: NIFTY_R1=24641.85 | AJ33: NIFTY_R1=24531.3 | AK33: NIFTY_R1=24696.2 | AL33: NIFTY_R1=24716.3 | AM33: NIFTY_R1=24790.35 | AN33: NIFTY_R1=24907.3 | AO33: NIFTY_R1=24841.7 | AP33: NIFTY_R1=24855.25 | AQ33: NIFTY_R1=24902.25 | AR33: NIFTY_R1=25034.2 | AS33: NIFTY_R1=25048.5 | AT33: NIFTY_R1=25156.3 | AU33: NIFTY_R1=25122.2 | AV33: NIFTY_R1=25310.20 | AW33: NIFTY_R1=25359.4 | AX33: NIFTY_R1=25471.8 | AY33: NIFTY_R1=25408.45 | AZ33: NIFTY_R1=25305.7 | BA33: NIFTY_R1=25259.4 | BB33: NIFTY_R1=25128.7 | BC33: NIFTY_R1=25029.6 | BD33: NIFTY_R1 = 24805.7 | BE33: NIFTY_R1 = 24748.75 | BF33: NIFTY_R1 = 24699.35 | BG33: NIFTY_R1 = 24934.2 | BH33: NIFTY_R1 = 24950.2 | BI33: NIFTY_R1 = 25155.2 | BJ33: NIFTY_R1 = 25194.05 | BK33: NIFTY_R1 = 25156.25 | BL33: NIFTY_R1 = 25245.95 | BM33: NIFTY_R1 = 25358.45 | BN33: NIFTY_R1 = 25279 | BO33: NIFTY_R1 = 25283.7 | BP33: NIFTY_R1 = 25406 | BQ33: NIFTY_R1 = 25681.5 | BR33: NIFTY_R1 = 25824.7 | BS33: NIFTY_R1 = 25926.7 | BT33: NIFTY_R1 = 26042.9 | BU33: NIFTY_R1 = 25920.15 | BV33: NIFTY_R1 = 26039 | BW33: NIFTY_R1 = 26039 | BX33: NIFTY_R1 = 26048.6 | BY33: NIFTY_R1 = 25991.5 | BZ33: NIFTY_R1 = 25880.15 | CA33: NIFTY_R1 = 25829.15 | CB33: NIFTY_R1 = 25730.55 | CC33: NIFTY_R1 = 25628.7 | CD33: NIFTY_R1 = 25589.55 | CE33: NIFTY_R1 = 25589.55 | CF33: NIFTY_R1 = 25790.75 | CG33: NIFTY_R1 = 25946.5 | CH33: NIFTY_R1 = 25990.45 | CI33: NIFTY_R1 = 25986.55 | CJ33: NIFTY_R1 = 26056.3 | CK33: NIFTY_R1 = 26001.1 | CL33: NIFTY_R1 = 26132.8 | CM33: NIFTY_R1 = 26271.45 | CN33: NIFTY_R1 = 26147.5 | CO33: NIFTY_R1 = 26097.5 | CP33: NIFTY_R1 = 25992.45 | CQ33: NIFTY_R1 = 26332.65 | CR33: NIFTY_R1 = 26303.35 | CS33: NIFTY_R1 = 26265 | CT33: NIFTY_R1 = 26292.95 | CU33: NIFTY_R1 = 26125.25 | CV33: NIFTY_R1 = 26071.3 | CW33: NIFTY_R1 = 26108.35 | CX33: NIFTY_R1 = 26264.25 | CY33: NIFTY_R1 = 26128.75 | CZ33: NIFTY_R1 = 25932.85 | DA33: NIFTY_R1 = 25892.25 | DB33: NIFTY_R1 = 25983.15 | DC33: NIFTY_R1 = 26090.2 | DD33: NIFTY_R1 = 26081.4 | DE33: NIFTY_R1 = 25949.1 | DF33: NIFTY_R1 = 25908.35 | DG33: NIFTY_R1 = 25900.15 | DH33: NIFTY_R1 = 26013 | DI33: NIFTY_R1 = 26219.45 | DJ33: NIFTY_R1 = 26234.1 | DK33: NIFTY_R1 = 26211.35 | DL33: NIFTY_R1 = 26121.45 | DM33: NIFTY_R1 = 26059.15 | DN33: NIFTY_R1 = 25984.4 | DO33: NIFTY_R1 = 26222.05 | DP33: NIFTY_R1 = 26191.6 | DQ33: NIFTY_R1 = 26406.25 | DR33: NIFTY_R1 = 26345.65 | DS33: NIFTY_R1 = 26260.2 | DT33: NIFTY_R1 = 26195.95 | DU33: NIFTY_R1 = 26053.9 | DV33: NIFTY_R1 = 25874.95 | DW33: NIFTY_R1 = 25911.15 | DX33: NIFTY_R1 = 25886.95 | DZ33: NIFTY_R1 = 25824.45 | EA33: NIFTY_R1 = 25824.45 | EB33: NIFTY_R1 = 25487.9 | EC33: NIFTY_R1 = 25332.35 | ED33: NIFTY_R1 = 25427.6 | EE33: NIFTY_R1 = 25255.95 | EF33: NIFTY_R1 = 25303.85 | EG33: NIFTY_R1 = 25414 | EH33: NIFTY_R1 = 25531.45 | EI33: NIFTY_R1 = 25531.45 | EJ33: NIFTY_R1 = 25320.3 | EK33: NIFTY_R1 = 25320.3 | EL33: NIFTY_R1 = 25237.85 | EM33: NIFTY_R1 = 26165.4 | EN33: NIFTY_R1 = 25875.05 | EO33: NIFTY_R1 = 25740.45 | EP33: NIFTY_R1 = 25767.8 | EQ33: NIFTY_R1 = 25932.75 | ER33: NIFTY_R1 = 25992.9 | ES33: NIFTY_R1 = 26008.9 | ET33: NIFTY_R1 = 25891.8 | EU33: NIFTY_R1 = 25586.2 | EV33: NIFTY_R1 = 25795.6 | EW33: NIFTY_R1 = 25803.1 | EX33: NIFTY_R1 = 25883.2 | EY33: NIFTY_R1 = 25763.5 | EZ33: NIFTY_R1 = 25696.6 | FA33: NIFTY_R1 = 25786.5 | FB33: NIFTY_R1 = 25601.75 | FC33: NIFTY_R1 = 25614
A34: NIFTY_CP | B34: = | C34: 25521.1 | D34: NIFTY_CP=25078.45 | E34: NIFTY_CP=25176.5 | F34: NIFTY_CP=25196.15 | G34: NIFTY_CP=25150.25 | H34: NIFTY_CP=25010.55 | I34: NIFTY_CP=25028.15 | J34: NIFTY_CP=25092.8 | K34: NIFTY_CP=25179.65 | L34: NIFTY_CP=25109 | M34: NIFTY_CP=24884.55 | N34: NIFTY_CP=24738.9 | O34: NIFTY_CP=24755 | P34: NIFTY_CP=24843.1 | Q34: NIFTY_CP=24786.6 | R34: NIFTY_CP=24628.2 | S34: NIFTY_CP=24671 | T34: NIFTY_CP=24657.65 | U34: NIFTY_CP=24594.95 | V34: NIFTY_CP=24524.85 | W34: NIFTY_CP=24428.75 | X34: NIFTY_CP=24511.1 | Y34: NIFTY_CP=24551.9 | Z34: NIFTY_CP=2460640 | AA34: NIFTY_CP=24638.95 | AB34: NIFTY_CP=24917.25 | AC34: NIFTY_CP=24955.75 | AD34: NIFTY_CP=25023 | AE34: NIFTY_CP=25097.45 | AF34: NIFTY_CP=24938.05 | AG34: NIFTY_CP=24964.2 | AH34: NIFTY_CP=24773.75 | AI34: NIFTY_CP=24561.7 | AJ34: NIFTY_CP=24468 | AK34: NIFTY_CP=24564.45 | AL34: NIFTY_CP=24619.35 | AM34: NIFTY_CP=24661.75 | AN34: NIFTY_CP=24807.75 | AO34: NIFTY_CP=24731.65 | AP34: NIFTY_CP=24803.4 | AQ34: NIFTY_CP=24858.15 | AR34: NIFTY_CP=24974.6 | AS34: NIFTY_CP=24994.3 | AT34: NIFTY_CP=25097.15 | AU34: NIFTY_CP=25085.45 | AV34: NIFTY_CP=25190.3 | AW34: NIFTY_CP=25317.35 | AX34: NIFTY_CP=25400.75 | AY34: NIFTY_CP=25347.35 | AZ34: NIFTY_CP=25228.35 | BA34: NIFTY_CP=25172 | BB34: NIFTY_CP=25078.05 | BC34: NIFTY_CP=24953.95 | BD34: NIFTY_CP = 24717.6 | BE34: NIFTY_CP = 24677.45 | BF34: NIFTY_CP = 24643.55 | BG34: NIFTY_CP = 24770.05 | BH34: NIFTY_CP = 24848.85 | BI34: NIFTY_CP = 25018.4 | BJ34: NIFTY_CP = 25135.15 | BK34: NIFTY_CP = 25082.4 | BL34: NIFTY_CP = 25135.1 | BM34: NIFTY_CP = 25257.65 | BN34: NIFTY_CP = 25215.65 | BO34: NIFTY_CP = 25172.15 | BP34: NIFTY_CP = 25282.7 | BQ34: NIFTY_CP = 25529.2 | BR34: NIFTY_CP = 25666.65 | BS34: NIFTY_CP = 25876.25 | BT34: NIFTY_CP = 25952.7 | BU34: NIFTY_CP = 25819.15 | BV34: NIFTY_CP = 25933 | BW34: NIFTY_CP = 25933 | BX34: NIFTY_CP = 25929.3 | BY34: NIFTY_CP = 25918.4 | BZ34: NIFTY_CP = 25795.7 | CA34: NIFTY_CP = 25737.3 | CB34: NIFTY_CP = 25654.5 | CC34: NIFTY_CP = 25560.15 | CD34: NIFTY_CP = 25454 | CE34: NIFTY_CP = 25454 | CF34: NIFTY_CP = 25620 | CG34: NIFTY_CP = 25863.85 | CH34: NIFTY_CP = 25899.4 | CI34: NIFTY_CP = 25863.7 | CJ34: NIFTY_CP = 25981.35 | CK34: NIFTY_CP = 25938.8 | CL34: NIFTY_CP = 25994.5 | CM34: NIFTY_CP = 26167.35 | CN34: NIFTY_CP = 26099.85 | CO34: NIFTY_CP = 26004.8 | CP34: NIFTY_CP = 25924.95 | CQ34: NIFTY_CP = 26087.8 | CR34: NIFTY_CP = 26222.65 | CS34: NIFTY_CP = 26218.7 | CT34: NIFTY_CP = 26208.6 | CU34: NIFTY_CP = 26061.55 | CV34: NIFTY_CP = 25981.15 | CW34: NIFTY_CP = 26023.65 | CX34: NIFTY_CP = 26124.8 | CY34: NIFTY_CP = 26010.5 | CZ34: NIFTY_CP = 25830.45 | DA34: NIFTY_CP = 25813.4 | DB34: NIFTY_CP = 25838.2 | DC34: NIFTY_CP = 26014.35 | DD34: NIFTY_CP = 25993.05 | DE34: NIFTY_CP = 25891.75 | DF34: NIFTY_CP = 25839.35 | DG34: NIFTY_CP = 25814.75 | DH34: NIFTY_CP = 25946.75 | DI34: NIFTY_CP = 26133.65 | DJ34: NIFTY_CP = 26176.6 | DK34: NIFTY_CP = 26167.15 | DL34: NIFTY_CP = 26065.05 | DM34: NIFTY_CP = 25989.75 | DN34: NIFTY_CP = 25931.2 | DO34: NIFTY_CP = 26095.5 | DP34: NIFTY_CP = 26152.5 | DQ34: NIFTY_CP = 26262.3 | DR34: NIFTY_CP = 26277.8 | DS34: NIFTY_CP = 26192.45 | DT34: NIFTY_CP = 26131.95 | DU34: NIFTY_CP = 25956.15 | DV34: NIFTY_CP = 25748.95 | DW34: NIFTY_CP = 25692.25 | DX34: NIFTY_CP = 25745.15 | DZ34: NIFTY_CP = 25743.4 | EA34: NIFTY_CP = 25743.4 | EB34: NIFTY_CP = 25329.6 | EC34: NIFTY_CP = 25126.1 | ED34: NIFTY_CP = 25298.05 | EE34: NIFTY_CP = 25140.65 | EF34: NIFTY_CP = 25118.2 | EG34: NIFTY_CP = 25300.85 | EH34: NIFTY_CP = 25345.6 | EI34: NIFTY_CP = 25345.6 | EJ34: NIFTY_CP = 24946.05 | EK34: NIFTY_CP = 24946.05 | EL34: NIFTY_CP = 24958.65 | EM34: NIFTY_CP = 25903.35 | EN34: NIFTY_CP = 25719.5 | EO34: NIFTY_CP = 25660 | EP34: NIFTY_CP = 25629.85 | EQ34: NIFTY_CP = 25856.8 | ER34: NIFTY_CP = 25931.7 | ES34: NIFTY_CP = 25954.25 | ET34: NIFTY_CP = 25822.1 | EU34: NIFTY_CP = 25515.25 | EV34: NIFTY_CP = 25584.15 | EW34: NIFTY_CP = 25686.7 | EX34: NIFTY_CP = 25764.2 | EY34: NIFTY_CP = 25576.15 | EZ34: NIFTY_CP = 25538.2 | FA34: NIFTY_CP = 25697.95 | FB34: NIFTY_CP = 25464.7 | FC34: NIFTY_CP = 25521.1
A35: NIFTY_S1 | B35: = | C35: 25389.6 | D35: NIFTY_S1=250005.8 | E35: NIFTY_S1=25107.75 | F35: NIFTY_S1=25136.95 | G35: NIFTY_S1=25062.2 | H35: NIFTY_S1=24876.55 | I35: NIFTY_S1=24944.85 | J35: NIFTY_S1=25003.65 | K35: NIFTY_S1=25125.75 | L35: NIFTY_S1=24971.8 | M35: NIFTY_S1=24758.8 | N35: NIFTY_S1=24588.6 | O35: NIFTY_S1=24664.1 | P35: NIFTY_S1=24783.9 | Q35: NIFTY_S1=24616.75 | R35: NIFTY_S1=24472.2 | S35: NIFTY_S1=24605.75 | T35: NIFTY_S1=24582.2 | U35: NIFTY_S1=24518.45 | V35: NIFTY_S1=24415.45 | W35: NIFTY_S1=24272.05 | X35: NIFTY_S1=24421.4 | Y35: NIFTY_S1=24401.15 | Z35: NIFTY_S1=24548.2 | AA35: NIFTY_S1=24594.25 | AB35: NIFTY_S1=24812.55 | AC35: NIFTY_S1=24898.85 | AD35: NIFTY_S1=24957.25 | AE35: NIFTY_S1=25041.2 | AF35: NIFTY_S1=24791.2 | AG35: NIFTY_S1=24900.9 | AH35: NIFTY_S1=24627.9 | AI35: NIFTY_S1=24420.8 | AJ35: NIFTY_S1=24363.55 | AK35: NIFTY_S1=24493.3 | AL35: NIFTY_S1=24482.6 | AM35: NIFTY_S1=24586.5 | AN35: NIFTY_S1=24634.75 | AO35: NIFTY_S1=24630.95 | AP35: NIFTY_S1=24721.3 | AQ35: NIFTY_S1=24824.45 | AR35: NIFTY_S1=24913.55 | AS35: NIFTY_S1=24951.35 | AT35: NIFTY_S1=25054.9 | AU35: NIFTY_S1=25032.5 | AV35: NIFTY_S1=25119.25 | AW35: NIFTY_S1=25288.25 | AX35: NIFTY_S1=25352.6 | AY35: NIFTY_S1=25266 | AZ35: NIFTY_S1=25125.05 | BA35: NIFTY_S1=25082.15 | BB35: NIFTY_S1=25006.3 | BC35: NIFTY_S1=24815.2 | BD35: NIFTY_S1 = 24566.55 | BE35: NIFTY_S1 = 24563.65 | BF35: NIFTY_S1 = 24555.25 | BG35: NIFTY_S1 = 24672.2 | BH35: NIFTY_S1 = 24792.95 | BI35: NIFTY_S1 = 24940.9 | BJ35: NIFTY_S1 = 25049.45 | BK35: NIFTY_S1 = 24972.25 | BL35: NIFTY_S1 = 25071 | BM35: NIFTY_S1 = 25184.55 | BN35: NIFTY_S1 = 25164 | BO35: NIFTY_S1 = 25033.9 | BP35: NIFTY_S1 = 25200.2 | BQ35: NIFTY_S1 = 25432.95 | BR35: NIFTY_S1 = 25551.8 | BS35: NIFTY_S1 = 25818.15 | BT35: NIFTY_S1 = 25801.15 | BU35: NIFTY_S1 = 25694.2 | BV35: NIFTY_S1 = 25860.05 | BW35: NIFTY_S1 = 25860.05 | BX35: NIFTY_S1 = 25816.95 | BY35: NIFTY_S1 = 25804.7 | BZ35: NIFTY_S1 = 25637.6 | CA35: NIFTY_S1 = 25671.55 | CB35: NIFTY_S1 = 25521.55 | CC35: NIFTY_S1 = 25441.1 | CD35: NIFTY_S1 = 25356.75 | CE35: NIFTY_S1 = 25356.75 | CF35: NIFTY_S1 = 25524.2 | CG35: NIFTY_S1 = 25793.1 | CH35: NIFTY_S1 = 25788.15 | CI35: NIFTY_S1 = 25787.15 | CJ35: NIFTY_S1 = 25938.45 | CK35: NIFTY_S1 = 25847.75 | CL35: NIFTY_S1 = 25914.35 | CM35: NIFTY_S1 = 26088 | CN35: NIFTY_S1 = 26020.5 | CO35: NIFTY_S1 = 25866.85 | CP35: NIFTY_S1 = 25817.35 | CQ35: NIFTY_S1 = 25960.45 | CR35: NIFTY_S1 = 26134.8 | CS35: NIFTY_S1 = 26156.65 | CT35: NIFTY_S1 = 26091.35 | CU35: NIFTY_S1 = 25968.5 | CV35: NIFTY_S1 = 25895.85 | CW35: NIFTY_S1 = 25949.05 | CX35: NIFTY_S1 = 26047 | CY35: NIFTY_S1 = 25842.3 | CZ35: NIFTY_S1 = 25737.2 | DA35: NIFTY_S1 = 25679.15 | DB35: NIFTY_S1 = 25753.6 | DC35: NIFTY_S1 = 25971.05 | DD35: NIFTY_S1 = 25939 | DE35: NIFTY_S1 = 25802.7 | DF35: NIFTY_S1 = 25749.55 | DG35: NIFTY_S1 = 25727.1 | DH35: NIFTY_S1 = 25900.1 | DI35: NIFTY_S1 = 26086.55 | DJ35: NIFTY_S1 = 26119.6 | DK35: NIFTY_S1 = 26097.95 | DL35: NIFTY_S1 = 25985.85 | DM35: NIFTY_S1 = 25872.65 | DN35: NIFTY_S1 = 25885.5 | DO35: NIFTY_S1 = 26003.1 | DP35: NIFTY_S1 = 26107.45 | DQ35: NIFTY_S1 = 26184.65 | DR35: NIFTY_S1 = 26182.5 | DS35: NIFTY_S1 = 26111 | DT35: NIFTY_S1 = 26076.7 | DU35: NIFTY_S1 = 25779.15 | DV35: NIFTY_S1 = 25557.35 | DW35: NIFTY_S1 = 25571.4 | DX35: NIFTY_S1 = 25590.45 | DZ35: NIFTY_S1 = 25613.35 | EA35: NIFTY_S1 = 25613.35 | EB35: NIFTY_S1 = 25074.25 | EC35: NIFTY_S1 = 24951.2 | ED35: NIFTY_S1 = 25160 | EE35: NIFTY_S1 = 24933.3 | EF35: NIFTY_S1 = 24989.75 | EG35: NIFTY_S1 = 25229.55 | EH35: NIFTY_S1 = 25233.1 | EI35: NIFTY_S1 = 25233.1 | EJ35: NIFTY_S1 = 24451.15 | EK35: NIFTY_S1 = 24451.15 | EL35: NIFTY_S1 = 24809.15 | EM35: NIFTY_S1 = 25465.5 | EN35: NIFTY_S1 = 25620.45 | EO35: NIFTY_S1 = 25562.3 | EP35: NIFTY_S1 = 25555.75 | EQ35: NIFTY_S1 = 25791.4 | ER35: NIFTY_S1 = 25873.9 | ES35: NIFTY_S1 = 25899.32 | ET35: NIFTY_S1 = 25737.5 | EU35: NIFTY_S1 = 25400.15 | EV35: NIFTY_S1 = 25471.3 | EW35: NIFTY_S1 = 25609 | EX35: NIFTY_S1 = 25700.3 | EY35: NIFTY_S1 = 25266.95 | EZ35: NIFTY_S1 = 25412.8 | FA35: NIFTY_S1 = 25624.4 | FB35: NIFTY_S1 = 25287.55 | FC35: NIFTY_S1 = 25389.6
A36: NIFTY_S2 | B36: = | C36: 25296.7 | D36: NIFTY_S2=24929.3 | E36: NIFTY_S2=25019.75 | F36: NIFTY_S2=25061.9 | G36: NIFTY_S2=25012.9 | H36: NIFTY_S2=24784.6 | I36: NIFTY_S2=24799.05 | J36: NIFTY_S2=24946.35 | K36: NIFTY_S2=25031.65 | L36: NIFTY_S2=24881.45 | M36: NIFTY_S2=24680.55 | N36: NIFTY_S2=24496.3 | O36: NIFTY_S2=24507.05 | P36: NIFTY_S2=24712.75 | Q36: NIFTY_S2=24465.1 | R36: NIFTY_S2=24379.1 | S36: NIFTY_S2=24488.75 | T36: NIFTY_S2=24514.85 | U36: NIFTY_S2=24462.75 | V36: NIFTY_S2=24234.8 | W36: NIFTY_S2=24180.75 | X36: NIFTY_S2=24257.7 | Y36: NIFTY_S2=24314.95 | Z36: NIFTY_S2=24477.1 | AA36: NIFTY_S2=24557.2 | AB36: NIFTY_S2=24748.1 | AC36: NIFTY_S2=24817.05 | AD36: NIFTY_S2=24864 | AE36: NIFTY_S2=24998.7 | AF36: NIFTY_S2=24712.35 | AG36: NIFTY_S2=24834 | AH36: NIFTY_S2=24543.7 | AI36: NIFTY_S2=24340.65 | AJ36: NIFTY_S2=24300.25 | AK36: NIFTY_S2=24361.55 | AL36: NIFTY_S2=24385.6 | AM36: NIFTY_S2=24457.9 | AN36: NIFTY_S2=24535.2 | AO36: NIFTY_S2=24520.9 | AP36: NIFTY_S2=24669.45 | AQ36: NIFTY_S2=24780.35 | AR36: NIFTY_S2=24853.97 | AS36: NIFTY_S2=24897.15 | AT36: NIFTY_S2=24995.75 | AU36: NIFTY_S2=24995.75 | AV36: NIFTY_S2=24999.32 | AW36: NIFTY_S2=25246.2 | AX36: NIFTY_S2=25281.55 | AY36: NIFTY_S2=25204.9 | AZ36: NIFTY_S2=25047.7 | BA36: NIFTY_S2=24994.75 | BB36: NIFTY_S2=24955.65 | BC36: NIFTY_S2=24739.55 | BD36: NIFTY_S2 = 24478.45 | BE36: NIFTY_S2 = 24492.35 | BF36: NIFTY_S2 = 24499.45 | BG36: NIFTY_S2 = 24508.05 | BH36: NIFTY_S2 = 24691.6 | BI36: NIFTY_S2 = 24804.1 | BJ36: NIFTY_S2 = 24990.55 | BK36: NIFTY_S2 = 24898.4 | BL36: NIFTY_S2 = 24960.15 | BM36: NIFTY_S2 = 25083.75 | BN36: NIFTY_S2 = 25100.65 | BO36: NIFTY_S2 = 24922.35 | BP36: NIFTY_S2 = 25076.9 | BQ36: NIFTY_S2 = 25280.65 | BR36: NIFTY_S2 = 25339.75 | BS36: NIFTY_S2 = 25767.7 | BT36: NIFTY_S2 = 25710.95 | BU36: NIFTY_S2 = 25593.2 | BV36: NIFTY_S2 = 25754.05 | BW36: NIFTY_S2 = 25754.05 | BX36: NIFTY_S2 = 25697.65 | BY36: NIFTY_S2 = 25731.6 | BZ36: NIFTY_S2 = 25553.15 | CA36: NIFTY_S2 = 25579.7 | CB36: NIFTY_S2 = 25445.5 | CC36: NIFTY_S2 = 25372.55 | CD36: NIFTY_S2 = 25221.2 | CE36: NIFTY_S2 = 25221.2 | CF36: NIFTY_S2 = 25353.45 | CG36: NIFTY_S2 = 25710.45 | CH36: NIFTY_S2 = 25697.1 | CI36: NIFTY_S2 = 25664.3 | CJ36: NIFTY_S2 = 25863.5 | CK36: NIFTY_S2 = 25785.45 | CL36: NIFTY_S2 = 25776.05 | CM36: NIFTY_S2 = 25983.9 | CN36: NIFTY_S2 = 25972.85 | CO36: NIFTY_S2 = 25774.15 | CP36: NIFTY_S2 = 25749.85 | CQ36: NIFTY_S2 = 25715.6 | CR36: NIFTY_S2 = 26054.1 | CS36: NIFTY_S2 = 26110.35 | CT36: NIFTY_S2 = 26007 | CU36: NIFTY_S2 = 25904.8 | CV36: NIFTY_S2 = 25805.7 | CW36: NIFTY_S2 = 25864.35 | CX36: NIFTY_S2 = 25907.55 | CY36: NIFTY_S2 = 25724.05 | CZ36: NIFTY_S2 = 25634.8 | DA36: NIFTY_S2 = 25600.3 | DB36: NIFTY_S2 = 25608.65 | DC36: NIFTY_S2 = 25895.2 | DD36: NIFTY_S2 = 25850.65 | DE36: NIFTY_S2 = 25745.35 | DF36: NIFTY_S2 = 25680.55 | DG36: NIFTY_S2 = 25638.7 | DH36: NIFTY_S2 = 25833.85 | DI36: NIFTY_S2 = 26000.75 | DJ36: NIFTY_S2 = 26062.1 | DK36: NIFTY_S2 = 26053.75 | DL36: NIFTY_S2 = 25929.45 | DM36: NIFTY_S2 = 25803.25 | DN36: NIFTY_S2 = 25832.45 | DO36: NIFTY_S2 = 25876.55 | DP36: NIFTY_S2 = 26068.35 | DQ36: NIFTY_S2 = 26040.7 | DR36: NIFTY_S2 = 26114.7 | DS36: NIFTY_S2 = 26043.25 | DT36: NIFTY_S2 = 26012.7 | DU36: NIFTY_S2 = 25681.4 | DV36: NIFTY_S2 = 25431.35 | DW36: NIFTY_S2 = 25352 | DX36: NIFTY_S2 = 25448.65 | DZ36: NIFTY_S2 = 25532.3 | EA36: NIFTY_S2 = 25532.3 | EB36: NIFTY_S2 = 24915.95 | EC36: NIFTY_S2 = 24744.95 | ED36: NIFTY_S2 = 25030.8 | EE36: NIFTY_S2 = 24818 | EF36: NIFTY_S2 = 24804.1 | EG36: NIFTY_S2 = 25116.4 | EH36: NIFTY_S2 = 25047.25 | EI36: NIFTY_S2 = 25047.25 | EJ36: NIFTY_S2 = 24076.9 | EK36: NIFTY_S2 = 24076.9 | EL36: NIFTY_S2 = 24529.95 | EM36: NIFTY_S2 = 25203.45 | EN36: NIFTY_S2 = 25464.9 | EO36: NIFTY_S2 = 25481.85 | EP36: NIFTY_S2 = 25417.8 | EQ36: NIFTY_S2 = 25715.45 | ER36: NIFTY_S2 = 25812.7 | ES36: NIFTY_S2 = 25844.75 | ET36: NIFTY_S2 = 25667.8 | EU36: NIFTY_S2 = 25329.2 | EV36: NIFTY_S2 = 25259.85 | EW36: NIFTY_S2 = 25492.6 | EX36: NIFTY_S2 = 25581.3 | EY36: NIFTY_S2 = 25079.6 | EZ36: NIFTY_S2 = 25254.4 | FA36: NIFTY_S2 = 25535.85 | FB36: NIFTY_S2 = 25150.5 | FC36: NIFTY_S2 = 25296.7
A37: NIFTY_S3 | B37: = | C37: 25165.2 | D37: NIFTY_S3=24856.65 | E37: NIFTY_S3=24951 | F37: NIFTY_S3=25002.7 | G37: NIFTY_S3=24924.85 | H37: NIFTY_S3=24650.55 | I37: NIFTY_S3=24715.75 | J37: NIFTY_S3=24857.2 | K37: NIFTY_S3=24977.75 | L37: NIFTY_S3=24744.25 | M37: NIFTY_S3=24554.8 | N37: NIFTY_S3=24346 | O37: NIFTY_S3=24415.55 | P37: NIFTY_S3=24653.55 | Q37: NIFTY_S3=24295.25 | R37: NIFTY_S3=24223.1 | S37: NIFTY_S3=24423.5 | T37: NIFTY_S3=24439.4 | U37: NIFTY_S3=24386.25 | V37: NIFTY_S3=24125.4 | W37: NIFTY_S3=24024.05 | X37: NIFTY_S3=24168 | Y37: NIFTY_S3=24164.2 | Z37: NIFTY_S3=24418.9 | AA37: NIFTY_S3=24517.5 | AB37: NIFTY_S3=24643.4 | AC37: NIFTY_S3=24760.15 | AD37: NIFTY_S3=24798.25 | AE37: NIFTY_S3=24942.45 | AF37: NIFTY_S3=24565.5 | AG37: NIFTY_S3=24773.7 | AH37: NIFTY_S3=24397.85 | AI37: NIFTY_S3=24199.75 | AJ37: NIFTY_S3=24195.8 | AK37: NIFTY_S3=24290.4 | AL37: NIFTY_S3=24248.85 | AM37: NIFTY_S3=24382.65 | AN37: NIFTY_S3=24362.2 | AO37: NIFTY_S3=24420.2 | AP37: NIFTY_S3=24587.35 | AQ37: NIFTY_S3=24746.65 | AR37: NIFTY_S3=24792.9 | AS37: NIFTY_S3=24854.2 | AT37: NIFTY_S3=24953.5 | AU37: NIFTY_S3=24942.8 | AV37: NIFTY_S3=24928.3 | AW37: NIFTY_S3=25217.1 | AX37: NIFTY_S3=25233.4 | AY37: NIFTY_S3=25123.55 | AZ37: NIFTY_S3=24944.4 | BA37: NIFTY_S3=24904.9 | BB37: NIFTY_S3=24883.9 | BC37: NIFTY_S3=24600.8 | BD37: NIFTY_S3 = 24327.4 | BE37: NIFTY_S3 = 24378.55 | BF37: NIFTY_S3 = 24411.15 | BG37: NIFTY_S3 = 24410.2 | BH37: NIFTY_S3 = 24635.7 | BI37: NIFTY_S3 = 24726.6 | BJ37: NIFTY_S3 = 24904.85 | BK37: NIFTY_S3 = 24788.25 | BL37: NIFTY_S3 = 24896.05 | BM37: NIFTY_S3 = 25010.65 | BN37: NIFTY_S3 = 25049 | BO37: NIFTY_S3 = 24784.1 | BP37: NIFTY_S3 = 24994.4 | BQ37: NIFTY_S3 = 25184.4 | BR37: NIFTY_S3 = 25278.9 | BS37: NIFTY_S3 = 25709.6 | BT37: NIFTY_S3 = 25559.4 | BU37: NIFTY_S3 = 25468.25 | BV37: NIFTY_S3 = 25681.1 | BW37: NIFTY_S3 = 25681.1 | BX37: NIFTY_S3 = 25585.3 | BY37: NIFTY_S3 = 25617.9 | BZ37: NIFTY_S3 = 25395.05 | CA37: NIFTY_S3 = 25513.95 | CB37: NIFTY_S3 = 25312.55 | CC37: NIFTY_S3 = 25253.5 | CD37: NIFTY_S3 = 25123.95 | CE37: NIFTY_S3 = 25123.95 | CF37: NIFTY_S3 = 25257.65 | CG37: NIFTY_S3 = 25639.7 | CH37: NIFTY_S3 = 25585.85 | CI37: NIFTY_S3 = 25587.75 | CJ37: NIFTY_S3 = 25820.6 | CK37: NIFTY_S3 = 25694.4 | CL37: NIFTY_S3 = 25695.9 | CM37: NIFTY_S3 = 25904.55 | CN37: NIFTY_S3 = 25893.5 | CO37: NIFTY_S3 = 25636.2 | CP37: NIFTY_S3 = 25642.25 | CQ37: NIFTY_S3 = 25588.25 | CR37: NIFTY_S3 = 25966.25 | CS37: NIFTY_S3 = 26048.3 | CT37: NIFTY_S3 = 25889.75 | CU37: NIFTY_S3 = 25811.75 | CV37: NIFTY_S3 = 25720.4 | CW37: NIFTY_S3 = 25789.75 | CX37: NIFTY_S3 = 25829.75 | CY37: NIFTY_S3 = 25555.85 | CZ37: NIFTY_S3 = 25541.55 | DA37: NIFTY_S3 = 25466.05 | DB37: NIFTY_S3 = 25524.05 | DC37: NIFTY_S3 = 25851.9 | DD37: NIFTY_S3 = 25796.6 | DE37: NIFTY_S3 = 25656.3 | DF37: NIFTY_S3 = 25590.75 | DG37: NIFTY_S3 = 25551.05 | DH37: NIFTY_S3 = 25787.2 | DI37: NIFTY_S3 = 25953.65 | DJ37: NIFTY_S3 = 26005.1 | DK37: NIFTY_S3 = 25984.55 | DL37: NIFTY_S3 = 25850.25 | DM37: NIFTY_S3 = 25686.15 | DN37: NIFTY_S3 = 25786.9 | DO37: NIFTY_S3 = 25784.15 | DP37: NIFTY_S3 = 26023.3 | DQ37: NIFTY_S3 = 25963.05 | DR37: NIFTY_S3 = 26019.35 | DS37: NIFTY_S3 = 25961.8 | DT37: NIFTY_S3 = 25957.45 | DU37: NIFTY_S3 = 25504.4 | DV37: NIFTY_S3 = 25239.75 | DW37: NIFTY_S3 = 25231.65 | DX37: NIFTY_S3 = 25293.95 | DZ37: NIFTY_S3 = 25402.25 | EA37: NIFTY_S3 = 25402.25 | EB37: NIFTY_S3 = 24660.6 | EC37: NIFTY_S3 = 24570.05 | ED37: NIFTY_S3 = 24893.1 | EE37: NIFTY_S3 = 24610.65 | EF37: NIFTY_S3 = 24675.65 | EG37: NIFTY_S3 = 25045.1 | EH37: NIFTY_S3 = 24934.75 | EI37: NIFTY_S3 = 24934.75 | EJ37: NIFTY_S3 = 23582 | EK37: NIFTY_S3 = 23582 | EL37: NIFTY_S3 = 24380.45 | EM37: NIFTY_S3 = 24765.6 | EN37: NIFTY_S3 = 25365.85 | EO37: NIFTY_S3 = 25384.1 | EP37: NIFTY_S3 = 25343.7 | EQ37: NIFTY_S3 = 25650.05 | ER37: NIFTY_S3 = 25754.9 | ES37: NIFTY_S3 = 25789.7 | ET37: NIFTY_S3 = 25583.2 | EU37: NIFTY_S3 = 25214.1 | EV37: NIFTY_S3 = 25147 | EW37: NIFTY_S3 = 25414.9 | EX37: NIFTY_S3 = 25517.4 | EY37: NIFTY_S3 = 24770.4 | EZ37: NIFTY_S3 = 25129 | FA37: NIFTY_S3 = 25462.3 | FB37: NIFTY_S3 = 24973.35 | FC37: NIFTY_S3 = 25165.2
... A39: NIFTY_S5 | B39: = | C39: 24902.2 | D39: NIFTY_S5=24711.35 | E39: NIFTY_S5=24813.6 | F39: NIFTY_S5=24884.4 | G39: NIFTY_S5=24748.6 | H39: NIFTY_S5=24382.45 | I39: NIFTY_S5=24549.25 | J39: NIFTY_S5=24678.8 | K39: NIFTY_S5=24870.05 | L39: NIFTY_S5=24469.75 | M39: NIFTY_S5=24303.2 | N39: NIFTY_S5=24045.4 | O39: NIFTY_S5=24232.4 | P39: NIFTY_S5=24535.15 | Q39: NIFTY_S5=23955.45 | R39: NIFTY_S5=23911.2 | S39: NIFTY_S5=24293 | T39: NIFTY_S5=24288.5 | U39: NIFTY_S5=24233.35 | V39: NIFTY_S5=23906.7 | W39: NIFTY_S5=23710.55 | X39: NIFTY_S5=23988.5 | Y39: NIFTY_S5=23862.8 | Z39: NIFTY_S5=24302.6 | AA39: NIFTY_S5=24438.1 | AB39: NIFTY_S5=24433.9 | AC39: NIFTY_S5=24646.35 | AD39: NIFTY_S5=24666.85 | AE39: NIFTY_S5=24830.05 | AF39: NIFTY_S5=24271.9 | AG39: NIFTY_S5=24653 | AH39: NIFTY_S5=24106.05 | AI39: NIFTY_S5=23917.85 | AJ39: NIFTY_S5=23956.9 | AK39: NIFTY_S5=24148.1 | AL39: NIFTY_S5=23975.35 | AM39: NIFTY_S5=24232.05 | AN39: NIFTY_S5=24016.2 | AO39: NIFTY_S5=24218.8 | AP39: NIFTY_S5=24423.15 | AQ39: NIFTY_S5=24679.35 | AR39: NIFTY_S5=24670.7 | AS39: NIFTY_S5=24768.2 | AT39: NIFTY_S5=24868.9 | AU39: NIFTY_S5=24836.8 | AV39: NIFTY_S5=24786.1 | AW39: NIFTY_S5=25158.8 | AX39: NIFTY_S5=25137 | AY39: NIFTY_S5=24960.75 | AZ39: NIFTY_S5=24737.7 | BA39: NIFTY_S5=24725.1 | BB39: NIFTY_S5=24740.3 | BC39: NIFTY_S5=24323.3 | BD39: NIFTY_S5 = 24025.4 | BE39: NIFTY_S5 = 24150.85 | BF39: NIFTY_S5 = 24234.65 | BG39: NIFTY_S5 = 24214.4 | BH39: NIFTY_S5 = 24523.8 | BI39: NIFTY_S5 = 24571.5 | BJ39: NIFTY_S5 = 24733.35 | BK39: NIFTY_S5 = 24568.05 | BL39: NIFTY_S5 = 24767.75 | BM39: NIFTY_S5 = 24864.45 | BN39: NIFTY_S5 = 24945.7 | BO39: NIFTY_S5 = 24507.7 | BP39: NIFTY_S5 = 24829.5 | BQ39: NIFTY_S5 = 24992 | BR39: NIFTY_S5 = 25049.2 | BS39: NIFTY_S5 = 25593.4 | BT39: NIFTY_S5 = 25256.4 | BU39: NIFTY_S5 = 25218.25 | BV39: NIFTY_S5 = 25535.2 | BW39: NIFTY_S5 = 25535.2 | BX39: NIFTY_S5 = 25360.5 | BY39: NIFTY_S5 = 25390.6 | BZ39: NIFTY_S5 = 25078.95 | CA39: NIFTY_S5 = 25382.35 | CB39: NIFTY_S5 = 25046.75 | CC39: NIFTY_S5 = 25015.5 | CD39: NIFTY_S5 = 24929.45 | CE39: NIFTY_S5 = 24929.45 | CF39: NIFTY_S5 = 25066.05 | CG39: NIFTY_S5 = 25498.3 | CH39: NIFTY_S5 = 25363.25 | CI39: NIFTY_S5 = 25434.75 | CJ39: NIFTY_S5 = 25734.9 | CK39: NIFTY_S5 = 25512.3 | CL39: NIFTY_S5 = 25535.6 | CM39: NIFTY_S5 = 25745.95 | CN39: NIFTY_S5 = 25734.8 | CO39: NIFTY_S5 = 25360.2 | CP39: NIFTY_S5 = 25426.95 | CQ39: NIFTY_S5 = 25333.55 | CR39: NIFTY_S5 = 25790.65 | CS39: NIFTY_S5 = 25924.2 | CT39: NIFTY_S5 = 25655.35 | CU39: NIFTY_S5 = 25625.65 | CV39: NIFTY_S5 = 25549.8 | CW39: NIFTY_S5 = 25640.55 | CX39: NIFTY_S5 = 25674.15 | CY39: NIFTY_S5 = 25219.45 | CZ39: NIFTY_S5 = 25355.15 | DA39: NIFTY_S5 = 25197.55 | DB39: NIFTY_S5 = 25354.85 | DC39: NIFTY_S5 = 25765.4 | DD39: NIFTY_S5 = 25688.4 | DE39: NIFTY_S5 = 25478.3 | DF39: NIFTY_S5 = 25411.15 | DG39: NIFTY_S5 = 25375.85 | DH39: NIFTY_S5 = 25694 | DI39: NIFTY_S5 = 25859.55 | DJ39: NIFTY_S5 = 25891.2 | DK39: NIFTY_S5 = 25846.05 | DL39: NIFTY_S5 = 25691.95 | DM39: NIFTY_S5 = 25452.05 | DN39: NIFTY_S5 = 25695.8 | DO39: NIFTY_S5 = 25599.25 | DP39: NIFTY_S5 = 25933.2 | DQ39: NIFTY_S5 = 25807.65 | DR39: NIFTY_S5 = 25828.65 | DS39: NIFTY_S5 = 25798.8 | DT39: NIFTY_S5 = 25847.05 | DU39: NIFTY_S5 = 25150.3 | DV39: NIFTY_S5 = 24856.45 | DW39: NIFTY_S5 = 24989.85 | DX39: NIFTY_S5 = 24984.65 | DZ39: NIFTY_S5 = 25142.05 | EA39: NIFTY_S5 = 25142.05 | EB39: NIFTY_S5 = 24149.8 | EC39: NIFTY_S5 = 24220.35 | ED39: NIFTY_S5 = 24617.7 | EE39: NIFTY_S5 = 24196.05 | EF39: NIFTY_S5 = 24418.75 | EG39: NIFTY_S5 = 24902.6 | EH39: NIFTY_S5 = 24709.65 | EI39: NIFTY_S5 = 24709.65 | EJ39: NIFTY_S5 = 22592.3 | EK39: NIFTY_S5 = 22592.3 | EL39: NIFTY_S5 = 24081.55 | EM39: NIFTY_S5 = 23889.9 | EN39: NIFTY_S5 = 25167.75 | EO39: NIFTY_S5 = 25188.85 | EP39: NIFTY_S5 = 25195.5 | EQ39: NIFTY_S5 = 25519.15 | ER39: NIFTY_S5 = 25639.4 | ES39: NIFTY_S5 = 25679.6 | ET39: NIFTY_S5 = 25414 | EU39: NIFTY_S5 = 24983.9 | EV39: NIFTY_S5 = 24921.3 | EW39: NIFTY_S5 = 25259.5 | EX39: NIFTY_S5 = 25389.7 | EY39: NIFTY_S5 = 24152.1 | EZ39: NIFTY_S5 = 24878.3 | FA39: NIFTY_S5 = 25315.3 | FB39: NIFTY_S5 = 24619.15 | FC39: NIFTY_S5 = 24902.2
A41: OBSERVATION
DC42: Observation_text = "Gussa aay ki mujhe sl lagan kun nahi aaata 😭😭 | DD42: Observation_text = " 👍Good👍 | DE42: Observation_text = " aaj mai record nahi karta, par kiya, 💕💕continutiy bani rahe | DF42: bservation_text = "eakdum tadap ke reh gaye, 6 candle no stop red | DG42: Observation_text ="👍Good👍 | DI42: Observation_text ="
DC43: \n yahan pe mre favour me nifty me 38 point gaya | DD43: \n proper risk mgmt follow kar raha tha ki sl kaha aur kitna bada hoga!! | DE43: \n galti kari thi HH pe entry le li thi,👿👿 | DF43: \n ==== Way forward ====== | DG43: \n ==== Dec 19 ====== | DI43: \n webhook url thoda samjh aaay
DC44: \n par mai index me 23 point lena cah raha tha to usko miss kar diya | DD44: \n 🎯aaj bahut acche se trail kiya tha!! | DE44: \n par waqt rehte dimag me aa gaya tha, | DF44: \n 💰💰 ==== Trade ===== 1 | DG44: \n jaldi se kud kar le liya tha to laga har baar kaam karega 😒😒😥😭 | DI44: \n bas secreat key daalan hoga
DC45: \n sl ka aaj hi concept clear karne ke liye mood khrab hua tha" | DD45: \n | DE45: \n plus hammer ke signal ne bachaliya tha 😪😪 | DF45: \n entry ke baad 6 candle ne jhanjhana diya | DG45: \n aaj ke din mane gap filter banaya, ki shift to higer timeframe | DI45: \n dropdown 💧to select ATM0,1,2
DD46: \n pehli candle , PDC ke neeche lag raha tha 25904 wale level se uthega | DE46: \n | DF46: \n par ab thoda bahut sL lagana aagaya hai,ki kab nikalna !! | DG46: \n agar candle badi ho to warning!! ⚠️⚠️ | DI46: \n 3exit 🥳3️⃣- premium based , SL and target,index based
DD47: \n mujhe dik raha tha support, | DE47: \n faida ki edit tez karne ka tareeka mil gaya, video marker pe 🎥 | DF47: \n 💰💰 ==== Trade ===== 2 | DG47: \n aur solution mil gaya ki kab kaun sa timeframe choose karen!! | DI47: \n no order palcement if price>150
DD48: \n par bahut strong tha 25904 pe agar wo toda to bahut neeche, | DE48: \n 🎨👓ye bhi samjh aaya ki long ke baad agar short hai to wo exit signal hai, | DF48: \n dimag ne nayi baat aa gayi!!🧠🧠🤯 | DG48: \n ==== Dec 20 Sat ====== | DI48: \n if first trade profit no new trade
DD49: \n | DE49: \n | DF49: \n swing ban chuka tha, major fallke baad | DG49: \n 20 dec ko journal table ban gayi \n mai dekh raha tha ki mai 100 ka premium leta | DI49: \n LLHH, ke pass no TRADE ZONE
DD50: \n 😒 Bad😒 | DE50: \n turant nikalne ka !! | DF50: \n signal ke bina entry le li | DG50: \n aur usme 20 point ke chakkar me rehta | DI50: \n codebase - google doc ➡️to google sheet
DD51: \n | DE51: \n itne major fall ke baad turant kab avoide karen | DF51: \n -840 +2000 net | DG51: \n wo 20% ka target ho jaata
DD52: \n 💰💰 ==== Trade ===== 1 | DE52: \n🧿🚨 ye jahan entyr mili wo pehla profit booking ki jagha | DF52: \n acchi baat apne RR ke liye ruka
DD53: \n wahan pe mai intezaar kar raha ki pura formation ho jaye par tab tak late | DE53: \n fir agar ye breakdown hua to jo ki iska exit hoga, wo entry ki jagha⚠️ | DF53: \n" | DG53: \n dimag me aaya ki 75 ke lot se mujhe 13 pt cahiye,
DD54: \n | DE54: \n | DG54: \n ab mai entry lene ke baad 13 ka bas target rakh dunga
DD55: \n SL bada to mai 1-2 candle ke liye wait, | DE55: \n aaj samjh aaya ki bt waala previous swing pe alert rehta hai!! 🚨⚠️ | DG55: \n premium pe len 100-200 ki range me
DD56: \n tab tak move aadha nikal gaya aur mai trap!! | DE56: \n -378 aur -1031 , net -1410 💸💸💰 | DF56: \n" | DG56: \n
DE57: \n" | DG57: \n dimag me chal raha tha ki ab se sirf nifty pe focus karenge
DD58: \n 💰💰 ==== Trade ===== 2 | DG58: \n to 1 me galat dusre me sahi ke chakkar me chale jaate!!
DD59: \n trade 2 bnf me liya usme usme support pe hammer🔨 | DG59: \n aise agar 1 signal galat hua to dusra sahi hoga par dono me kudne lagte
DD60: \n jis participant ne banaya hoga wo defend karega!!💯 | DG60: \n
DD61: \n wo uske close ka intezaar wo bhi move miss, | DG61: \n ye bhi chal raha tha ki mai window pe bada sa nifty ka chart
DD62: \n to 🧠dimag me banne laga ki wait karne se move chala jaata , | DG62: \n aur uske side me dusra nifty ka hi chart zoom kar ke rakhenge
DD63: \n | DG63: \n journal banane me dikkat aa rahi thi confusing lag raha tha ,
DD64: \n to maine hammer bante hi entry le len ka filter banane ka soocha!! | DG64: \n par hit and try karte karte elegent solution jo sheet aur ,
DD65: \n | DG65: \n pinescript me kaam karega!!
DD66: \n dhayan dena cahiye ki candle 57point ki ⚠️ | DG66: \n mai apne video dekhte hue ye note bhi bana raha tha 👩🏻‍🎓👩🏻‍🎓
DD67: \n aur upar se gapdown, sellers kas kar hawi hain aaj!! | DG67: \n solution mila ki jo entry miss hojaati to kya karen??.. ab kab, max trade me bhada den, to mil sakti hai, next jab aaye gi!!🤖🤖😍😁
DD68: \n 🔥🔥hope duniya ki sabse powerfull feeling!! breakout zone ke neeche to turant kaat denge!!" | DG68: \n foundation of modular code!!
DD69: \n aur upar se gapdown, sellers kas ke hawi hain aaj!! | DG69: \n 😒 Bad😒
DD70: \n 🔥🔥hope duniya ki sabse powerfull feeling!! breakout zone ke neeche to turant kaat denge!!" | DG70: \n 💰💰 ==== Trade ===== 1
DG71: \n 💰💰 ==== Trade ===== 2"

Sheet DHAN TB
B1: Date | C1: Time | D1: Name | E1: Buy/Sell | F1: Order | G1: Exchange | H1: Segment | I1: Quantity/Lot | J1: Trade Price | K1: Trade Value | L1: Status
A2: 1 | B2: 46023 | C2: 0.61834491 | D2: NIFTY 06 JAN 26150 PUT | E2: BUY | F2: INTRADAY | G2: NSE | H2: Derivative | I2: 65 | J2: 69.15 | K2: 4494.75 | L2: Traded
A3: 2 | B3: 46023 | C3: 0.6250463 | D3: NIFTY 06 JAN 26150 PUT | E3: SELL | F3: INTRADAY | G3: NSE | H3: Derivative | I3: 65 | J3: 65.05 | K3: 4228.25 | L3: Traded
A4: 3 | B4: 46023 | C4: 0.63561343 | D4: NIFTY 06 JAN 26150 PUT | E4: BUY | F4: MARGIN | G4: NSE | H4: Derivative | I4: 65 | J4: 71.6 | K4: 4654 | L4: Traded
A5: 4 | B5: 46023 | C5: 0.63710648 | D5: NIFTY 06 JAN 26150 PUT | E5: SELL | F5: MARGIN | G5: NSE | H5: Derivative | I5: 65 | J5: 71.45 | K5: 4644.25 | L5: Traded
A6: 5 | B6: 46024 | C6: 0.3868287 | D6: NIFTY 06 JAN 26200 PUT | E6: BUY | F6: INTRADAY | G6: NSE | H6: Derivative | I6: 65 | J6: 71.75 | K6: 4663.75 | L6: Traded
A7: 6 | B7: 46024 | C7: 0.3909838 | D7: NIFTY 06 JAN 26200 PUT | E7: SELL | F7: INTRADAY | G7: NSE | H7: Derivative | I7: 65 | J7: 65.35 | K7: 4247.75 | L7: Traded
A8: 7 | B8: 46024 | C8: 0.39238426 | D8: NIFTY 06 JAN 26200 CALL | E8: BUY | F8: INTRADAY | G8: NSE | H8: Derivative | I8: 65 | J8: 77.3 | K8: 5024.5 | L8: Traded
A9: 8 | B9: 46024 | C9: 0.40611111 | D9: NIFTY 06 JAN 26200 CALL | E9: SELL | F9: INTRADAY | G9: NSE | H9: Derivative | I9: 65 | J9: 111.6 | K9: 7254 | L9: Traded
A10: 9 | B10: 46024 | C10: 0.45628472 | D10: NIFTY 06 JAN 26250 PUT | E10: BUY | F10: INTRADAY | G10: NSE | H10: Derivative | I10: 65 | J10: 59.75 | K10: 3883.75 | L10: Traded
A11: 10 | B11: 46024 | C11: 0.47503472 | D11: NIFTY 06 JAN 26250 PUT | E11: SELL | F11: INTRADAY | G11: NSE | H11: Derivative | I11: 65 | J11: 55.6 | K11: 3614 | L11: Traded
A12: 11 | B12: 46027 | C12: 0.40003472 | D12: NIFTY 06 JAN 26300 PUT | E12: BUY | F12: INTRADAY | G12: NSE | H12: Derivative | I12: 65 | J12: 71.35 | K12: 4637.75 | L12: Traded
A13: 12 | B13: 46027 | C13: 0.40038194 | D13: NIFTY 06 JAN 26300 PUT | E13: SELL | F13: INTRADAY | G13: NSE | H13: Derivative | I13: 65 | J13: 74.9 | K13: 4868.5 | L13: Traded
... A146: 144 | B146: 46059 | C146: 0.58806713 | D146: NIFTY 10 FEB 25600 CALL | E146: SELL | F146: INTRADAY | G146: NSE | H146: Derivative | I146: 65 | J146: 118.65 | K146: 7712.25 | L146: Traded

Sheet CODEBASE
A1: MainFunction | B1: Date Of Creation | C1: in Detail | D1: Date of Removal | E1: CodeBase
A2: Yahan se Google Doc me log Rakhna shuru | B2: 45973 | C2: No change
A3: Code cleanup | B3: 45978 | C3: Simple clean - Unused toggle off kar diye Show latest Hh/LL ka toggle bana diya Ye confuse karta hai Sirf jab levels pe hi breakout ho to range bane uske liye Require touch to trigger, ki sirf level pe kibina touch kiye bhi shouldRun = (bullishAfterTouch or bearishAfterTouch) and deleteOld and inDateRange and (useTouched ? touched : true)
A4: Reduce Number of Signals | B4: 45978 | C4: if (bullishAfterTouch or bearishAfterTouch) and deleteOld and inDateRange and touched | E4: Add kar diya Aisa karne se signal bahut kam aayenge, frustration hoga ki miss kar rahe, par jo aayenge wo clean honge Aur dono index me kisi me aa sakte
A5: Breakout zone line clr | B5: 45984 | C5: _isBull ? color.new(color.red, 0) : color.new(color.teal, 0) | E5: Breakout zone, ki line red clr ki banei, red candle ke saath
A6: Breakout zone | B6: 45985 | C6: keepOldLines | E6: Keep Old Breakout Lines, toggle Chart pe purani line ko delete nahi karna hai, isse back, issebreakout faliur kun aur kab hota dekhne ko milta hai
A7: Valid harami candle body size | B7: 45985 | C7: Wahi valdi harami candle jo pichli candle ka atleast 50% ho | E7: body50pct = currBody >= prevBody * 0.5
A8: Valid engulding Candle | B8: 45985 | C8: Engulfing tab hi valid hai, jab previous candle body atleast>=1pt | E8: prevBodyMinPoints = input.float(1.0, "Min previous body (points)", step = 0.1) ******** Dec 20 Sat ***************** 0.5 //20 dec
A9: Inverted Hammmer Created | B9: 45985 | C9: GreenHammerCondition = hammerShape and isGreen RedHammerCondition = hammerShape and isRed bullish = (bullishEngulfing or bullishHarami or GreenHammerCondition bearish = (bearishEngulfing or bearishHarami or RedHammerCondition) | E9: Green ke saath Red hammer ko clear define kar diya, isse wo auto exclude ho jaa raha ******** Dec 20 Sat ***************** Min body size 1 hammer aur inverted hammer ka
A10: prevGreen | B10: 45993 | C10: Valid Entry tabhi jab, Previous/breakout ke clr ki candle Aur breakout zone ke neeche price close | E10: prevGreen = lastBullTouch and (close[1] > open[1]) longCondition = lastBullTouch and isGreen and prevGreen and not na(bullLineHigh_price) and (close > bullLineHigh_price)
A11: Finally Long Short Entry Signals | B11: 45993 | C11: Finally Strategy me long short entry Jo tameez se kaam kar rahi!! | E11: if longCondition and tradesToday < maxTradesPerDay and inDateRange and (EntryCandleBodySize <= bodySizeThreshold) and (lineType != "R") and (lineType != "PD_H")
A12: slLevelLong | B12: 45993 | C12: var float slLevelLong = na slLevelLong := math.min(low, low[1]) strategy.exit(id="Exit Long",from_entry="Long",stop=slLevelLong) | E12: Exit jab breakout zone ke neechey price close
A13: maxTradesPerDay | B13: 45993 | C13: maxTradesPerDay = 4 | E13: Max trade 4, excluding entry
A14: Max candle body size size | C14: Max candle size Bnf ki candle max Body size 25 Nifty ka max body size 20 | E14: bodySizeThreshold = 20 bodySizeThreshold = 25
A15: BackTest | B15: 45993 | C15: Nov - Bnf /Nifty | E15: BackTest nifty/BNF Dono ko pure nov ke liye backtest kar liya
A16: requireProximity | B16: 45996 | C16: requireProximity and (not requireProximity or (not na(proximityLongDiff) and proximityLongDiff <= proximityThreshold)) | E16: Valid entry jab, distance between H/L and breakout zone continuation candle is less than specified point <=30 for nifty <=60 or BNF
A17: SL katne ki jagha | B17: 45996 | C17: if (not na(bullLineLow_price) and close < bullLineLow_price and close < open) | E17: SL katne ki jagha Jab price high/Low ke upar close ho jaye with G/R candle
A18: proximity filter BreakoutZOne Distance | B18: 45997 | C18: proximity filter se | E18: breakout zone ke beech ka distance pe label auto script me value sahi
A19: Code cleanup | B19: 46010 | C19: Code cleanup | E19: Bahut acche se coad clean kiya, bahut confidence aa raha tha ki ab mujhe eakdum clear dikh raha kis line se kya ho raha hai!!
A20: Journal Table Bana di | B20: 46011 | C20: Journal Table Bana di | E20: Good bad way forward kar ke likh sakte wo chart pe hi rahe ga, multiple toggle text tool mange nahi karne padenge!!! Sabse mast cheez, excell me save karni ki jagha bhi hai!! Har chart ke saath individual load hhoga
A21: Safty CONDITIONS - ⚠️ Wide GAP - Switch to Higher TimeFrame | B21: 46011 | C21: // Safty CONDITIONS - ⚠️ Wide GAP - Switch to Higher TimeFrame | E21: // ================================================================ // Safty CONDITIONS - 📏 Label Size // ================================================================ // === Label Size Dropdown === SafetySafetylabelSizeInput = input.string( "tiny", title = "Safety Label Size", options = ["tiny", "small", "normal", "large", "huge"], inline = "Safty" ) SafetylabelSize = SafetySafetylabelSizeInput == "tiny" ? size.tiny : SafetySafetylabelSizeInput == "small" ? size.small : SafetySafetylabelSizeInput == "normal" ? size.normal: SafetySafetylabelSizeInput == "large" ? size.large : size.huge // ================================================================ // Safty CONDITIONS - ⚠️ Wide GAP - Switch to Higher TimeFrame // ================================================================ // --- First candle of the day --- isFirstCandle = ta.change(time("D")) // --- Previous day close --- prevDayClose = request.security( syminfo.tickerid, "D", close, lookahead = barmerge.lookahead_on )[1] // --- GAP calculation --- gapPoints = math.abs(open - prevDayClose) // --- First candle range --- firstCandleRange = high - low // --- User toggle --- GapWarning_toggle = true // GapWarning_toggle = input.bool(true, "Gap Warning", inline = "Safty") // --- GAP condition --- gapValid = (isNifty and gapPoints > 80) or (isBankNifty and gapPoints > 150) if timeframe.isminutes and timeframe.multiplier == 2 if isFirstCandle and gapValid and GapWarning_toggle and inDateRange label.new( bar_index, high, "⚠️ Wide GAP\n" + str.tostring(math.round(gapPoints)) + " pts\n" + "Switch to Higher TF", style = label.style_label_down, color = color.yellow, textcolor = color.black, size = size.large )
A22: Saftey 🔴 FIRST CANDLE RANGE HIGHLIGHT | B22: 46011 | C22: 🔴 FIRST CANDLE RANGE HIGHLIGHT | E22: // =========================================================== // Safty CONDITIONS - 🔴 FIRST CANDLE RANGE HIGHLIGHT // =========================================================== firstCandleBigRange = isFirstCandle and (firstCandleRange >= 50) // --- Highlight candle --- barcolor( firstCandleBigRange ? color.new(color.orange, 0) : na ) // --- Label for big first candle --- if timeframe.isminutes and timeframe.multiplier == 2 if firstCandleBigRange and GapWarning_toggle and inDateRange label.new( bar_index, high, "🔥 Big First Candle\n" + str.tostring(math.round(firstCandleRange)) + " pts", style = label.style_label_down, color = color.aqua, textcolor = color.white, size = size.large )
A23: Daily exponential moving average | B23: 46011 | C23: Daily exponential moving average | E23: //============================ // DEMA //============================ showDEMA_toggle = input.bool(true, "Show DEMA") length = 100 // length = input.int(100, minval=1) // src = input(close, title="Source") src = close e1 = ta.ema(src, length) e2 = ta.ema(e1, length) dema = 2 * e1 - e2 plot( (showDEMA_toggle and inDateRange) ? dema : na, // 👈 toggle logic title = "DEMA (Step)", color = color.black, style = plot.style_stepline, linewidth = 3 )
A24: Zone Width Calculation | B24: 46011 | C24: SAfty CONDITIONS - 2 // 🔴 Zone Width Calculation | D24: 46014 | E24: var float zoneWidth = na if not na(zone_Upper_line_price) and not na(zone_Lower_line_price) zoneWidth := math.abs(zone_Upper_line_price - zone_Lower_line_price) zoneLimit = timeframe.isminutes and timeframe.multiplier == 2 ? (isBankNifty ? 30 : 25) : timeframe.isminutes and timeframe.multiplier == 3 ? (isBankNifty ? 60 : 50) : (isBankNifty ? 30 : 25) // default safety zoneTooWide = not na(zoneWidth) and zoneWidth > zoneLimit ********* 23/12/2025 ************
A25: Zone Too Wide | B25: 46011 | C25: SAfty CONDITIONS - 4 // ⛔ Zone Too Wide | E25: zoneLimit = timeframe.isminutes and timeframe.multiplier == 2 ? 25 : timeframe.isminutes and timeframe.multiplier == 3 ? 50 : 25 // default safety zoneTooWide = not na(zoneWidth) and zoneWidth > zoneLimit ********* 23/12/2025 ************
A26: trackedHigh vs zone_Upper_line (too close) | B26: 46011 | C26: SAfty CONDITIONS - 5.1 // 🔺 Safety: trackedHigh vs zone_Upper_line (too close) // Long entry blockd | E26: // ========================= // // // SAfty CONDITIONS - 5.1 // 🔺 Safety: trackedHigh vs zone_Upper_line (too close) // Long entry block // ========================= var float lastTrackedHigh = na var float lastZoneHigh = na var bool hhTooCloseShown = false // store last valid values if not na(trackedHigh) lastTrackedHigh := trackedHigh if not na(zone_Upper_line_price) lastZoneHigh := zone_Upper_line_price // diff calculation var float trackedHighZoneDiff = na if not na(lastTrackedHigh) and not na(lastZoneHigh) trackedHighZoneDiff := math.abs(lastTrackedHigh - lastZoneHigh) // block condition trackedHighTooClose = not na(trackedHighZoneDiff) and trackedHighZoneDiff < 30 // show label only once per zone ShortCloseText = "⛔ HH too close" + "\nDiff: " + str.tostring(trackedHighZoneDiff) + "\nYahan Long mat karna !!" + "\nShort ke liye sooch sakte" if trackedHighTooClose and not hhTooCloseShown label.new( bar_index, lastTrackedHigh, ShortCloseText, style = label.style_label_down, color = color.red, textcolor = color.white, size = size.small ) hhTooCloseShown := true /// RESET LOGIC (VERY IMPORTANT – same as LL) // ina ka lable spam ko rokne ke liye if (Bearish_Candle_exitingZone or Bullish_Candle_exitingZone) and inDateRange llTooCloseShown := false hhTooCloseShown := false
A27: Safty CONDITIONS - 📏 LL no TradeZone | B27: 46014 | C27: -LL line pe box banata upper aur lower bound pe -uske andar no entry | E27: // =========================================================== // Safty CONDITIONS - 📏 LL no TradeZone // ============================================================= var float lastTrackedLow = na var float lastZoneLow = na var bool llTooCloseShown = false if not na(trackedLow) lastTrackedLow := trackedLow if not na(zone_Lower_line_price) lastZoneLow := zone_Lower_line_price var float trackedLowZoneDiff = na if not na(lastTrackedLow) and not na(lastZoneLow) trackedLowZoneDiff := math.abs(lastTrackedLow - lastZoneLow) upperBandInput = input.int(4, "upperBand_LL", minval=1) LowerBandInput = input.int(4, "LowerBand_LL", minval=1) insideNoTradeZone_LL_toggle = input.bool(true, "insideNoTradeZone_LL_toggle") upperBand = trackedLow + upperBandInput lowerBand = trackedLow - LowerBandInput // STEP 1: Locked values var float lockedLow = na var float lockedUpperBand = na var float lockedLowerBand = na // STEP 2: Lock once if not na(trackedLow) and na(lockedLow) lockedLow := trackedLow lockedUpperBand := trackedLow + upperBandInput lockedLowerBand := trackedLow - LowerBandInput // STEP 3: No-trade zone insideNoTradeZone_LL = not na(lockedLow) and insideNoTradeZone_LL_toggle and close <= lockedUpperBand and close >= lockedLowerBand // STEP 4: Reset ONLY on fresh entry enteredTrade = strategy.position_size != 0 and strategy.position_size[1] == 0 if enteredTrade lockedLow := na lockedUpperBand := na lockedLowerBand := na var box upperZoneBox = na var box lowerZoneBox = na if not na(trackedLow) and inDateRange // delete old boxes if not na(upperZoneBox) box.delete(upperZoneBox) if not na(lowerZoneBox) box.delete(lowerZoneBox) // 🔴 Upper shaded zone (LL → upperBand) upperZoneBox := box.new( left = bar_index - 10, right = bar_index, top = upperBand, bottom = trackedLow, bgcolor = color.new(color.red, 85), border_color = color.new(color.red, 70) ) // 🔴 Lower shaded zone (lowerBand → LL) lowerZoneBox := box.new( left = bar_index - 10, right = bar_index, top = trackedLow, bottom = lowerBand, bgcolor = color.new(color.red, 88), border_color = color.new(color.red, 75) )
A28: 🌐🕸️🌐🕸️ DHAN WEBHOOK INPUTS | B28: 46014 | C28: // 🌐🕸️🌐🕸️ DHAN WEBHOOK INPUTS secret key indexSymbol - Dropdown Selection Atm Size | E28: // ================================ // 🌐🕸️🌐🕸️ DHAN WEBHOOK INPUTS // ================================ dhanSecret = input.string("zxUSE", "Dhan Secret",group = "🗝️ Order Placement") indexSymbol = input.string( "NSE:BANKNIFTY", title = "Index Symbol", options = ["NSE:NIFTY", "NSE:BANKNIFTY"],group = "🗝️ Order Placement") // ================================ // 🔢 Steps size & ATM // ================================ stepSize = indexSymbol == "NSE:BANKNIFTY" ? 100 : 50 atmStrike = math.round(close / stepSize) * stepSize distanceStep = input.int(0, "Strike Distance (Steps)", options = [0,1,2],group = "🗝️ Order Placement") distanceValue = distanceStep * stepSize ceStrike_calc = atmStrike + distanceValue peStrike_calc = atmStrike - distanceValue // ================================ // ✅🔒 LOCK VARIABLES (MOST IMPORTANT) // ================================ var float lockedCEStrike = na var float lockedPEStrike = na // ✅ STEP 5: STRIKE → STRING (for symbol) ceStrike_str = str.tostring(lockedCEStrike) peStrike_str = str.tostring(lockedPEStrike) // Use calculated strike when not locked ceStrike_display = not na(lockedCEStrike) ? lockedCEStrike : ceStrike_calc peStrike_display = not na(lockedPEStrike) ? lockedPEStrike : peStrike_calc // ================================ // ExpiryDate 📅 // ================================ // expiryDate = input.string("251230", "Expiry Date",group = "🗝️ Order Placement") // YYYY-MM-DD niftyExpiry = input.string( "251223", title = "Expiry (YYMMDD) NIFTY ", options = [ "251223", // 23 Dec "251230", // 30 Dec "260106", // 06 Jan "260113", // 13 Jan "260120" // 20 Jan ], group = "🗝️ Order Placement", inline = "expiry" ) bnfExpiry = input.string( "251230", title = "BANKNIFTY", options = [ "251230", // 30 Dec "260127" // 27 Jan ], group = "🗝️ Order Placement", inline = "expiry" ) expiryDate = indexSymbol == "NSE:NIFTY" ? niftyExpiry : indexSymbol == "NSE:BANKNIFTY" ? bnfExpiry : na // 🔹 symbol (sirf jab lockedStrike valid ho) ceSymbol = not na(lockedCEStrike) ? indexSymbol + expiryDate + "C" + str.tostring(lockedCEStrike) : na peSymbol = not na(lockedPEStrike) ? indexSymbol + expiryDate + "P" + str.tostring(lockedPEStrike) : na maxPremium = input.float(150, "Max Option Premium") cePrice = not na(ceSymbol) ? request.security(ceSymbol, timeframe.period, close) : na pePrice = not na(peSymbol) ? request.security(peSymbol, timeframe.period, close) : na ceValid = not na(cePrice) and cePrice <= maxPremium peValid = not na(pePrice) and pePrice <= maxPremium quantity = input.string("1", "Quantity",group = "🗝️ Order Placement") exchange = "NSE" productType = "I" instrument = "OPT" long_Entry_msg = not na(lockedCEStrike) ? ( '{' + '"secret":"' + dhanSecret + '",' + '"alertType":"multi_leg_order",' + '"order_legs":[{' + '"transactionType":"B",' + '"orderType":"MKT",' + '"quantity":"' + quantity + '",' + '"exchange":"' + exchange + '",' + '"symbol":"' + indexSymbol + '",' + '"instrument":"' + instrument + '",' + '"productType":"' + productType + '",' + '"sort_order":"1",' + '"price":"0",' + '"option_type":"CE",' + '"strike_price":"' + str.tostring(lockedCEStrike) + '",' + '"expiry_date":"' + expiryDate + '"' + '}]' + '}'): na Long_exit_msg = not na(lockedCEStrike) ?( '{' + '"secret":"' + dhanSecret + '",' + '"alertType":"multi_leg_order",' + '"order_legs":[{' + '"transactionType":"S",' + '"orderType":"MKT",' + '"quantity":"' + quantity + '",' + '"exchange":"' + exchange + '",' + '"symbol":"' + indexSymbol + '",' + '"instrument":"' + instrument + '",' + '"productType":"' + productType + '",' + '"sort_order":"1",' + '"price":"0",' + '"option_type":"CE",' + '"strike_price":"' + str.tostring(lockedCEStrike) + '",' + '"expiry_date":"' + expiryDate + '"' + '}]' + '}'): na short_Entry_msg = not na(lockedPEStrike) ?( '{' + '"secret":"' + dhanSecret + '",' + '"alertType":"multi_leg_order",' + '"order_legs":[{' + '"transactionType":"B",' + '"orderType":"MKT",' + '"quantity":"' + quantity + '",' + '"exchange":"' + exchange + '",' + '"symbol":"' + indexSymbol + '",' + '"instrument":"' + instrument + '",' + '"productType":"' + productType + '",' + '"sort_order":"1",' + '"price":"0",' + '"option_type":"PE",' + '"strike_price":"' + str.tostring(lockedPEStrike) + '",' + '"expiry_date":"' + expiryDate + '"' + '}]' + '}'): na short_exit_msg = not na(lockedPEStrike) ?( '{' + '"secret":"' + dhanSecret + '",' + '"alertType":"multi_leg_order",' + '"order_legs":[{' + '"transactionType":"S",' + '"orderType":"MKT",' + '"quantity":"' + quantity + '",' + '"exchange":"' + exchange + '",' + '"symbol":"' + indexSymbol + '",' + '"instrument":"' + instrument + '",' + '"productType":"' + productType + '",' + '"sort_order":"1",' + '"price":"0",' + '"option_type":"PE",' + '"strike_price":"' + str.tostring(lockedPEStrike) + '",' + '"expiry_date":"' + expiryDate + '"' + '}]' + '}'): na
A29: // 📊 Strike Selection Visual Table Creates sadsa | B29: 46014 | C29: // 📊 Strike Selection Visual Table Creates sadsa | E29: // ================================ // 📊 Strike Selection Visual Table // ================================ var table strikeTable = table.new(position.top_right, 2, 6, border_width = 1) f_expiryLabel(exp) => exp == "251223" ? "23 Dec" : exp == "251230" ? "30 Dec" : exp == "260106" ? "06 Jan" : exp == "260113" ? "13 Jan" : exp == "260120" ? "20 Jan" : exp == "260127" ? "27 Jan" : exp OrderTable_BG_Clr = color.blue // if barstate.islast table.cell(strikeTable, 0, 0, "INDEX", bgcolor=OrderTable_BG_Clr, text_color=color.white) table.cell(strikeTable, 1, 0, indexSymbol) table.cell(strikeTable, 0, 1, "ATM STRIKE", bgcolor=OrderTable_BG_Clr, text_color=color.white) table.cell(strikeTable, 1, 1, str.tostring(atmStrike)) table.cell(strikeTable, 0, 2, "DISTANCE STEP", bgcolor=OrderTable_BG_Clr, text_color=color.white) table.cell(strikeTable, 1, 2, str.tostring(distanceStep)) table.cell(strikeTable, 0, 3, "CE STRIKE", bgcolor=color.new(color.green, 80)) table.cell(strikeTable, 1, 3, str.tostring(ceStrike_display)) table.cell(strikeTable, 0, 4, "PE STRIKE", bgcolor=color.new(color.red, 80)) table.cell(strikeTable, 1, 4, str.tostring(peStrike_display)) table.cell(strikeTable, 0, 5, "EXPIRY", bgcolor=OrderTable_BG_Clr, text_color=color.white) table.cell(strikeTable, 1, 5, f_expiryLabel(expiryDate), text_size = size.large)
A30: PREMIUM BASED TARGET & SL | B30: 46014 | C30: PREMIUM BASED TARGET & SL | E30: // // ====================================================== // // PREMIUM BASED TARGET & SL // // ========================================================= premiumTarget = 10 premiumSL = 10 // ===== Entry Premium Lock (Very Important) ===== // 🔒 PREMIUM SNAPSHOT STORE KARNA (ENTRY PE) var float entryPremium = na if strategy.position_size > 0 and na(entryPremium) entryPremium := cePrice if strategy.position_size < 0 and na(entryPremium) entryPremium := pePrice if strategy.position_size == 0 entryPremium := na premiumPnL = strategy.position_size > 0 ? cePrice - entryPremium : strategy.position_size < 0 ? entryPremium - pePrice : na // ===== P&L ===== longPremiumProfit = not na(entryPremium) ? cePrice - entryPremium : na shortPremiumProfit = not na(entryPremium) ? entryPremium - pePrice : na // ===== Exit Guard ===== // 📌 IMPORTANT NOTES (ignore mat karna) // ⚠️ 1. Premium spikes // Option premium gap karta hai // +10 / −10 exact nahi milega // 👉 slippage accept karna padega // ⚠️ 2. First bar issue // Entry bar pe hi premium move ho sakta hai // 👉 entry ke baad next bar se exit check better barsAfterEntry = ta.barssince(strategy.position_size != 0) allowExit = barsAfterEntry > 0 //👉 allowExit ek SAFETY GATE hai jo bolta “Entry ke same bar me exit mat lene do.” // ===== Exit Logic ===== Prem_base_exitLong = ((longPremiumProfit >= premiumTarget) or (longPremiumProfit <= -premiumSL)) Prem_base_exitShort = ((shortPremiumProfit >= premiumTarget) or (shortPremiumProfit <= -premiumSL)) Long_indexExitCondition = (close_Below_Red_zone and (close < open)) // long Short_indexExitCondition = (close_Above_Red_zone and (close > open)) // short LongExitTrigger = Long_indexExitCondition or Prem_base_exitLong shortExitTrigger = Short_indexExitCondition or Prem_base_exitShort
A31: Google Doc se➡️sheet me moved | B31: 46014
A32: if 1st trade in PROFIT, no further Trader | B32: 46014 | E32: // // ============================================ // Agar pehla trade PROFIT me exit hua // // ============================================ // 🔹 STEP 1: Entry price lock karo (index price) var float entryIndexPrice = na // LONG entry if strategy.position_size > 0 and na(entryIndexPrice) entryIndexPrice := close // SHORT entry if strategy.position_size < 0 and na(entryIndexPrice) entryIndexPrice := close // reset when flat if strategy.position_size == 0 entryIndexPrice := na // 🔹 STEP 2: Day profit lock flag var bool dayProfitLocked = false // day reset if ta.change(time("D")) dayProfitLocked := false // 🔹 STEP 3: PROFIT CLOSE detection (EXIT KE BAAD) // detect exit bar justClosed = strategy.position_size[1] != 0 and strategy.position_size == 0 float entryAtExit = na float exitIndexPrice = na if justClosed exitIndexPrice := close[1] if justClosed entryAtExit := entryIndexPrice[1] // LowerBandInput_HH_HH = input.int(4, "LowerBand_HH", minval=1) FirstTradeProfit_points_Index_Nifty = input.float(10, "FirstTradeProfit_points_Index_Nifty",minval = 0.1) FirstTradeProfit_points_Index_Nifty_toggle = input.bool(true, "FirstTradeProfit_points_Index_Nifty_toggle") if justClosed longProfitClose = strategy.position_size[1] > 0 and FirstTradeProfit_points_Index_Nifty_toggle and exitIndexPrice >= entryIndexPrice[1] + FirstTradeProfit_points_Index_Nifty shortProfitClose = strategy.position_size[1] < 0 and FirstTradeProfit_points_Index_Nifty_toggle and exitIndexPrice <= entryIndexPrice[1] - FirstTradeProfit_points_Index_Nifty if longProfitClose or shortProfitClose dayProfitLocked := true //🔑 Yahin pe lock lagta hai — EXIT KE BAAD if justClosed Loopme DiffPt = math.abs(exitIndexPrice - entryIndexPrice[1]) if justClosed label.new( bar_index, high, "Entry @ " + str.tostring(entryIndexPrice[1]) + "\nExit @ " + str.tostring(exitIndexPrice) + "\nPT = " + str.tostring(DiffPt) + "\nLOCK = " + str.tostring(dayProfitLocked), color = dayProfitLocked ? color.red : color.green, textcolor = color.white, size = size.small ) if justClosed entryIndexPrice := na

Sheet STATEMENT
A2: Yr | B2: Month | C2: Inc | D2: Tax | E2: Net | F2: Inc Month Cumm | G2: Inc LifeTime Cumm | H2: Column 1 | I2: Column 9 | J2: Column 10 | K2: Column 11 | L2: Column 12
A4: 2023 | B4: Sep | C4: -8680 | D4: -6350 | E4: =C4+D4 -> -15030 | F4: =C4+F5 -> -8799.22 | G4: =C4+G5 -> -8799.22
A5: 2023 | B5: Sep | C5: -119.22 | D5: =E5-C5 -> -168.76 | E5: -287.98 | F5: =C5 -> -119.22 | G5: =C5 -> -119.22
A6: 2023 | B6: Oct | C6: -1415.1 | D6: =E6-C6 -> -2198 | E6: -3613.1 | F6: =C6+F4 -> -10214.32 | G6: =C6+G4 -> -10214.32
A7: 2023 | B7: Nov | C7: -5921.2 | D7: =E7-C7 -> -6198.31 | E7: -12119.51 | F7: =C7+F6 -> -16135.52 | G7: =C7+G6 -> -16135.52
A8: 2023 | B8: Dec | C8: -71.25 | D8: =E8-C8 -> -562.28 | E8: -633.53 | F8: =C8+F7 -> -16206.77 | G8: =C8+G7 -> -16206.77
A9: 2023 | B9: ToTal | C9: =SUM(C3:C8) -> -16206.77 | D9: =SUM(D3:D8) -> -15477.35 | E9: =SUM(E3:E8) -> -31684.12
A10: 2024 | B10: Jan | C10: -9517.6 | D10: =E10-C10 -> -12693.08 | E10: -22210.68 | F10: =C10+F9 -> -9517.6 | G10: =C10+G8 -> -25724.37
A11: 2024 | B11: Feb | C11: -7348.15 | D11: =E11-C11 -> -5177.34 | E11: -12525.49 | F11: =C11+F10 -> -16865.75 | G11: =C11+G10 -> -33072.52
A12: 2024 | B12: Mar | C12: - | D12: - | E12: - | F12: - | G12: -
A13: 2024 | B13: Apr | C13: - | D13: - | E13: - | F13: - | G13: -
A14: 2024 | B14: May | C14: - | D14: - | E14: - | F14: - | G14: -
A15: 2024 | B15: Jun | C15: - | D15: - | E15: - | F15: - | G15: -
A16: 2024 | B16: Jul | C16: - | D16: - | E16: - | F16: - | G16: -
A17: 2024 | B17: Aug | C17: - | D17: - | E17: - | F17: - | G17: -
A18: 2024 | B18: Sep | C18: 6.65 | D18: =E18-C18 -> -147.8 | E18: -141.15 | F18: =C18+F11 -> -16859.1 | G18: =C18+G11 -> -33065.87
A19: 2024 | B19: Oct | C19: -6056.23 | D19: =E19-C19 -> -3077.81 | E19: -9134.04 | F19: =C19+F18 -> -22915.33 | G19: =C19+G18 -> -39122.1
A20: 2024 | B20: Nov | C20: -1522 | D20: -8725 | E20: -11925 | F20: =C20+F19 -> -24437.33 | G20: =C20+G19 -> -40644.1
A21: 2024 | B21: Dec | C21: 2633.75 | D21: =E21-C21 -> -2782.14 | E21: -148.39 | F21: - | G21: -
A22: 2024 | B22: ToTal | C22: =sum(C10:C21) -> -21803.58 | D22: =sum(D10:D21) -> -32603.17 | E22: =sum(E10:E21) -> -56084.75
A23: 2025 | B23: Jan | C23: -1922.5 | D23: =(E23-C23) -> -2206.94 | E23: -4129.44 | F23: - | G23: -
A24: 2025 | B24: Feb | C24: -2823.25 | D24: =(E24-C24) -> -1766.67 | E24: -4589.92 | F24: - | G24: -
A25: 2025 | B25: Mar | C25: -29842.75 | D25: -4827.5 | E25: -34670.25 | F25: - | G25: -
A26: 2025 | B26: Apr | C26: -2255 | D26: =E26-C26 -> -271.5 | E26: -2526.5 | F26: - | G26: -
A27: 2025 | B27: May | C27: -8650 | D27: -2710 | E27: -11370
A28: 2025 | B28: Jun | C28: 6590 | D28: -2780 | E28: 3800
A29: 2025 | B29: Jul | C29: 2870 | D29: -4840 | E29: -2090
A30: 2025 | B30: Aug | C30: -2090 | D30: -5500 | E30: -8800
A31: 2025 | B31: Sep | C31: -10877 | D31: -2317.49 | E31: =-D31-C31 -> 13194.49
A32: 2025 | B32: Oct | C32: 832.5 | D32: -2253.85 | E32: -1421.35
A33: 2025 | B33: Nov | C33: -5608 | D33: -3773 | E33: -9381.68
A34: 2025 | B34: Dec | C34: -6178.3 | D34: -3187.23 | E34: -9365.55
A35: 2025 | B35: ToTal | C35: =sum(C23:C34) -> -59954.3 | D35: =sum(D23:D34) -> -36434.18 | E35: =sum(E23:E34) -> -71350.2
A36: NET | B36: ToTal | C36: =C35+C22+C9 -> -97964.65 | D36: =D35+D22+D9 -> -84514.7 | E36: =E35+E22+E9 -> -159119.07
A41: Yr | B41: Month | C41: Inc | D41: Tax | E41: Net | F41: Broker
A42: 2023 | B42: Sep | C42: -119.22 | D42: =E42-C42 -> -168.76 | E42: -287.98 | F42: Dhan
A43: 2023 | B43: Sep | C43: -8680 | D43: -6350 | E43: =C43+D43 -> -15030 | F43: Zerodha
A44: 2023 | B44: ToTal | C44: =SUM(C42:C43) -> -8799.22 | D44: =SUM(D42:D43) -> -6518.76 | E44: =SUM(E42:E43) -> -15317.98
A45: 2024 | B45: Nov | C45: 838.87 | D45: =E45+C45 -> -3913.13 | E45: -4752 | F45: Dhan
A46: 2024 | B46: Nov | C46: -2361 | D46: -4812 | E46: -7173 | F46: BTC
A47: 2024 | B47: ToTal | C47: =SUM(C45:C46) -> -1522.13 | D47: =SUM(D45:D46) -> -8725.13 | E47: =SUM(E45:E46) -> -11925
A48: 2025 | B48: Mar | C48: -4518.75 | D48: =(E48-C48) -> -272 | E48: -4790.75 | F48: DHAN
